Workbook

Sheet Config_Equipamentos
A1: ID | B1: Área | C1: Equipamento | D1: Potência_kW | E1: Qtd_Peq | F1: Qtd_Med | G1: 00h | H1: 01h | I1: 02h | J1: 03h | K1: 04h | L1: 05h | M1: 06h | N1: 07h | O1: 08h | P1: 09h | Q1: 10h | R1: 11h | S1: 12h | T1: 13h | U1: 14h | V1: 15h | W1: 16h | X1: 17h | Y1: 18h | Z1: 19h | AA1: 20h | AB1: 21h | AC1: 22h | AD1: 23h
A2: ESC-01 | B2: Escritório | C2: Iluminação LED | D2: 0.1 | E2: 6 | F2: 10 | G2: 0 | H2: 0 | I2: 0 | J2: 0 | K2: 0 | L2: 0 | M2: 0 | N2: 1 | O2: 1 | P2: 1 | Q2: 1 | R2: 1 | S2: 1 | T2: 1 | U2: 1 | V2: 1 | W2: 1 | X2: 1 | Y2: 0 | Z2: 0 | AA2: 0 | AB2: 0 | AC2: 0 | AD2: 0
A3: ESC-02 | B3: Escritório | C3: Computador/Notebook | D3: 0.15 | E3: 2 | F3: 4 | G3: 0 | H3: 0 | I3: 0 | J3: 0 | K3: 0 | L3: 0 | M3: 0 | N3: 0 | O3: 1 | P3: 1 | Q3: 1 | R3: 1 | S3: 1 | T3: 1 | U3: 1 | V3: 1 | W3: 1 | X3: 0 | Y3: 0 | Z3: 0 | AA3: 0 | AB3: 0 | AC3: 0 | AD3: 0
A4: ESC-03 | B4: Escritório | C4: Impressora | D4: 0.3 | E4: 1 | F4: 1 | G4: 0 | H4: 0 | I4: 0 | J4: 0 | K4: 0 | L4: 0 | M4: 0 | N4: 0 | O4: 0.3 | P4: 0.3 | Q4: 0.3 | R4: 0.3 | S4: 0.3 | T4: 0.3 | U4: 0.3 | V4: 0.3 | W4: 0.3 | X4: 0 | Y4: 0 | Z4: 0 | AA4: 0 | AB4: 0 | AC4: 0 | AD4: 0
A5: ESC-04 | B5: Escritório | C5: Ar-condicionado | D5: 1.2 | E5: 1 | F5: 2 | G5: 0 | H5: 0 | I5: 0 | J5: 0 | K5: 0 | L5: 0 | M5: 0 | N5: 0 | O5: 0 | P5: 0.8 | Q5: 0.8 | R5: 0.8 | S5: 0.8 | T5: 0.8 | U5: 0.8 | V5: 0.8 | W5: 0.8 | X5: 0 | Y5: 0 | Z5: 0 | AA5: 0 | AB5: 0 | AC5: 0 | AD5: 0
A6: ESC-05 | B6: Escritório | C6: Roteador Wi-Fi | D6: 0.02 | E6: 1 | F6: 2 | G6: 1 | H6: 1 | I6: 1 | J6: 1 | K6: 1 | L6: 1 | M6: 1 | N6: 1 | O6: 1 | P6: 1 | Q6: 1 | R6: 1 | S6: 1 | T6: 1 | U6: 1 | V6: 1 | W6: 1 | X6: 1 | Y6: 1 | Z6: 1 | AA6: 1 | AB6: 1 | AC6: 1 | AD6: 1
A7: ESC-06 | B7: Escritório | C7: Carregadores | D7: 0.05 | E7: 2 | F7: 3 | G7: 0 | H7: 0 | I7: 0 | J7: 0 | K7: 0 | L7: 0 | M7: 0 | N7: 0 | O7: 0.5 | P7: 0.5 | Q7: 0.5 | R7: 0.5 | S7: 0.5 | T7: 0.5 | U7: 0.5 | V7: 0.5 | W7: 0.5 | X7: 0 | Y7: 0 | Z7: 0 | AA7: 0 | AB7: 0 | AC7: 0 | AD7: 0
A8: COZ-01 | B8: Cozinha | C8: Geladeira/Freezer | D8: 0.15 | E8: 1 | F8: 2 | G8: 0.4 | H8: 0.4 | I8: 0.4 | J8: 0.4 | K8: 0.4 | L8: 0.4 | M8: 0.4 | N8: 0.4 | O8: 0.4 | P8: 0.4 | Q8: 0.4 | R8: 0.4 | S8: 0.4 | T8: 0.4 | U8: 0.4 | V8: 0.4 | W8: 0.4 | X8: 0.4 | Y8: 0.4 | Z8: 0.4 | AA8: 0.4 | AB8: 0.4 | AC8: 0.4 | AD8: 0.4
A9: COZ-02 | B9: Cozinha | C9: Freezer horizontal | D9: 0.2 | E9: 1 | F9: 1 | G9: 0.35 | H9: 0.35 | I9: 0.35 | J9: 0.35 | K9: 0.35 | L9: 0.35 | M9: 0.35 | N9: 0.35 | O9: 0.35 | P9: 0.35 | Q9: 0.35 | R9: 0.35 | S9: 0.35 | T9: 0.35 | U9: 0.35 | V9: 0.35 | W9: 0.35 | X9: 0.35 | Y9: 0.35 | Z9: 0.35 | AA9: 0.35 | AB9: 0.35 | AC9: 0.35 | AD9: 0.35
A10: COZ-03 | B10: Cozinha | C10: Micro-ondas | D10: 1.2 | E10: 1 | F10: 1 | G10: 0 | H10: 0 | I10: 0 | J10: 0 | K10: 0 | L10: 0 | M10: 0.5 | N10: 0.5 | O10: 0 | P10: 0 | Q10: 0 | R10: 0 | S10: 0.8 | T10: 0.8 | U10: 0 | V10: 0 | W10: 0 | X10: 0.5 | Y10: 0.8 | Z10: 0.8 | AA10: 0 | AB10: 0 | AC10: 0 | AD10: 0
A11: COZ-04 | B11: Cozinha | C11: Cafeteira elétrica | D11: 0.8 | E11: 1 | F11: 1 | G11: 0 | H11: 0 | I11: 0 | J11: 0 | K11: 0 | L11: 0.5 | M11: 0.8 | N11: 0.8 | O11: 0.4 | P11: 0 | Q11: 0 | R11: 0 | S11: 0 | T11: 0 | U11: 0.4 | V11: 0.4 | W11: 0 | X11: 0 | Y11: 0 | Z11: 0 | AA11: 0 | AB11: 0 | AC11: 0 | AD11: 0
A12: COZ-05 | B12: Cozinha | C12: Iluminação LED | D12: 0.1 | E12: 4 | F12: 6 | G12: 0.3 | H12: 0.3 | I12: 0.3 | J12: 0.3 | K12: 0.3 | L12: 0.5 | M12: 0.8 | N12: 0.6 | O12: 0.4 | P12: 0.3 | Q12: 0.3 | R12: 0.5 | S12: 0.8 | T12: 0.5 | U12: 0.3 | V12: 0.3 | W12: 0.3 | X12: 0.5 | Y12: 0.8 | Z12: 0.6 | AA12: 0.4 | AB12: 0.3 | AC12: 0.3 | AD12: 0.3
A13: COZ-06 | B13: Cozinha | C13: Purificador de água | D13: 0.08 | E13: 1 | F13: 1 | G13: 0.3 | H13: 0.3 | I13: 0.3 | J13: 0.3 | K13: 0.3 | L13: 0.3 | M13: 0.3 | N13: 0.3 | O13: 0.3 | P13: 0.3 | Q13: 0.3 | R13: 0.3 | S13: 0.3 | T13: 0.3 | U13: 0.3 | V13: 0.3 | W13: 0.3 | X13: 0.3 | Y13: 0.3 | Z13: 0.3 | AA13: 0.3 | AB13: 0.3 | AC13: 0.3 | AD13: 0.3
... A17: QUA-04 | B17: Quarto | C17: Carregador celular | D17: 0.02 | E17: 3 | F17: 5 | G17: 0.8 | H17: 0.8 | I17: 0.8 | J17: 0.8 | K17: 0.5 | L17: 0.3 | M17: 0 | N17: 0 | O17: 0 | P17: 0 | Q17: 0 | R17: 0 | S17: 0 | T17: 0 | U17: 0 | V17: 0 | W17: 0 | X17: 0 | Y17: 0 | Z17: 0 | AA17: 0.3 | AB17: 0.5 | AC17: 0.8 | AD17: 0.9
A18: IRR-01 | B18: Irrigação/Lavoura | C18: Pivô central | D18: 4 | E18: 1 | F18: 2 | G18: 1 | H18: 1 | I18: 1 | J18: 1 | K18: 1 | L18: 0 | M18: 0 | N18: 0 | O18: 0 | P18: 0 | Q18: 0 | R18: 0 | S18: 0 | T18: 0 | U18: 0 | V18: 0 | W18: 0 | X18: 0 | Y18: 0 | Z18: 0 | AA18: 1 | AB18: 1 | AC18: 1 | AD18: 1 | AE18: Referência: Bomba pivo 3.68 kW planilha modelo_dados Darvin
A19: IRR-02 | B19: Irrigação/Lavoura | C19: Bomba auxiliar | D19: 22 | E19: 0 | F19: 1 | G19: 0.8 | H19: 0.8 | I19: 0 | J19: 0 | K19: 0 | L19: 0 | M19: 0 | N19: 0.8 | O19: 0.8 | P19: 0 | Q19: 0 | R19: 0 | S19: 0 | T19: 0 | U19: 0.8 | V19: 0.8 | W19: 0 | X19: 0 | Y19: 0 | Z19: 0 | AA19: 0.8 | AB19: 0.8 | AC19: 0 | AD19: 0 | AE19: Referência: Bomba captação 22.1 kW Planilha de modelo_dados Darvin
A20: IRR-03 | B20: Irrigação/Lavoura | C20: Secadora/Silo | D20: 2.4 | E20: 0 | F20: 1 | G20: 0.98625557 | H20: 0.98254086 | I20: 0.95839525 | J20: 0.98551263 | K20: 0.95319465 | L20: 0.99145617 | M20: 0.97956909 | N20: 0.96322437 | O20: 0.98774146 | P20: 0.98625557 | Q20: 0.97845468 | R20: 0.96582467 | S20: 0.96210996 | T20: 0.99071322 | U20: 1 | V20: 0.98402675 | W20: 0.9832838 | X20: 0.97771174 | Y20: 0.9910847 | Z20: 0.98922734 | AA20: 0.96508172 | AB20: 0.97399703 | AC20: 0.99294205 | AD20: 0.97622585
A21: IRR-04 | B21: Irrigação/Lavoura | C21: Quadro de automação | D21: 0.2 | E21: 1 | F21: 1 | G21: 1 | H21: 1 | I21: 1 | J21: 1 | K21: 1 | L21: 1 | M21: 1 | N21: 1 | O21: 1 | P21: 1 | Q21: 1 | R21: 1 | S21: 1 | T21: 1 | U21: 1 | V21: 1 | W21: 1 | X21: 1 | Y21: 1 | Z21: 1 | AA21: 1 | AB21: 1 | AC21: 1 | AD21: 1

Sheet Perfil_Area
A1: Perfil de Potência por Carga — DERIVADO dos Equipamentos
A2: Carga | B2: Tipo_Fazenda | C2: 00h_kW | D2: 01h_kW | E2: 02h_kW | F2: 03h_kW | G2: 04h_kW | H2: 05h_kW | I2: 06h_kW | J2: 07h_kW | K2: 08h_kW | L2: 09h_kW | M2: 10h_kW | N2: 11h_kW | O2: 12h_kW | P2: 13h_kW | Q2: 14h_kW | R2: 15h_kW | S2: 16h_kW | T2: 17h_kW | U2: 18h_kW | V2: 19h_kW | W2: 20h_kW | X2: 21h_kW | Y2: 22h_kW | Z2: 23h_kW | AA2: Total_kWh/dia
A3: Escritório | B3: Pequena | C3: =SUMPRODUCT((Config_Equipamentos!$B$2:$B$21="Escritório")*Config_Equipamentos!$D$2:$D$21*Config_Equipamentos!$E$2:$E$21*Config_Equipamentos!$G$2:$G$21) -> 0.02 | D3: =SUMPRODUCT((Config_Equipamentos!$B$2:$B$21="Escritório")*Config_Equipamentos!$D$2:$D$21*Config_Equipamentos!$E$2:$E$21*Config_Equipamentos!$H$2:$H$21) -> 0.02 | E3: =SUMPRODUCT((Config_Equipamentos!$B$2:$B$21="Escritório")*Config_Equipamentos!$D$2:$D$21*Config_Equipamentos!$E$2:$E$21*Config_Equipamentos!$I$2:$I$21) -> 0.02 | F3: =SUMPRODUCT((Config_Equipamentos!$B$2:$B$21="Escritório")*Config_Equipamentos!$D$2:$D$21*Config_Equipamentos!$E$2:$E$21*Config_Equipamentos!$J$2:$J$21) -> 0.02 | G3: =SUMPRODUCT((Config_Equipamentos!$B$2:$B$21="Escritório")*Config_Equipamentos!$D$2:$D$21*Config_Equipamentos!$E$2:$E$21*Config_Equipamentos!$K$2:$K$21) -> 0.02 | H3: =SUMPRODUCT((Config_Equipamentos!$B$2:$B$21="Escritório")*Config_Equipamentos!$D$2:$D$21*Config_Equipamentos!$E$2:$E$21*Config_Equipamentos!$L$2:$L$21) -> 0.02 | I3: =SUMPRODUCT((Config_Equipamentos!$B$2:$B$21="Escritório")*Config_Equipamentos!$D$2:$D$21*Config_Equipamentos!$E$2:$E$21*Config_Equipamentos!$M$2:$M$21) -> 0.02 | J3: =SUMPRODUCT((Config_Equipamentos!$B$2:$B$21="Escritório")*Config_Equipamentos!$D$2:$D$21*Config_Equipamentos!$E$2:$E$21*Config_Equipamentos!$N$2:$N$21) -> 0.62 | K3: =SUMPRODUCT((Config_Equipamentos!$B$2:$B$21="Escritório")*Config_Equipamentos!$D$2:$D$21*Config_Equipamentos!$E$2:$E$21*Config_Equipamentos!$O$2:$O$21) -> 1.06 | L3: =SUMPRODUCT((Config_Equipamentos!$B$2:$B$21="Escritório")*Config_Equipamentos!$D$2:$D$21*Config_Equipamentos!$E$2:$E$21*Config_Equipamentos!$P$2:$P$21) -> 2.02 | M3: =SUMPRODUCT((Config_Equipamentos!$B$2:$B$21="Escritório")*Config_Equipamentos!$D$2:$D$21*Config_Equipamentos!$E$2:$E$21*Config_Equipamentos!$Q$2:$Q$21) -> 2.02 | N3: =SUMPRODUCT((Config_Equipamentos!$B$2:$B$21="Escritório")*Config_Equipamentos!$D$2:$D$21*Config_Equipamentos!$E$2:$E$21*Config_Equipamentos!$R$2:$R$21) -> 2.02 | O3: =SUMPRODUCT((Config_Equipamentos!$B$2:$B$21="Escritório")*Config_Equipamentos!$D$2:$D$21*Config_Equipamentos!$E$2:$E$21*Config_Equipamentos!$S$2:$S$21) -> 2.02 | P3: =SUMPRODUCT((Config_Equipamentos!$B$2:$B$21="Escritório")*Config_Equipamentos!$D$2:$D$21*Config_Equipamentos!$E$2:$E$21*Config_Equipamentos!$T$2:$T$21) -> 2.02 | Q3: =SUMPRODUCT((Config_Equipamentos!$B$2:$B$21="Escritório")*Config_Equipamentos!$D$2:$D$21*Config_Equipamentos!$E$2:$E$21*Config_Equipamentos!$U$2:$U$21) -> 2.02 | R3: =SUMPRODUCT((Config_Equipamentos!$B$2:$B$21="Escritório")*Config_Equipamentos!$D$2:$D$21*Config_Equipamentos!$E$2:$E$21*Config_Equipamentos!$V$2:$V$21) -> 2.02 | S3: =SUMPRODUCT((Config_Equipamentos!$B$2:$B$21="Escritório")*Config_Equipamentos!$D$2:$D$21*Config_Equipamentos!$E$2:$E$21*Config_Equipamentos!$W$2:$W$21) -> 2.02 | T3: =SUMPRODUCT((Config_Equipamentos!$B$2:$B$21="Escritório")*Config_Equipamentos!$D$2:$D$21*Config_Equipamentos!$E$2:$E$21*Config_Equipamentos!$X$2:$X$21) -> 0.62 | U3: =SUMPRODUCT((Config_Equipamentos!$B$2:$B$21="Escritório")*Config_Equipamentos!$D$2:$D$21*Config_Equipamentos!$E$2:$E$21*Config_Equipamentos!$Y$2:$Y$21) -> 0.02 | V3: =SUMPRODUCT((Config_Equipamentos!$B$2:$B$21="Escritório")*Config_Equipamentos!$D$2:$D$21*Config_Equipamentos!$E$2:$E$21*Config_Equipamentos!$Z$2:$Z$21) -> 0.02 | W3: =SUMPRODUCT((Config_Equipamentos!$B$2:$B$21="Escritório")*Config_Equipamentos!$D$2:$D$21*Config_Equipamentos!$E$2:$E$21*Config_Equipamentos!$AA$2:$AA$21) -> 0.02 | X3: =SUMPRODUCT((Config_Equipamentos!$B$2:$B$21="Escritório")*Config_Equipamentos!$D$2:$D$21*Config_Equipamentos!$E$2:$E$21*Config_Equipamentos!$AB$2:$AB$21) -> 0.02 | Y3: =SUMPRODUCT((Config_Equipamentos!$B$2:$B$21="Escritório")*Config_Equipamentos!$D$2:$D$21*Config_Equipamentos!$E$2:$E$21*Config_Equipamentos!$AC$2:$AC$21) -> 0.02 | Z3: =SUMPRODUCT((Config_Equipamentos!$B$2:$B$21="Escritório")*Config_Equipamentos!$D$2:$D$21*Config_Equipamentos!$E$2:$E$21*Config_Equipamentos!$AD$2:$AD$21) -> 0.02 | AA3: =SUM(C3:Z3) -> 18.72
A4: Escritório | B4: Média | C4: =SUMPRODUCT((Config_Equipamentos!$B$2:$B$21="Escritório")*Config_Equipamentos!$D$2:$D$21*Config_Equipamentos!$F$2:$F$21*Config_Equipamentos!$G$2:$G$21) -> 0.04 | D4: =SUMPRODUCT((Config_Equipamentos!$B$2:$B$21="Escritório")*Config_Equipamentos!$D$2:$D$21*Config_Equipamentos!$F$2:$F$21*Config_Equipamentos!$H$2:$H$21) -> 0.04 | E4: =SUMPRODUCT((Config_Equipamentos!$B$2:$B$21="Escritório")*Config_Equipamentos!$D$2:$D$21*Config_Equipamentos!$F$2:$F$21*Config_Equipamentos!$I$2:$I$21) -> 0.04 | F4: =SUMPRODUCT((Config_Equipamentos!$B$2:$B$21="Escritório")*Config_Equipamentos!$D$2:$D$21*Config_Equipamentos!$F$2:$F$21*Config_Equipamentos!$J$2:$J$21) -> 0.04 | G4: =SUMPRODUCT((Config_Equipamentos!$B$2:$B$21="Escritório")*Config_Equipamentos!$D$2:$D$21*Config_Equipamentos!$F$2:$F$21*Config_Equipamentos!$K$2:$K$21) -> 0.04 | H4: =SUMPRODUCT((Config_Equipamentos!$B$2:$B$21="Escritório")*Config_Equipamentos!$D$2:$D$21*Config_Equipamentos!$F$2:$F$21*Config_Equipamentos!$L$2:$L$21) -> 0.04 | I4: =SUMPRODUCT((Config_Equipamentos!$B$2:$B$21="Escritório")*Config_Equipamentos!$D$2:$D$21*Config_Equipamentos!$F$2:$F$21*Config_Equipamentos!$M$2:$M$21) -> 0.04 | J4: =SUMPRODUCT((Config_Equipamentos!$B$2:$B$21="Escritório")*Config_Equipamentos!$D$2:$D$21*Config_Equipamentos!$F$2:$F$21*Config_Equipamentos!$N$2:$N$21) -> 1.04 | K4: =SUMPRODUCT((Config_Equipamentos!$B$2:$B$21="Escritório")*Config_Equipamentos!$D$2:$D$21*Config_Equipamentos!$F$2:$F$21*Config_Equipamentos!$O$2:$O$21) -> 1.805 | L4: =SUMPRODUCT((Config_Equipamentos!$B$2:$B$21="Escritório")*Config_Equipamentos!$D$2:$D$21*Config_Equipamentos!$F$2:$F$21*Config_Equipamentos!$P$2:$P$21) -> 3.725 | M4: =SUMPRODUCT((Config_Equipamentos!$B$2:$B$21="Escritório")*Config_Equipamentos!$D$2:$D$21*Config_Equipamentos!$F$2:$F$21*Config_Equipamentos!$Q$2:$Q$21) -> 3.725 | N4: =SUMPRODUCT((Config_Equipamentos!$B$2:$B$21="Escritório")*Config_Equipamentos!$D$2:$D$21*Config_Equipamentos!$F$2:$F$21*Config_Equipamentos!$R$2:$R$21) -> 3.725 | O4: =SUMPRODUCT((Config_Equipamentos!$B$2:$B$21="Escritório")*Config_Equipamentos!$D$2:$D$21*Config_Equipamentos!$F$2:$F$21*Config_Equipamentos!$S$2:$S$21) -> 3.725 | P4: =SUMPRODUCT((Config_Equipamentos!$B$2:$B$21="Escritório")*Config_Equipamentos!$D$2:$D$21*Config_Equipamentos!$F$2:$F$21*Config_Equipamentos!$T$2:$T$21) -> 3.725 | Q4: =SUMPRODUCT((Config_Equipamentos!$B$2:$B$21="Escritório")*Config_Equipamentos!$D$2:$D$21*Config_Equipamentos!$F$2:$F$21*Config_Equipamentos!$U$2:$U$21) -> 3.725 | R4: =SUMPRODUCT((Config_Equipamentos!$B$2:$B$21="Escritório")*Config_Equipamentos!$D$2:$D$21*Config_Equipamentos!$F$2:$F$21*Config_Equipamentos!$V$2:$V$21) -> 3.725 | S4: =SUMPRODUCT((Config_Equipamentos!$B$2:$B$21="Escritório")*Config_Equipamentos!$D$2:$D$21*Config_Equipamentos!$F$2:$F$21*Config_Equipamentos!$W$2:$W$21) -> 3.725 | T4: =SUMPRODUCT((Config_Equipamentos!$B$2:$B$21="Escritório")*Config_Equipamentos!$D$2:$D$21*Config_Equipamentos!$F$2:$F$21*Config_Equipamentos!$X$2:$X$21) -> 1.04 | U4: =SUMPRODUCT((Config_Equipamentos!$B$2:$B$21="Escritório")*Config_Equipamentos!$D$2:$D$21*Config_Equipamentos!$F$2:$F$21*Config_Equipamentos!$Y$2:$Y$21) -> 0.04 | V4: =SUMPRODUCT((Config_Equipamentos!$B$2:$B$21="Escritório")*Config_Equipamentos!$D$2:$D$21*Config_Equipamentos!$F$2:$F$21*Config_Equipamentos!$Z$2:$Z$21) -> 0.04 | W4: =SUMPRODUCT((Config_Equipamentos!$B$2:$B$21="Escritório")*Config_Equipamentos!$D$2:$D$21*Config_Equipamentos!$F$2:$F$21*Config_Equipamentos!$AA$2:$AA$21) -> 0.04 | X4: =SUMPRODUCT((Config_Equipamentos!$B$2:$B$21="Escritório")*Config_Equipamentos!$D$2:$D$21*Config_Equipamentos!$F$2:$F$21*Config_Equipamentos!$AB$2:$AB$21) -> 0.04 | Y4: =SUMPRODUCT((Config_Equipamentos!$B$2:$B$21="Escritório")*Config_Equipamentos!$D$2:$D$21*Config_Equipamentos!$F$2:$F$21*Config_Equipamentos!$AC$2:$AC$21) -> 0.04 | Z4: =SUMPRODUCT((Config_Equipamentos!$B$2:$B$21="Escritório")*Config_Equipamentos!$D$2:$D$21*Config_Equipamentos!$F$2:$F$21*Config_Equipamentos!$AD$2:$AD$21) -> 0.04 | AA4: =SUM(C4:Z4) -> 34.205
A5: Cozinha | B5: Pequena | C5: =SUMPRODUCT((Config_Equipamentos!$B$2:$B$21="Cozinha")*Config_Equipamentos!$D$2:$D$21*Config_Equipamentos!$E$2:$E$21*Config_Equipamentos!$G$2:$G$21) -> 0.274 | D5: =SUMPRODUCT((Config_Equipamentos!$B$2:$B$21="Cozinha")*Config_Equipamentos!$D$2:$D$21*Config_Equipamentos!$E$2:$E$21*Config_Equipamentos!$H$2:$H$21) -> 0.274 | E5: =SUMPRODUCT((Config_Equipamentos!$B$2:$B$21="Cozinha")*Config_Equipamentos!$D$2:$D$21*Config_Equipamentos!$E$2:$E$21*Config_Equipamentos!$I$2:$I$21) -> 0.274 | F5: =SUMPRODUCT((Config_Equipamentos!$B$2:$B$21="Cozinha")*Config_Equipamentos!$D$2:$D$21*Config_Equipamentos!$E$2:$E$21*Config_Equipamentos!$J$2:$J$21) -> 0.274 | G5: =SUMPRODUCT((Config_Equipamentos!$B$2:$B$21="Cozinha")*Config_Equipamentos!$D$2:$D$21*Config_Equipamentos!$E$2:$E$21*Config_Equipamentos!$K$2:$K$21) -> 0.274 | H5: =SUMPRODUCT((Config_Equipamentos!$B$2:$B$21="Cozinha")*Config_Equipamentos!$D$2:$D$21*Config_Equipamentos!$E$2:$E$21*Config_Equipamentos!$L$2:$L$21) -> 0.754 | I5: =SUMPRODUCT((Config_Equipamentos!$B$2:$B$21="Cozinha")*Config_Equipamentos!$D$2:$D$21*Config_Equipamentos!$E$2:$E$21*Config_Equipamentos!$M$2:$M$21) -> 1.714 | J5: =SUMPRODUCT((Config_Equipamentos!$B$2:$B$21="Cozinha")*Config_Equipamentos!$D$2:$D$21*Config_Equipamentos!$E$2:$E$21*Config_Equipamentos!$N$2:$N$21) -> 1.634 | K5: =SUMPRODUCT((Config_Equipamentos!$B$2:$B$21="Cozinha")*Config_Equipamentos!$D$2:$D$21*Config_Equipamentos!$E$2:$E$21*Config_Equipamentos!$O$2:$O$21) -> 0.634 | L5: =SUMPRODUCT((Config_Equipamentos!$B$2:$B$21="Cozinha")*Config_Equipamentos!$D$2:$D$21*Config_Equipamentos!$E$2:$E$21*Config_Equipamentos!$P$2:$P$21) -> 0.274 | M5: =SUMPRODUCT((Config_Equipamentos!$B$2:$B$21="Cozinha")*Config_Equipamentos!$D$2:$D$21*Config_Equipamentos!$E$2:$E$21*Config_Equipamentos!$Q$2:$Q$21) -> 0.274 | N5: =SUMPRODUCT((Config_Equipamentos!$B$2:$B$21="Cozinha")*Config_Equipamentos!$D$2:$D$21*Config_Equipamentos!$E$2:$E$21*Config_Equipamentos!$R$2:$R$21) -> 0.354 | O5: =SUMPRODUCT((Config_Equipamentos!$B$2:$B$21="Cozinha")*Config_Equipamentos!$D$2:$D$21*Config_Equipamentos!$E$2:$E$21*Config_Equipamentos!$S$2:$S$21) -> 1.434 | P5: =SUMPRODUCT((Config_Equipamentos!$B$2:$B$21="Cozinha")*Config_Equipamentos!$D$2:$D$21*Config_Equipamentos!$E$2:$E$21*Config_Equipamentos!$T$2:$T$21) -> 1.314 | Q5: =SUMPRODUCT((Config_Equipamentos!$B$2:$B$21="Cozinha")*Config_Equipamentos!$D$2:$D$21*Config_Equipamentos!$E$2:$E$21*Config_Equipamentos!$U$2:$U$21) -> 0.594 | R5: =SUMPRODUCT((Config_Equipamentos!$B$2:$B$21="Cozinha")*Config_Equipamentos!$D$2:$D$21*Config_Equipamentos!$E$2:$E$21*Config_Equipamentos!$V$2:$V$21) -> 0.594 | S5: =SUMPRODUCT((Config_Equipamentos!$B$2:$B$21="Cozinha")*Config_Equipamentos!$D$2:$D$21*Config_Equipamentos!$E$2:$E$21*Config_Equipamentos!$W$2:$W$21) -> 0.274 | T5: =SUMPRODUCT((Config_Equipamentos!$B$2:$B$21="Cozinha")*Config_Equipamentos!$D$2:$D$21*Config_Equipamentos!$E$2:$E$21*Config_Equipamentos!$X$2:$X$21) -> 0.954 | U5: =SUMPRODUCT((Config_Equipamentos!$B$2:$B$21="Cozinha")*Config_Equipamentos!$D$2:$D$21*Config_Equipamentos!$E$2:$E$21*Config_Equipamentos!$Y$2:$Y$21) -> 1.434 | V5: =SUMPRODUCT((Config_Equipamentos!$B$2:$B$21="Cozinha")*Config_Equipamentos!$D$2:$D$21*Config_Equipamentos!$E$2:$E$21*Config_Equipamentos!$Z$2:$Z$21) -> 1.354 | W5: =SUMPRODUCT((Config_Equipamentos!$B$2:$B$21="Cozinha")*Config_Equipamentos!$D$2:$D$21*Config_Equipamentos!$E$2:$E$21*Config_Equipamentos!$AA$2:$AA$21) -> 0.314 | X5: =SUMPRODUCT((Config_Equipamentos!$B$2:$B$21="Cozinha")*Config_Equipamentos!$D$2:$D$21*Config_Equipamentos!$E$2:$E$21*Config_Equipamentos!$AB$2:$AB$21) -> 0.274 | Y5: =SUMPRODUCT((Config_Equipamentos!$B$2:$B$21="Cozinha")*Config_Equipamentos!$D$2:$D$21*Config_Equipamentos!$E$2:$E$21*Config_Equipamentos!$AC$2:$AC$21) -> 0.274 | Z5: =SUMPRODUCT((Config_Equipamentos!$B$2:$B$21="Cozinha")*Config_Equipamentos!$D$2:$D$21*Config_Equipamentos!$E$2:$E$21*Config_Equipamentos!$AD$2:$AD$21) -> 0.274 | AA5: =SUM(C5:Z5) -> 16.096
A6: Cozinha | B6: Média | C6: =SUMPRODUCT((Config_Equipamentos!$B$2:$B$21="Cozinha")*Config_Equipamentos!$D$2:$D$21*Config_Equipamentos!$F$2:$F$21*Config_Equipamentos!$G$2:$G$21) -> 0.394 | D6: =SUMPRODUCT((Config_Equipamentos!$B$2:$B$21="Cozinha")*Config_Equipamentos!$D$2:$D$21*Config_Equipamentos!$F$2:$F$21*Config_Equipamentos!$H$2:$H$21) -> 0.394 | E6: =SUMPRODUCT((Config_Equipamentos!$B$2:$B$21="Cozinha")*Config_Equipamentos!$D$2:$D$21*Config_Equipamentos!$F$2:$F$21*Config_Equipamentos!$I$2:$I$21) -> 0.394 | F6: =SUMPRODUCT((Config_Equipamentos!$B$2:$B$21="Cozinha")*Config_Equipamentos!$D$2:$D$21*Config_Equipamentos!$F$2:$F$21*Config_Equipamentos!$J$2:$J$21) -> 0.394 | G6: =SUMPRODUCT((Config_Equipamentos!$B$2:$B$21="Cozinha")*Config_Equipamentos!$D$2:$D$21*Config_Equipamentos!$F$2:$F$21*Config_Equipamentos!$K$2:$K$21) -> 0.394 | H6: =SUMPRODUCT((Config_Equipamentos!$B$2:$B$21="Cozinha")*Config_Equipamentos!$D$2:$D$21*Config_Equipamentos!$F$2:$F$21*Config_Equipamentos!$L$2:$L$21) -> 0.914 | I6: =SUMPRODUCT((Config_Equipamentos!$B$2:$B$21="Cozinha")*Config_Equipamentos!$D$2:$D$21*Config_Equipamentos!$F$2:$F$21*Config_Equipamentos!$M$2:$M$21) -> 1.934 | J6: =SUMPRODUCT((Config_Equipamentos!$B$2:$B$21="Cozinha")*Config_Equipamentos!$D$2:$D$21*Config_Equipamentos!$F$2:$F$21*Config_Equipamentos!$N$2:$N$21) -> 1.814 | K6: =SUMPRODUCT((Config_Equipamentos!$B$2:$B$21="Cozinha")*Config_Equipamentos!$D$2:$D$21*Config_Equipamentos!$F$2:$F$21*Config_Equipamentos!$O$2:$O$21) -> 0.774 | L6: =SUMPRODUCT((Config_Equipamentos!$B$2:$B$21="Cozinha")*Config_Equipamentos!$D$2:$D$21*Config_Equipamentos!$F$2:$F$21*Config_Equipamentos!$P$2:$P$21) -> 0.394 | M6: =SUMPRODUCT((Config_Equipamentos!$B$2:$B$21="Cozinha")*Config_Equipamentos!$D$2:$D$21*Config_Equipamentos!$F$2:$F$21*Config_Equipamentos!$Q$2:$Q$21) -> 0.394 | N6: =SUMPRODUCT((Config_Equipamentos!$B$2:$B$21="Cozinha")*Config_Equipamentos!$D$2:$D$21*Config_Equipamentos!$F$2:$F$21*Config_Equipamentos!$R$2:$R$21) -> 0.514 | O6: =SUMPRODUCT((Config_Equipamentos!$B$2:$B$21="Cozinha")*Config_Equipamentos!$D$2:$D$21*Config_Equipamentos!$F$2:$F$21*Config_Equipamentos!$S$2:$S$21) -> 1.654 | P6: =SUMPRODUCT((Config_Equipamentos!$B$2:$B$21="Cozinha")*Config_Equipamentos!$D$2:$D$21*Config_Equipamentos!$F$2:$F$21*Config_Equipamentos!$T$2:$T$21) -> 1.474 | Q6: =SUMPRODUCT((Config_Equipamentos!$B$2:$B$21="Cozinha")*Config_Equipamentos!$D$2:$D$21*Config_Equipamentos!$F$2:$F$21*Config_Equipamentos!$U$2:$U$21) -> 0.714 | R6: =SUMPRODUCT((Config_Equipamentos!$B$2:$B$21="Cozinha")*Config_Equipamentos!$D$2:$D$21*Config_Equipamentos!$F$2:$F$21*Config_Equipamentos!$V$2:$V$21) -> 0.714 | S6: =SUMPRODUCT((Config_Equipamentos!$B$2:$B$21="Cozinha")*Config_Equipamentos!$D$2:$D$21*Config_Equipamentos!$F$2:$F$21*Config_Equipamentos!$W$2:$W$21) -> 0.394 | T6: =SUMPRODUCT((Config_Equipamentos!$B$2:$B$21="Cozinha")*Config_Equipamentos!$D$2:$D$21*Config_Equipamentos!$F$2:$F$21*Config_Equipamentos!$X$2:$X$21) -> 1.114 | U6: =SUMPRODUCT((Config_Equipamentos!$B$2:$B$21="Cozinha")*Config_Equipamentos!$D$2:$D$21*Config_Equipamentos!$F$2:$F$21*Config_Equipamentos!$Y$2:$Y$21) -> 1.654 | V6: =SUMPRODUCT((Config_Equipamentos!$B$2:$B$21="Cozinha")*Config_Equipamentos!$D$2:$D$21*Config_Equipamentos!$F$2:$F$21*Config_Equipamentos!$Z$2:$Z$21) -> 1.534 | W6: =SUMPRODUCT((Config_Equipamentos!$B$2:$B$21="Cozinha")*Config_Equipamentos!$D$2:$D$21*Config_Equipamentos!$F$2:$F$21*Config_Equipamentos!$AA$2:$AA$21) -> 0.454 | X6: =SUMPRODUCT((Config_Equipamentos!$B$2:$B$21="Cozinha")*Config_Equipamentos!$D$2:$D$21*Config_Equipamentos!$F$2:$F$21*Config_Equipamentos!$AB$2:$AB$21) -> 0.394 | Y6: =SUMPRODUCT((Config_Equipamentos!$B$2:$B$21="Cozinha")*Config_Equipamentos!$D$2:$D$21*Config_Equipamentos!$F$2:$F$21*Config_Equipamentos!$AC$2:$AC$21) -> 0.394 | Z6: =SUMPRODUCT((Config_Equipamentos!$B$2:$B$21="Cozinha")*Config_Equipamentos!$D$2:$D$21*Config_Equipamentos!$F$2:$F$21*Config_Equipamentos!$AD$2:$AD$21) -> 0.394 | AA6: =SUM(C6:Z6) -> 19.596
A7: Quarto | B7: Pequena | C7: =SUMPRODUCT((Config_Equipamentos!$B$2:$B$21="Quarto")*Config_Equipamentos!$D$2:$D$21*Config_Equipamentos!$E$2:$E$21*Config_Equipamentos!$G$2:$G$21) -> 0.176 | D7: =SUMPRODUCT((Config_Equipamentos!$B$2:$B$21="Quarto")*Config_Equipamentos!$D$2:$D$21*Config_Equipamentos!$E$2:$E$21*Config_Equipamentos!$H$2:$H$21) -> 0.176 | E7: =SUMPRODUCT((Config_Equipamentos!$B$2:$B$21="Quarto")*Config_Equipamentos!$D$2:$D$21*Config_Equipamentos!$E$2:$E$21*Config_Equipamentos!$I$2:$I$21) -> 0.176 | F7: =SUMPRODUCT((Config_Equipamentos!$B$2:$B$21="Quarto")*Config_Equipamentos!$D$2:$D$21*Config_Equipamentos!$E$2:$E$21*Config_Equipamentos!$J$2:$J$21) -> 0.176 | G7: =SUMPRODUCT((Config_Equipamentos!$B$2:$B$21="Quarto")*Config_Equipamentos!$D$2:$D$21*Config_Equipamentos!$E$2:$E$21*Config_Equipamentos!$K$2:$K$21) -> 0.158 | H7: =SUMPRODUCT((Config_Equipamentos!$B$2:$B$21="Quarto")*Config_Equipamentos!$D$2:$D$21*Config_Equipamentos!$E$2:$E$21*Config_Equipamentos!$L$2:$L$21) -> 0.114 | I7: =SUMPRODUCT((Config_Equipamentos!$B$2:$B$21="Quarto")*Config_Equipamentos!$D$2:$D$21*Config_Equipamentos!$E$2:$E$21*Config_Equipamentos!$M$2:$M$21) -> 0.048 | J7: =SUMPRODUCT((Config_Equipamentos!$B$2:$B$21="Quarto")*Config_Equipamentos!$D$2:$D$21*Config_Equipamentos!$E$2:$E$21*Config_Equipamentos!$N$2:$N$21) -> 0 | K7: =SUMPRODUCT((Config_Equipamentos!$B$2:$B$21="Quarto")*Config_Equipamentos!$D$2:$D$21*Config_Equipamentos!$E$2:$E$21*Config_Equipamentos!$O$2:$O$21) -> 0 | L7: =SUMPRODUCT((Config_Equipamentos!$B$2:$B$21="Quarto")*Config_Equipamentos!$D$2:$D$21*Config_Equipamentos!$E$2:$E$21*Config_Equipamentos!$P$2:$P$21) -> 0 | M7: =SUMPRODUCT((Config_Equipamentos!$B$2:$B$21="Quarto")*Config_Equipamentos!$D$2:$D$21*Config_Equipamentos!$E$2:$E$21*Config_Equipamentos!$Q$2:$Q$21) -> 0 | N7: =SUMPRODUCT((Config_Equipamentos!$B$2:$B$21="Quarto")*Config_Equipamentos!$D$2:$D$21*Config_Equipamentos!$E$2:$E$21*Config_Equipamentos!$R$2:$R$21) -> 0 | O7: =SUMPRODUCT((Config_Equipamentos!$B$2:$B$21="Quarto")*Config_Equipamentos!$D$2:$D$21*Config_Equipamentos!$E$2:$E$21*Config_Equipamentos!$S$2:$S$21) -> 0 | P7: =SUMPRODUCT((Config_Equipamentos!$B$2:$B$21="Quarto")*Config_Equipamentos!$D$2:$D$21*Config_Equipamentos!$E$2:$E$21*Config_Equipamentos!$T$2:$T$21) -> 0 | Q7: =SUMPRODUCT((Config_Equipamentos!$B$2:$B$21="Quarto")*Config_Equipamentos!$D$2:$D$21*Config_Equipamentos!$E$2:$E$21*Config_Equipamentos!$U$2:$U$21) -> 0 | R7: =SUMPRODUCT((Config_Equipamentos!$B$2:$B$21="Quarto")*Config_Equipamentos!$D$2:$D$21*Config_Equipamentos!$E$2:$E$21*Config_Equipamentos!$V$2:$V$21) -> 0 | S7: =SUMPRODUCT((Config_Equipamentos!$B$2:$B$21="Quarto")*Config_Equipamentos!$D$2:$D$21*Config_Equipamentos!$E$2:$E$21*Config_Equipamentos!$W$2:$W$21) -> 0 | T7: =SUMPRODUCT((Config_Equipamentos!$B$2:$B$21="Quarto")*Config_Equipamentos!$D$2:$D$21*Config_Equipamentos!$E$2:$E$21*Config_Equipamentos!$X$2:$X$21) -> 0 | U7: =SUMPRODUCT((Config_Equipamentos!$B$2:$B$21="Quarto")*Config_Equipamentos!$D$2:$D$21*Config_Equipamentos!$E$2:$E$21*Config_Equipamentos!$Y$2:$Y$21) -> 0.25 | V7: =SUMPRODUCT((Config_Equipamentos!$B$2:$B$21="Quarto")*Config_Equipamentos!$D$2:$D$21*Config_Equipamentos!$E$2:$E$21*Config_Equipamentos!$Z$2:$Z$21) -> 0.548 | W7: =SUMPRODUCT((Config_Equipamentos!$B$2:$B$21="Quarto")*Config_Equipamentos!$D$2:$D$21*Config_Equipamentos!$E$2:$E$21*Config_Equipamentos!$AA$2:$AA$21) -> 0.63 | X7: =SUMPRODUCT((Config_Equipamentos!$B$2:$B$21="Quarto")*Config_Equipamentos!$D$2:$D$21*Config_Equipamentos!$E$2:$E$21*Config_Equipamentos!$AB$2:$AB$21) -> 0.674 | Y7: =SUMPRODUCT((Config_Equipamentos!$B$2:$B$21="Quarto")*Config_Equipamentos!$D$2:$D$21*Config_Equipamentos!$E$2:$E$21*Config_Equipamentos!$AC$2:$AC$21) -> 0.608 | Z7: =SUMPRODUCT((Config_Equipamentos!$B$2:$B$21="Quarto")*Config_Equipamentos!$D$2:$D$21*Config_Equipamentos!$E$2:$E$21*Config_Equipamentos!$AD$2:$AD$21) -> 0.338 | AA7: =SUM(C7:Z7) -> 4.072
A8: Quarto | B8: Média | C8: =SUMPRODUCT((Config_Equipamentos!$B$2:$B$21="Quarto")*Config_Equipamentos!$D$2:$D$21*Config_Equipamentos!$F$2:$F$21*Config_Equipamentos!$G$2:$G$21) -> 0.336 | D8: =SUMPRODUCT((Config_Equipamentos!$B$2:$B$21="Quarto")*Config_Equipamentos!$D$2:$D$21*Config_Equipamentos!$F$2:$F$21*Config_Equipamentos!$H$2:$H$21) -> 0.336 | E8: =SUMPRODUCT((Config_Equipamentos!$B$2:$B$21="Quarto")*Config_Equipamentos!$D$2:$D$21*Config_Equipamentos!$F$2:$F$21*Config_Equipamentos!$I$2:$I$21) -> 0.336 | F8: =SUMPRODUCT((Config_Equipamentos!$B$2:$B$21="Quarto")*Config_Equipamentos!$D$2:$D$21*Config_Equipamentos!$F$2:$F$21*Config_Equipamentos!$J$2:$J$21) -> 0.336 | G8: =SUMPRODUCT((Config_Equipamentos!$B$2:$B$21="Quarto")*Config_Equipamentos!$D$2:$D$21*Config_Equipamentos!$F$2:$F$21*Config_Equipamentos!$K$2:$K$21) -> 0.306 | H8: =SUMPRODUCT((Config_Equipamentos!$B$2:$B$21="Quarto")*Config_Equipamentos!$D$2:$D$21*Config_Equipamentos!$F$2:$F$21*Config_Equipamentos!$L$2:$L$21) -> 0.222 | I8: =SUMPRODUCT((Config_Equipamentos!$B$2:$B$21="Quarto")*Config_Equipamentos!$D$2:$D$21*Config_Equipamentos!$F$2:$F$21*Config_Equipamentos!$M$2:$M$21) -> 0.096 | J8: =SUMPRODUCT((Config_Equipamentos!$B$2:$B$21="Quarto")*Config_Equipamentos!$D$2:$D$21*Config_Equipamentos!$F$2:$F$21*Config_Equipamentos!$N$2:$N$21) -> 0 | K8: =SUMPRODUCT((Config_Equipamentos!$B$2:$B$21="Quarto")*Config_Equipamentos!$D$2:$D$21*Config_Equipamentos!$F$2:$F$21*Config_Equipamentos!$O$2:$O$21) -> 0 | L8: =SUMPRODUCT((Config_Equipamentos!$B$2:$B$21="Quarto")*Config_Equipamentos!$D$2:$D$21*Config_Equipamentos!$F$2:$F$21*Config_Equipamentos!$P$2:$P$21) -> 0 | M8: =SUMPRODUCT((Config_Equipamentos!$B$2:$B$21="Quarto")*Config_Equipamentos!$D$2:$D$21*Config_Equipamentos!$F$2:$F$21*Config_Equipamentos!$Q$2:$Q$21) -> 0 | N8: =SUMPRODUCT((Config_Equipamentos!$B$2:$B$21="Quarto")*Config_Equipamentos!$D$2:$D$21*Config_Equipamentos!$F$2:$F$21*Config_Equipamentos!$R$2:$R$21) -> 0 | O8: =SUMPRODUCT((Config_Equipamentos!$B$2:$B$21="Quarto")*Config_Equipamentos!$D$2:$D$21*Config_Equipamentos!$F$2:$F$21*Config_Equipamentos!$S$2:$S$21) -> 0 | P8: =SUMPRODUCT((Config_Equipamentos!$B$2:$B$21="Quarto")*Config_Equipamentos!$D$2:$D$21*Config_Equipamentos!$F$2:$F$21*Config_Equipamentos!$T$2:$T$21) -> 0 | Q8: =SUMPRODUCT((Config_Equipamentos!$B$2:$B$21="Quarto")*Config_Equipamentos!$D$2:$D$21*Config_Equipamentos!$F$2:$F$21*Config_Equipamentos!$U$2:$U$21) -> 0 | R8: =SUMPRODUCT((Config_Equipamentos!$B$2:$B$21="Quarto")*Config_Equipamentos!$D$2:$D$21*Config_Equipamentos!$F$2:$F$21*Config_Equipamentos!$V$2:$V$21) -> 0 | S8: =SUMPRODUCT((Config_Equipamentos!$B$2:$B$21="Quarto")*Config_Equipamentos!$D$2:$D$21*Config_Equipamentos!$F$2:$F$21*Config_Equipamentos!$W$2:$W$21) -> 0 | T8: =SUMPRODUCT((Config_Equipamentos!$B$2:$B$21="Quarto")*Config_Equipamentos!$D$2:$D$21*Config_Equipamentos!$F$2:$F$21*Config_Equipamentos!$X$2:$X$21) -> 0 | U8: =SUMPRODUCT((Config_Equipamentos!$B$2:$B$21="Quarto")*Config_Equipamentos!$D$2:$D$21*Config_Equipamentos!$F$2:$F$21*Config_Equipamentos!$Y$2:$Y$21) -> 0.4 | V8: =SUMPRODUCT((Config_Equipamentos!$B$2:$B$21="Quarto")*Config_Equipamentos!$D$2:$D$21*Config_Equipamentos!$F$2:$F$21*Config_Equipamentos!$Z$2:$Z$21) -> 0.896 | W8: =SUMPRODUCT((Config_Equipamentos!$B$2:$B$21="Quarto")*Config_Equipamentos!$D$2:$D$21*Config_Equipamentos!$F$2:$F$21*Config_Equipamentos!$AA$2:$AA$21) -> 1.054 | X8: =SUMPRODUCT((Config_Equipamentos!$B$2:$B$21="Quarto")*Config_Equipamentos!$D$2:$D$21*Config_Equipamentos!$F$2:$F$21*Config_Equipamentos!$AB$2:$AB$21) -> 1.138 | Y8: =SUMPRODUCT((Config_Equipamentos!$B$2:$B$21="Quarto")*Config_Equipamentos!$D$2:$D$21*Config_Equipamentos!$F$2:$F$21*Config_Equipamentos!$AC$2:$AC$21) -> 1.04 | Z8: =SUMPRODUCT((Config_Equipamentos!$B$2:$B$21="Quarto")*Config_Equipamentos!$D$2:$D$21*Config_Equipamentos!$F$2:$F$21*Config_Equipamentos!$AD$2:$AD$21) -> 0.598 | AA8: =SUM(C8:Z8) -> 7.094
A9: Pivô | B9: Pequena | C9: =SUMPRODUCT((Config_Equipamentos!$B$2:$B$21="Irrigação/Lavoura")*(Config_Equipamentos!$C$2:$C$21="Pivô central")*Config_Equipamentos!$D$2:$D$21*Config_Equipamentos!$E$2:$E$21*Config_Equipamentos!$G$2:$G$21) -> 4 | D9: =SUMPRODUCT((Config_Equipamentos!$B$2:$B$21="Irrigação/Lavoura")*(Config_Equipamentos!$C$2:$C$21="Pivô central")*Config_Equipamentos!$D$2:$D$21*Config_Equipamentos!$E$2:$E$21*Config_Equipamentos!$H$2:$H$21) -> 4 | E9: =SUMPRODUCT((Config_Equipamentos!$B$2:$B$21="Irrigação/Lavoura")*(Config_Equipamentos!$C$2:$C$21="Pivô central")*Config_Equipamentos!$D$2:$D$21*Config_Equipamentos!$E$2:$E$21*Config_Equipamentos!$I$2:$I$21) -> 4 | F9: =SUMPRODUCT((Config_Equipamentos!$B$2:$B$21="Irrigação/Lavoura")*(Config_Equipamentos!$C$2:$C$21="Pivô central")*Config_Equipamentos!$D$2:$D$21*Config_Equipamentos!$E$2:$E$21*Config_Equipamentos!$J$2:$J$21) -> 4 | G9: =SUMPRODUCT((Config_Equipamentos!$B$2:$B$21="Irrigação/Lavoura")*(Config_Equipamentos!$C$2:$C$21="Pivô central")*Config_Equipamentos!$D$2:$D$21*Config_Equipamentos!$E$2:$E$21*Config_Equipamentos!$K$2:$K$21) -> 4 | H9: =SUMPRODUCT((Config_Equipamentos!$B$2:$B$21="Irrigação/Lavoura")*(Config_Equipamentos!$C$2:$C$21="Pivô central")*Config_Equipamentos!$D$2:$D$21*Config_Equipamentos!$E$2:$E$21*Config_Equipamentos!$L$2:$L$21) -> 0 | I9: =SUMPRODUCT((Config_Equipamentos!$B$2:$B$21="Irrigação/Lavoura")*(Config_Equipamentos!$C$2:$C$21="Pivô central")*Config_Equipamentos!$D$2:$D$21*Config_Equipamentos!$E$2:$E$21*Config_Equipamentos!$M$2:$M$21) -> 0 | J9: =SUMPRODUCT((Config_Equipamentos!$B$2:$B$21="Irrigação/Lavoura")*(Config_Equipamentos!$C$2:$C$21="Pivô central")*Config_Equipamentos!$D$2:$D$21*Config_Equipamentos!$E$2:$E$21*Config_Equipamentos!$N$2:$N$21) -> 0 | K9: =SUMPRODUCT((Config_Equipamentos!$B$2:$B$21="Irrigação/Lavoura")*(Config_Equipamentos!$C$2:$C$21="Pivô central")*Config_Equipamentos!$D$2:$D$21*Config_Equipamentos!$E$2:$E$21*Config_Equipamentos!$O$2:$O$21) -> 0 | L9: =SUMPRODUCT((Config_Equipamentos!$B$2:$B$21="Irrigação/Lavoura")*(Config_Equipamentos!$C$2:$C$21="Pivô central")*Config_Equipamentos!$D$2:$D$21*Config_Equipamentos!$E$2:$E$21*Config_Equipamentos!$P$2:$P$21) -> 0 | M9: =SUMPRODUCT((Config_Equipamentos!$B$2:$B$21="Irrigação/Lavoura")*(Config_Equipamentos!$C$2:$C$21="Pivô central")*Config_Equipamentos!$D$2:$D$21*Config_Equipamentos!$E$2:$E$21*Config_Equipamentos!$Q$2:$Q$21) -> 0 | N9: =SUMPRODUCT((Config_Equipamentos!$B$2:$B$21="Irrigação/Lavoura")*(Config_Equipamentos!$C$2:$C$21="Pivô central")*Config_Equipamentos!$D$2:$D$21*Config_Equipamentos!$E$2:$E$21*Config_Equipamentos!$R$2:$R$21) -> 0 | O9: =SUMPRODUCT((Config_Equipamentos!$B$2:$B$21="Irrigação/Lavoura")*(Config_Equipamentos!$C$2:$C$21="Pivô central")*Config_Equipamentos!$D$2:$D$21*Config_Equipamentos!$E$2:$E$21*Config_Equipamentos!$S$2:$S$21) -> 0 | P9: =SUMPRODUCT((Config_Equipamentos!$B$2:$B$21="Irrigação/Lavoura")*(Config_Equipamentos!$C$2:$C$21="Pivô central")*Config_Equipamentos!$D$2:$D$21*Config_Equipamentos!$E$2:$E$21*Config_Equipamentos!$T$2:$T$21) -> 0 | Q9: =SUMPRODUCT((Config_Equipamentos!$B$2:$B$21="Irrigação/Lavoura")*(Config_Equipamentos!$C$2:$C$21="Pivô central")*Config_Equipamentos!$D$2:$D$21*Config_Equipamentos!$E$2:$E$21*Config_Equipamentos!$U$2:$U$21) -> 0 | R9: =SUMPRODUCT((Config_Equipamentos!$B$2:$B$21="Irrigação/Lavoura")*(Config_Equipamentos!$C$2:$C$21="Pivô central")*Config_Equipamentos!$D$2:$D$21*Config_Equipamentos!$E$2:$E$21*Config_Equipamentos!$V$2:$V$21) -> 0 | S9: =SUMPRODUCT((Config_Equipamentos!$B$2:$B$21="Irrigação/Lavoura")*(Config_Equipamentos!$C$2:$C$21="Pivô central")*Config_Equipamentos!$D$2:$D$21*Config_Equipamentos!$E$2:$E$21*Config_Equipamentos!$W$2:$W$21) -> 0 | T9: =SUMPRODUCT((Config_Equipamentos!$B$2:$B$21="Irrigação/Lavoura")*(Config_Equipamentos!$C$2:$C$21="Pivô central")*Config_Equipamentos!$D$2:$D$21*Config_Equipamentos!$E$2:$E$21*Config_Equipamentos!$X$2:$X$21) -> 0 | U9: =SUMPRODUCT((Config_Equipamentos!$B$2:$B$21="Irrigação/Lavoura")*(Config_Equipamentos!$C$2:$C$21="Pivô central")*Config_Equipamentos!$D$2:$D$21*Config_Equipamentos!$E$2:$E$21*Config_Equipamentos!$Y$2:$Y$21) -> 0 | V9: =SUMPRODUCT((Config_Equipamentos!$B$2:$B$21="Irrigação/Lavoura")*(Config_Equipamentos!$C$2:$C$21="Pivô central")*Config_Equipamentos!$D$2:$D$21*Config_Equipamentos!$E$2:$E$21*Config_Equipamentos!$Z$2:$Z$21) -> 0 | W9: =SUMPRODUCT((Config_Equipamentos!$B$2:$B$21="Irrigação/Lavoura")*(Config_Equipamentos!$C$2:$C$21="Pivô central")*Config_Equipamentos!$D$2:$D$21*Config_Equipamentos!$E$2:$E$21*Config_Equipamentos!$AA$2:$AA$21) -> 4 | X9: =SUMPRODUCT((Config_Equipamentos!$B$2:$B$21="Irrigação/Lavoura")*(Config_Equipamentos!$C$2:$C$21="Pivô central")*Config_Equipamentos!$D$2:$D$21*Config_Equipamentos!$E$2:$E$21*Config_Equipamentos!$AB$2:$AB$21) -> 4 | Y9: =SUMPRODUCT((Config_Equipamentos!$B$2:$B$21="Irrigação/Lavoura")*(Config_Equipamentos!$C$2:$C$21="Pivô central")*Config_Equipamentos!$D$2:$D$21*Config_Equipamentos!$E$2:$E$21*Config_Equipamentos!$AC$2:$AC$21) -> 4 | Z9: =SUMPRODUCT((Config_Equipamentos!$B$2:$B$21="Irrigação/Lavoura")*(Config_Equipamentos!$C$2:$C$21="Pivô central")*Config_Equipamentos!$D$2:$D$21*Config_Equipamentos!$E$2:$E$21*Config_Equipamentos!$AD$2:$AD$21) -> 4 | AA9: =SUM(C9:Z9) -> 36
A10: Pivô | B10: Média | C10: =SUMPRODUCT((Config_Equipamentos!$B$2:$B$21="Irrigação/Lavoura")*(Config_Equipamentos!$C$2:$C$21="Pivô central")*Config_Equipamentos!$D$2:$D$21*Config_Equipamentos!$F$2:$F$21*Config_Equipamentos!$G$2:$G$21) -> 8 | D10: =SUMPRODUCT((Config_Equipamentos!$B$2:$B$21="Irrigação/Lavoura")*(Config_Equipamentos!$C$2:$C$21="Pivô central")*Config_Equipamentos!$D$2:$D$21*Config_Equipamentos!$F$2:$F$21*Config_Equipamentos!$H$2:$H$21) -> 8 | E10: =SUMPRODUCT((Config_Equipamentos!$B$2:$B$21="Irrigação/Lavoura")*(Config_Equipamentos!$C$2:$C$21="Pivô central")*Config_Equipamentos!$D$2:$D$21*Config_Equipamentos!$F$2:$F$21*Config_Equipamentos!$I$2:$I$21) -> 8 | F10: =SUMPRODUCT((Config_Equipamentos!$B$2:$B$21="Irrigação/Lavoura")*(Config_Equipamentos!$C$2:$C$21="Pivô central")*Config_Equipamentos!$D$2:$D$21*Config_Equipamentos!$F$2:$F$21*Config_Equipamentos!$J$2:$J$21) -> 8 | G10: =SUMPRODUCT((Config_Equipamentos!$B$2:$B$21="Irrigação/Lavoura")*(Config_Equipamentos!$C$2:$C$21="Pivô central")*Config_Equipamentos!$D$2:$D$21*Config_Equipamentos!$F$2:$F$21*Config_Equipamentos!$K$2:$K$21) -> 8 | H10: =SUMPRODUCT((Config_Equipamentos!$B$2:$B$21="Irrigação/Lavoura")*(Config_Equipamentos!$C$2:$C$21="Pivô central")*Config_Equipamentos!$D$2:$D$21*Config_Equipamentos!$F$2:$F$21*Config_Equipamentos!$L$2:$L$21) -> 0 | I10: =SUMPRODUCT((Config_Equipamentos!$B$2:$B$21="Irrigação/Lavoura")*(Config_Equipamentos!$C$2:$C$21="Pivô central")*Config_Equipamentos!$D$2:$D$21*Config_Equipamentos!$F$2:$F$21*Config_Equipamentos!$M$2:$M$21) -> 0 | J10: =SUMPRODUCT((Config_Equipamentos!$B$2:$B$21="Irrigação/Lavoura")*(Config_Equipamentos!$C$2:$C$21="Pivô central")*Config_Equipamentos!$D$2:$D$21*Config_Equipamentos!$F$2:$F$21*Config_Equipamentos!$N$2:$N$21) -> 0 | K10: =SUMPRODUCT((Config_Equipamentos!$B$2:$B$21="Irrigação/Lavoura")*(Config_Equipamentos!$C$2:$C$21="Pivô central")*Config_Equipamentos!$D$2:$D$21*Config_Equipamentos!$F$2:$F$21*Config_Equipamentos!$O$2:$O$21) -> 0 | L10: =SUMPRODUCT((Config_Equipamentos!$B$2:$B$21="Irrigação/Lavoura")*(Config_Equipamentos!$C$2:$C$21="Pivô central")*Config_Equipamentos!$D$2:$D$21*Config_Equipamentos!$F$2:$F$21*Config_Equipamentos!$P$2:$P$21) -> 0 | M10: =SUMPRODUCT((Config_Equipamentos!$B$2:$B$21="Irrigação/Lavoura")*(Config_Equipamentos!$C$2:$C$21="Pivô central")*Config_Equipamentos!$D$2:$D$21*Config_Equipamentos!$F$2:$F$21*Config_Equipamentos!$Q$2:$Q$21) -> 0 | N10: =SUMPRODUCT((Config_Equipamentos!$B$2:$B$21="Irrigação/Lavoura")*(Config_Equipamentos!$C$2:$C$21="Pivô central")*Config_Equipamentos!$D$2:$D$21*Config_Equipamentos!$F$2:$F$21*Config_Equipamentos!$R$2:$R$21) -> 0 | O10: =SUMPRODUCT((Config_Equipamentos!$B$2:$B$21="Irrigação/Lavoura")*(Config_Equipamentos!$C$2:$C$21="Pivô central")*Config_Equipamentos!$D$2:$D$21*Config_Equipamentos!$F$2:$F$21*Config_Equipamentos!$S$2:$S$21) -> 0 | P10: =SUMPRODUCT((Config_Equipamentos!$B$2:$B$21="Irrigação/Lavoura")*(Config_Equipamentos!$C$2:$C$21="Pivô central")*Config_Equipamentos!$D$2:$D$21*Config_Equipamentos!$F$2:$F$21*Config_Equipamentos!$T$2:$T$21) -> 0 | Q10: =SUMPRODUCT((Config_Equipamentos!$B$2:$B$21="Irrigação/Lavoura")*(Config_Equipamentos!$C$2:$C$21="Pivô central")*Config_Equipamentos!$D$2:$D$21*Config_Equipamentos!$F$2:$F$21*Config_Equipamentos!$U$2:$U$21) -> 0 | R10: =SUMPRODUCT((Config_Equipamentos!$B$2:$B$21="Irrigação/Lavoura")*(Config_Equipamentos!$C$2:$C$21="Pivô central")*Config_Equipamentos!$D$2:$D$21*Config_Equipamentos!$F$2:$F$21*Config_Equipamentos!$V$2:$V$21) -> 0 | S10: =SUMPRODUCT((Config_Equipamentos!$B$2:$B$21="Irrigação/Lavoura")*(Config_Equipamentos!$C$2:$C$21="Pivô central")*Config_Equipamentos!$D$2:$D$21*Config_Equipamentos!$F$2:$F$21*Config_Equipamentos!$W$2:$W$21) -> 0 | T10: =SUMPRODUCT((Config_Equipamentos!$B$2:$B$21="Irrigação/Lavoura")*(Config_Equipamentos!$C$2:$C$21="Pivô central")*Config_Equipamentos!$D$2:$D$21*Config_Equipamentos!$F$2:$F$21*Config_Equipamentos!$X$2:$X$21) -> 0 | U10: =SUMPRODUCT((Config_Equipamentos!$B$2:$B$21="Irrigação/Lavoura")*(Config_Equipamentos!$C$2:$C$21="Pivô central")*Config_Equipamentos!$D$2:$D$21*Config_Equipamentos!$F$2:$F$21*Config_Equipamentos!$Y$2:$Y$21) -> 0 | V10: =SUMPRODUCT((Config_Equipamentos!$B$2:$B$21="Irrigação/Lavoura")*(Config_Equipamentos!$C$2:$C$21="Pivô central")*Config_Equipamentos!$D$2:$D$21*Config_Equipamentos!$F$2:$F$21*Config_Equipamentos!$Z$2:$Z$21) -> 0 | W10: =SUMPRODUCT((Config_Equipamentos!$B$2:$B$21="Irrigação/Lavoura")*(Config_Equipamentos!$C$2:$C$21="Pivô central")*Config_Equipamentos!$D$2:$D$21*Config_Equipamentos!$F$2:$F$21*Config_Equipamentos!$AA$2:$AA$21) -> 8 | X10: =SUMPRODUCT((Config_Equipamentos!$B$2:$B$21="Irrigação/Lavoura")*(Config_Equipamentos!$C$2:$C$21="Pivô central")*Config_Equipamentos!$D$2:$D$21*Config_Equipamentos!$F$2:$F$21*Config_Equipamentos!$AB$2:$AB$21) -> 8 | Y10: =SUMPRODUCT((Config_Equipamentos!$B$2:$B$21="Irrigação/Lavoura")*(Config_Equipamentos!$C$2:$C$21="Pivô central")*Config_Equipamentos!$D$2:$D$21*Config_Equipamentos!$F$2:$F$21*Config_Equipamentos!$AC$2:$AC$21) -> 8 | Z10: =SUMPRODUCT((Config_Equipamentos!$B$2:$B$21="Irrigação/Lavoura")*(Config_Equipamentos!$C$2:$C$21="Pivô central")*Config_Equipamentos!$D$2:$D$21*Config_Equipamentos!$F$2:$F$21*Config_Equipamentos!$AD$2:$AD$21) -> 8 | AA10: =SUM(C10:Z10) -> 72
A11: Bomba_Aux | B11: Pequena | C11: =SUMPRODUCT((Config_Equipamentos!$B$2:$B$21="Irrigação/Lavoura")*(Config_Equipamentos!$C$2:$C$21="Bomba auxiliar")*Config_Equipamentos!$D$2:$D$21*Config_Equipamentos!$E$2:$E$21*Config_Equipamentos!$G$2:$G$21) -> 0 | D11: =SUMPRODUCT((Config_Equipamentos!$B$2:$B$21="Irrigação/Lavoura")*(Config_Equipamentos!$C$2:$C$21="Bomba auxiliar")*Config_Equipamentos!$D$2:$D$21*Config_Equipamentos!$E$2:$E$21*Config_Equipamentos!$H$2:$H$21) -> 0 | E11: =SUMPRODUCT((Config_Equipamentos!$B$2:$B$21="Irrigação/Lavoura")*(Config_Equipamentos!$C$2:$C$21="Bomba auxiliar")*Config_Equipamentos!$D$2:$D$21*Config_Equipamentos!$E$2:$E$21*Config_Equipamentos!$I$2:$I$21) -> 0 | F11: =SUMPRODUCT((Config_Equipamentos!$B$2:$B$21="Irrigação/Lavoura")*(Config_Equipamentos!$C$2:$C$21="Bomba auxiliar")*Config_Equipamentos!$D$2:$D$21*Config_Equipamentos!$E$2:$E$21*Config_Equipamentos!$J$2:$J$21) -> 0 | G11: =SUMPRODUCT((Config_Equipamentos!$B$2:$B$21="Irrigação/Lavoura")*(Config_Equipamentos!$C$2:$C$21="Bomba auxiliar")*Config_Equipamentos!$D$2:$D$21*Config_Equipamentos!$E$2:$E$21*Config_Equipamentos!$K$2:$K$21) -> 0 | H11: =SUMPRODUCT((Config_Equipamentos!$B$2:$B$21="Irrigação/Lavoura")*(Config_Equipamentos!$C$2:$C$21="Bomba auxiliar")*Config_Equipamentos!$D$2:$D$21*Config_Equipamentos!$E$2:$E$21*Config_Equipamentos!$L$2:$L$21) -> 0 | I11: =SUMPRODUCT((Config_Equipamentos!$B$2:$B$21="Irrigação/Lavoura")*(Config_Equipamentos!$C$2:$C$21="Bomba auxiliar")*Config_Equipamentos!$D$2:$D$21*Config_Equipamentos!$E$2:$E$21*Config_Equipamentos!$M$2:$M$21) -> 0 | J11: =SUMPRODUCT((Config_Equipamentos!$B$2:$B$21="Irrigação/Lavoura")*(Config_Equipamentos!$C$2:$C$21="Bomba auxiliar")*Config_Equipamentos!$D$2:$D$21*Config_Equipamentos!$E$2:$E$21*Config_Equipamentos!$N$2:$N$21) -> 0 | K11: =SUMPRODUCT((Config_Equipamentos!$B$2:$B$21="Irrigação/Lavoura")*(Config_Equipamentos!$C$2:$C$21="Bomba auxiliar")*Config_Equipamentos!$D$2:$D$21*Config_Equipamentos!$E$2:$E$21*Config_Equipamentos!$O$2:$O$21) -> 0 | L11: =SUMPRODUCT((Config_Equipamentos!$B$2:$B$21="Irrigação/Lavoura")*(Config_Equipamentos!$C$2:$C$21="Bomba auxiliar")*Config_Equipamentos!$D$2:$D$21*Config_Equipamentos!$E$2:$E$21*Config_Equipamentos!$P$2:$P$21) -> 0 | M11: =SUMPRODUCT((Config_Equipamentos!$B$2:$B$21="Irrigação/Lavoura")*(Config_Equipamentos!$C$2:$C$21="Bomba auxiliar")*Config_Equipamentos!$D$2:$D$21*Config_Equipamentos!$E$2:$E$21*Config_Equipamentos!$Q$2:$Q$21) -> 0 | N11: =SUMPRODUCT((Config_Equipamentos!$B$2:$B$21="Irrigação/Lavoura")*(Config_Equipamentos!$C$2:$C$21="Bomba auxiliar")*Config_Equipamentos!$D$2:$D$21*Config_Equipamentos!$E$2:$E$21*Config_Equipamentos!$R$2:$R$21) -> 0 | O11: =SUMPRODUCT((Config_Equipamentos!$B$2:$B$21="Irrigação/Lavoura")*(Config_Equipamentos!$C$2:$C$21="Bomba auxiliar")*Config_Equipamentos!$D$2:$D$21*Config_Equipamentos!$E$2:$E$21*Config_Equipamentos!$S$2:$S$21) -> 0 | P11: =SUMPRODUCT((Config_Equipamentos!$B$2:$B$21="Irrigação/Lavoura")*(Config_Equipamentos!$C$2:$C$21="Bomba auxiliar")*Config_Equipamentos!$D$2:$D$21*Config_Equipamentos!$E$2:$E$21*Config_Equipamentos!$T$2:$T$21) -> 0 | Q11: =SUMPRODUCT((Config_Equipamentos!$B$2:$B$21="Irrigação/Lavoura")*(Config_Equipamentos!$C$2:$C$21="Bomba auxiliar")*Config_Equipamentos!$D$2:$D$21*Config_Equipamentos!$E$2:$E$21*Config_Equipamentos!$U$2:$U$21) -> 0 | R11: =SUMPRODUCT((Config_Equipamentos!$B$2:$B$21="Irrigação/Lavoura")*(Config_Equipamentos!$C$2:$C$21="Bomba auxiliar")*Config_Equipamentos!$D$2:$D$21*Config_Equipamentos!$E$2:$E$21*Config_Equipamentos!$V$2:$V$21) -> 0 | S11: =SUMPRODUCT((Config_Equipamentos!$B$2:$B$21="Irrigação/Lavoura")*(Config_Equipamentos!$C$2:$C$21="Bomba auxiliar")*Config_Equipamentos!$D$2:$D$21*Config_Equipamentos!$E$2:$E$21*Config_Equipamentos!$W$2:$W$21) -> 0 | T11: =SUMPRODUCT((Config_Equipamentos!$B$2:$B$21="Irrigação/Lavoura")*(Config_Equipamentos!$C$2:$C$21="Bomba auxiliar")*Config_Equipamentos!$D$2:$D$21*Config_Equipamentos!$E$2:$E$21*Config_Equipamentos!$X$2:$X$21) -> 0 | U11: =SUMPRODUCT((Config_Equipamentos!$B$2:$B$21="Irrigação/Lavoura")*(Config_Equipamentos!$C$2:$C$21="Bomba auxiliar")*Config_Equipamentos!$D$2:$D$21*Config_Equipamentos!$E$2:$E$21*Config_Equipamentos!$Y$2:$Y$21) -> 0 | V11: =SUMPRODUCT((Config_Equipamentos!$B$2:$B$21="Irrigação/Lavoura")*(Config_Equipamentos!$C$2:$C$21="Bomba auxiliar")*Config_Equipamentos!$D$2:$D$21*Config_Equipamentos!$E$2:$E$21*Config_Equipamentos!$Z$2:$Z$21) -> 0 | W11: =SUMPRODUCT((Config_Equipamentos!$B$2:$B$21="Irrigação/Lavoura")*(Config_Equipamentos!$C$2:$C$21="Bomba auxiliar")*Config_Equipamentos!$D$2:$D$21*Config_Equipamentos!$E$2:$E$21*Config_Equipamentos!$AA$2:$AA$21) -> 0 | X11: =SUMPRODUCT((Config_Equipamentos!$B$2:$B$21="Irrigação/Lavoura")*(Config_Equipamentos!$C$2:$C$21="Bomba auxiliar")*Config_Equipamentos!$D$2:$D$21*Config_Equipamentos!$E$2:$E$21*Config_Equipamentos!$AB$2:$AB$21) -> 0 | Y11: =SUMPRODUCT((Config_Equipamentos!$B$2:$B$21="Irrigação/Lavoura")*(Config_Equipamentos!$C$2:$C$21="Bomba auxiliar")*Config_Equipamentos!$D$2:$D$21*Config_Equipamentos!$E$2:$E$21*Config_Equipamentos!$AC$2:$AC$21) -> 0 | Z11: =SUMPRODUCT((Config_Equipamentos!$B$2:$B$21="Irrigação/Lavoura")*(Config_Equipamentos!$C$2:$C$21="Bomba auxiliar")*Config_Equipamentos!$D$2:$D$21*Config_Equipamentos!$E$2:$E$21*Config_Equipamentos!$AD$2:$AD$21) -> 0 | AA11: =SUM(C11:Z11) -> 0
A12: Bomba_Aux | B12: Média | C12: =SUMPRODUCT((Config_Equipamentos!$B$2:$B$21="Irrigação/Lavoura")*(Config_Equipamentos!$C$2:$C$21="Bomba auxiliar")*Config_Equipamentos!$D$2:$D$21*Config_Equipamentos!$F$2:$F$21*Config_Equipamentos!$G$2:$G$21) -> 17.6 | D12: =SUMPRODUCT((Config_Equipamentos!$B$2:$B$21="Irrigação/Lavoura")*(Config_Equipamentos!$C$2:$C$21="Bomba auxiliar")*Config_Equipamentos!$D$2:$D$21*Config_Equipamentos!$F$2:$F$21*Config_Equipamentos!$H$2:$H$21) -> 17.6 | E12: =SUMPRODUCT((Config_Equipamentos!$B$2:$B$21="Irrigação/Lavoura")*(Config_Equipamentos!$C$2:$C$21="Bomba auxiliar")*Config_Equipamentos!$D$2:$D$21*Config_Equipamentos!$F$2:$F$21*Config_Equipamentos!$I$2:$I$21) -> 0 | F12: =SUMPRODUCT((Config_Equipamentos!$B$2:$B$21="Irrigação/Lavoura")*(Config_Equipamentos!$C$2:$C$21="Bomba auxiliar")*Config_Equipamentos!$D$2:$D$21*Config_Equipamentos!$F$2:$F$21*Config_Equipamentos!$J$2:$J$21) -> 0 | G12: =SUMPRODUCT((Config_Equipamentos!$B$2:$B$21="Irrigação/Lavoura")*(Config_Equipamentos!$C$2:$C$21="Bomba auxiliar")*Config_Equipamentos!$D$2:$D$21*Config_Equipamentos!$F$2:$F$21*Config_Equipamentos!$K$2:$K$21) -> 0 | H12: =SUMPRODUCT((Config_Equipamentos!$B$2:$B$21="Irrigação/Lavoura")*(Config_Equipamentos!$C$2:$C$21="Bomba auxiliar")*Config_Equipamentos!$D$2:$D$21*Config_Equipamentos!$F$2:$F$21*Config_Equipamentos!$L$2:$L$21) -> 0 | I12: =SUMPRODUCT((Config_Equipamentos!$B$2:$B$21="Irrigação/Lavoura")*(Config_Equipamentos!$C$2:$C$21="Bomba auxiliar")*Config_Equipamentos!$D$2:$D$21*Config_Equipamentos!$F$2:$F$21*Config_Equipamentos!$M$2:$M$21) -> 0 | J12: =SUMPRODUCT((Config_Equipamentos!$B$2:$B$21="Irrigação/Lavoura")*(Config_Equipamentos!$C$2:$C$21="Bomba auxiliar")*Config_Equipamentos!$D$2:$D$21*Config_Equipamentos!$F$2:$F$21*Config_Equipamentos!$N$2:$N$21) -> 17.6 | K12: =SUMPRODUCT((Config_Equipamentos!$B$2:$B$21="Irrigação/Lavoura")*(Config_Equipamentos!$C$2:$C$21="Bomba auxiliar")*Config_Equipamentos!$D$2:$D$21*Config_Equipamentos!$F$2:$F$21*Config_Equipamentos!$O$2:$O$21) -> 17.6 | L12: =SUMPRODUCT((Config_Equipamentos!$B$2:$B$21="Irrigação/Lavoura")*(Config_Equipamentos!$C$2:$C$21="Bomba auxiliar")*Config_Equipamentos!$D$2:$D$21*Config_Equipamentos!$F$2:$F$21*Config_Equipamentos!$P$2:$P$21) -> 0 | M12: =SUMPRODUCT((Config_Equipamentos!$B$2:$B$21="Irrigação/Lavoura")*(Config_Equipamentos!$C$2:$C$21="Bomba auxiliar")*Config_Equipamentos!$D$2:$D$21*Config_Equipamentos!$F$2:$F$21*Config_Equipamentos!$Q$2:$Q$21) -> 0 | N12: =SUMPRODUCT((Config_Equipamentos!$B$2:$B$21="Irrigação/Lavoura")*(Config_Equipamentos!$C$2:$C$21="Bomba auxiliar")*Config_Equipamentos!$D$2:$D$21*Config_Equipamentos!$F$2:$F$21*Config_Equipamentos!$R$2:$R$21) -> 0 | O12: =SUMPRODUCT((Config_Equipamentos!$B$2:$B$21="Irrigação/Lavoura")*(Config_Equipamentos!$C$2:$C$21="Bomba auxiliar")*Config_Equipamentos!$D$2:$D$21*Config_Equipamentos!$F$2:$F$21*Config_Equipamentos!$S$2:$S$21) -> 0 | P12: =SUMPRODUCT((Config_Equipamentos!$B$2:$B$21="Irrigação/Lavoura")*(Config_Equipamentos!$C$2:$C$21="Bomba auxiliar")*Config_Equipamentos!$D$2:$D$21*Config_Equipamentos!$F$2:$F$21*Config_Equipamentos!$T$2:$T$21) -> 0 | Q12: =SUMPRODUCT((Config_Equipamentos!$B$2:$B$21="Irrigação/Lavoura")*(Config_Equipamentos!$C$2:$C$21="Bomba auxiliar")*Config_Equipamentos!$D$2:$D$21*Config_Equipamentos!$F$2:$F$21*Config_Equipamentos!$U$2:$U$21) -> 17.6 | R12: =SUMPRODUCT((Config_Equipamentos!$B$2:$B$21="Irrigação/Lavoura")*(Config_Equipamentos!$C$2:$C$21="Bomba auxiliar")*Config_Equipamentos!$D$2:$D$21*Config_Equipamentos!$F$2:$F$21*Config_Equipamentos!$V$2:$V$21) -> 17.6 | S12: =SUMPRODUCT((Config_Equipamentos!$B$2:$B$21="Irrigação/Lavoura")*(Config_Equipamentos!$C$2:$C$21="Bomba auxiliar")*Config_Equipamentos!$D$2:$D$21*Config_Equipamentos!$F$2:$F$21*Config_Equipamentos!$W$2:$W$21) -> 0 | T12: =SUMPRODUCT((Config_Equipamentos!$B$2:$B$21="Irrigação/Lavoura")*(Config_Equipamentos!$C$2:$C$21="Bomba auxiliar")*Config_Equipamentos!$D$2:$D$21*Config_Equipamentos!$F$2:$F$21*Config_Equipamentos!$X$2:$X$21) -> 0 | U12: =SUMPRODUCT((Config_Equipamentos!$B$2:$B$21="Irrigação/Lavoura")*(Config_Equipamentos!$C$2:$C$21="Bomba auxiliar")*Config_Equipamentos!$D$2:$D$21*Config_Equipamentos!$F$2:$F$21*Config_Equipamentos!$Y$2:$Y$21) -> 0 | V12: =SUMPRODUCT((Config_Equipamentos!$B$2:$B$21="Irrigação/Lavoura")*(Config_Equipamentos!$C$2:$C$21="Bomba auxiliar")*Config_Equipamentos!$D$2:$D$21*Config_Equipamentos!$F$2:$F$21*Config_Equipamentos!$Z$2:$Z$21) -> 0 | W12: =SUMPRODUCT((Config_Equipamentos!$B$2:$B$21="Irrigação/Lavoura")*(Config_Equipamentos!$C$2:$C$21="Bomba auxiliar")*Config_Equipamentos!$D$2:$D$21*Config_Equipamentos!$F$2:$F$21*Config_Equipamentos!$AA$2:$AA$21) -> 17.6 | X12: =SUMPRODUCT((Config_Equipamentos!$B$2:$B$21="Irrigação/Lavoura")*(Config_Equipamentos!$C$2:$C$21="Bomba auxiliar")*Config_Equipamentos!$D$2:$D$21*Config_Equipamentos!$F$2:$F$21*Config_Equipamentos!$AB$2:$AB$21) -> 17.6 | Y12: =SUMPRODUCT((Config_Equipamentos!$B$2:$B$21="Irrigação/Lavoura")*(Config_Equipamentos!$C$2:$C$21="Bomba auxiliar")*Config_Equipamentos!$D$2:$D$21*Config_Equipamentos!$F$2:$F$21*Config_Equipamentos!$AC$2:$AC$21) -> 0 | Z12: =SUMPRODUCT((Config_Equipamentos!$B$2:$B$21="Irrigação/Lavoura")*(Config_Equipamentos!$C$2:$C$21="Bomba auxiliar")*Config_Equipamentos!$D$2:$D$21*Config_Equipamentos!$F$2:$F$21*Config_Equipamentos!$AD$2:$AD$21) -> 0 | AA12: =SUM(C12:Z12) -> 140.8
A13: Secadora | B13: Pequena | C13: =SUMPRODUCT((Config_Equipamentos!$B$2:$B$21="Irrigação/Lavoura")*(Config_Equipamentos!$C$2:$C$21="Secadora/Silo")*Config_Equipamentos!$D$2:$D$21*Config_Equipamentos!$E$2:$E$21*Config_Equipamentos!$G$2:$G$21) -> 0 | D13: =SUMPRODUCT((Config_Equipamentos!$B$2:$B$21="Irrigação/Lavoura")*(Config_Equipamentos!$C$2:$C$21="Secadora/Silo")*Config_Equipamentos!$D$2:$D$21*Config_Equipamentos!$E$2:$E$21*Config_Equipamentos!$H$2:$H$21) -> 0 | E13: =SUMPRODUCT((Config_Equipamentos!$B$2:$B$21="Irrigação/Lavoura")*(Config_Equipamentos!$C$2:$C$21="Secadora/Silo")*Config_Equipamentos!$D$2:$D$21*Config_Equipamentos!$E$2:$E$21*Config_Equipamentos!$I$2:$I$21) -> 0 | F13: =SUMPRODUCT((Config_Equipamentos!$B$2:$B$21="Irrigação/Lavoura")*(Config_Equipamentos!$C$2:$C$21="Secadora/Silo")*Config_Equipamentos!$D$2:$D$21*Config_Equipamentos!$E$2:$E$21*Config_Equipamentos!$J$2:$J$21) -> 0 | G13: =SUMPRODUCT((Config_Equipamentos!$B$2:$B$21="Irrigação/Lavoura")*(Config_Equipamentos!$C$2:$C$21="Secadora/Silo")*Config_Equipamentos!$D$2:$D$21*Config_Equipamentos!$E$2:$E$21*Config_Equipamentos!$K$2:$K$21) -> 0 | H13: =SUMPRODUCT((Config_Equipamentos!$B$2:$B$21="Irrigação/Lavoura")*(Config_Equipamentos!$C$2:$C$21="Secadora/Silo")*Config_Equipamentos!$D$2:$D$21*Config_Equipamentos!$E$2:$E$21*Config_Equipamentos!$L$2:$L$21) -> 0 | I13: =SUMPRODUCT((Config_Equipamentos!$B$2:$B$21="Irrigação/Lavoura")*(Config_Equipamentos!$C$2:$C$21="Secadora/Silo")*Config_Equipamentos!$D$2:$D$21*Config_Equipamentos!$E$2:$E$21*Config_Equipamentos!$M$2:$M$21) -> 0 | J13: =SUMPRODUCT((Config_Equipamentos!$B$2:$B$21="Irrigação/Lavoura")*(Config_Equipamentos!$C$2:$C$21="Secadora/Silo")*Config_Equipamentos!$D$2:$D$21*Config_Equipamentos!$E$2:$E$21*Config_Equipamentos!$N$2:$N$21) -> 0 | K13: =SUMPRODUCT((Config_Equipamentos!$B$2:$B$21="Irrigação/Lavoura")*(Config_Equipamentos!$C$2:$C$21="Secadora/Silo")*Config_Equipamentos!$D$2:$D$21*Config_Equipamentos!$E$2:$E$21*Config_Equipamentos!$O$2:$O$21) -> 0 | L13: =SUMPRODUCT((Config_Equipamentos!$B$2:$B$21="Irrigação/Lavoura")*(Config_Equipamentos!$C$2:$C$21="Secadora/Silo")*Config_Equipamentos!$D$2:$D$21*Config_Equipamentos!$E$2:$E$21*Config_Equipamentos!$P$2:$P$21) -> 0 | M13: =SUMPRODUCT((Config_Equipamentos!$B$2:$B$21="Irrigação/Lavoura")*(Config_Equipamentos!$C$2:$C$21="Secadora/Silo")*Config_Equipamentos!$D$2:$D$21*Config_Equipamentos!$E$2:$E$21*Config_Equipamentos!$Q$2:$Q$21) -> 0 | N13: =SUMPRODUCT((Config_Equipamentos!$B$2:$B$21="Irrigação/Lavoura")*(Config_Equipamentos!$C$2:$C$21="Secadora/Silo")*Config_Equipamentos!$D$2:$D$21*Config_Equipamentos!$E$2:$E$21*Config_Equipamentos!$R$2:$R$21) -> 0 | O13: =SUMPRODUCT((Config_Equipamentos!$B$2:$B$21="Irrigação/Lavoura")*(Config_Equipamentos!$C$2:$C$21="Secadora/Silo")*Config_Equipamentos!$D$2:$D$21*Config_Equipamentos!$E$2:$E$21*Config_Equipamentos!$S$2:$S$21) -> 0 | P13: =SUMPRODUCT((Config_Equipamentos!$B$2:$B$21="Irrigação/Lavoura")*(Config_Equipamentos!$C$2:$C$21="Secadora/Silo")*Config_Equipamentos!$D$2:$D$21*Config_Equipamentos!$E$2:$E$21*Config_Equipamentos!$T$2:$T$21) -> 0 | Q13: =SUMPRODUCT((Config_Equipamentos!$B$2:$B$21="Irrigação/Lavoura")*(Config_Equipamentos!$C$2:$C$21="Secadora/Silo")*Config_Equipamentos!$D$2:$D$21*Config_Equipamentos!$E$2:$E$21*Config_Equipamentos!$U$2:$U$21) -> 0 | R13: =SUMPRODUCT((Config_Equipamentos!$B$2:$B$21="Irrigação/Lavoura")*(Config_Equipamentos!$C$2:$C$21="Secadora/Silo")*Config_Equipamentos!$D$2:$D$21*Config_Equipamentos!$E$2:$E$21*Config_Equipamentos!$V$2:$V$21) -> 0 | S13: =SUMPRODUCT((Config_Equipamentos!$B$2:$B$21="Irrigação/Lavoura")*(Config_Equipamentos!$C$2:$C$21="Secadora/Silo")*Config_Equipamentos!$D$2:$D$21*Config_Equipamentos!$E$2:$E$21*Config_Equipamentos!$W$2:$W$21) -> 0 | T13: =SUMPRODUCT((Config_Equipamentos!$B$2:$B$21="Irrigação/Lavoura")*(Config_Equipamentos!$C$2:$C$21="Secadora/Silo")*Config_Equipamentos!$D$2:$D$21*Config_Equipamentos!$E$2:$E$21*Config_Equipamentos!$X$2:$X$21) -> 0 | U13: =SUMPRODUCT((Config_Equipamentos!$B$2:$B$21="Irrigação/Lavoura")*(Config_Equipamentos!$C$2:$C$21="Secadora/Silo")*Config_Equipamentos!$D$2:$D$21*Config_Equipamentos!$E$2:$E$21*Config_Equipamentos!$Y$2:$Y$21) -> 0 | V13: =SUMPRODUCT((Config_Equipamentos!$B$2:$B$21="Irrigação/Lavoura")*(Config_Equipamentos!$C$2:$C$21="Secadora/Silo")*Config_Equipamentos!$D$2:$D$21*Config_Equipamentos!$E$2:$E$21*Config_Equipamentos!$Z$2:$Z$21) -> 0 | W13: =SUMPRODUCT((Config_Equipamentos!$B$2:$B$21="Irrigação/Lavoura")*(Config_Equipamentos!$C$2:$C$21="Secadora/Silo")*Config_Equipamentos!$D$2:$D$21*Config_Equipamentos!$E$2:$E$21*Config_Equipamentos!$AA$2:$AA$21) -> 0 | X13: =SUMPRODUCT((Config_Equipamentos!$B$2:$B$21="Irrigação/Lavoura")*(Config_Equipamentos!$C$2:$C$21="Secadora/Silo")*Config_Equipamentos!$D$2:$D$21*Config_Equipamentos!$E$2:$E$21*Config_Equipamentos!$AB$2:$AB$21) -> 0 | Y13: =SUMPRODUCT((Config_Equipamentos!$B$2:$B$21="Irrigação/Lavoura")*(Config_Equipamentos!$C$2:$C$21="Secadora/Silo")*Config_Equipamentos!$D$2:$D$21*Config_Equipamentos!$E$2:$E$21*Config_Equipamentos!$AC$2:$AC$21) -> 0 | Z13: =SUMPRODUCT((Config_Equipamentos!$B$2:$B$21="Irrigação/Lavoura")*(Config_Equipamentos!$C$2:$C$21="Secadora/Silo")*Config_Equipamentos!$D$2:$D$21*Config_Equipamentos!$E$2:$E$21*Config_Equipamentos!$AD$2:$AD$21) -> 0 | AA13: =SUM(C13:Z13) -> 0
A14: Secadora | B14: Média | C14: =SUMPRODUCT((Config_Equipamentos!$B$2:$B$21="Irrigação/Lavoura")*(Config_Equipamentos!$C$2:$C$21="Secadora/Silo")*Config_Equipamentos!$D$2:$D$21*Config_Equipamentos!$F$2:$F$21*Config_Equipamentos!$G$2:$G$21) -> 2.3670134 | D14: =SUMPRODUCT((Config_Equipamentos!$B$2:$B$21="Irrigação/Lavoura")*(Config_Equipamentos!$C$2:$C$21="Secadora/Silo")*Config_Equipamentos!$D$2:$D$21*Config_Equipamentos!$F$2:$F$21*Config_Equipamentos!$H$2:$H$21) -> 2.3580981 | E14: =SUMPRODUCT((Config_Equipamentos!$B$2:$B$21="Irrigação/Lavoura")*(Config_Equipamentos!$C$2:$C$21="Secadora/Silo")*Config_Equipamentos!$D$2:$D$21*Config_Equipamentos!$F$2:$F$21*Config_Equipamentos!$I$2:$I$21) -> 2.3001486 | F14: =SUMPRODUCT((Config_Equipamentos!$B$2:$B$21="Irrigação/Lavoura")*(Config_Equipamentos!$C$2:$C$21="Secadora/Silo")*Config_Equipamentos!$D$2:$D$21*Config_Equipamentos!$F$2:$F$21*Config_Equipamentos!$J$2:$J$21) -> 2.3652303 | G14: =SUMPRODUCT((Config_Equipamentos!$B$2:$B$21="Irrigação/Lavoura")*(Config_Equipamentos!$C$2:$C$21="Secadora/Silo")*Config_Equipamentos!$D$2:$D$21*Config_Equipamentos!$F$2:$F$21*Config_Equipamentos!$K$2:$K$21) -> 2.2876672 | H14: =SUMPRODUCT((Config_Equipamentos!$B$2:$B$21="Irrigação/Lavoura")*(Config_Equipamentos!$C$2:$C$21="Secadora/Silo")*Config_Equipamentos!$D$2:$D$21*Config_Equipamentos!$F$2:$F$21*Config_Equipamentos!$L$2:$L$21) -> 2.3794948 | I14: =SUMPRODUCT((Config_Equipamentos!$B$2:$B$21="Irrigação/Lavoura")*(Config_Equipamentos!$C$2:$C$21="Secadora/Silo")*Config_Equipamentos!$D$2:$D$21*Config_Equipamentos!$F$2:$F$21*Config_Equipamentos!$M$2:$M$21) -> 2.3509658 | J14: =SUMPRODUCT((Config_Equipamentos!$B$2:$B$21="Irrigação/Lavoura")*(Config_Equipamentos!$C$2:$C$21="Secadora/Silo")*Config_Equipamentos!$D$2:$D$21*Config_Equipamentos!$F$2:$F$21*Config_Equipamentos!$N$2:$N$21) -> 2.3117385 | K14: =SUMPRODUCT((Config_Equipamentos!$B$2:$B$21="Irrigação/Lavoura")*(Config_Equipamentos!$C$2:$C$21="Secadora/Silo")*Config_Equipamentos!$D$2:$D$21*Config_Equipamentos!$F$2:$F$21*Config_Equipamentos!$O$2:$O$21) -> 2.3705795 | L14: =SUMPRODUCT((Config_Equipamentos!$B$2:$B$21="Irrigação/Lavoura")*(Config_Equipamentos!$C$2:$C$21="Secadora/Silo")*Config_Equipamentos!$D$2:$D$21*Config_Equipamentos!$F$2:$F$21*Config_Equipamentos!$P$2:$P$21) -> 2.3670134 | M14: =SUMPRODUCT((Config_Equipamentos!$B$2:$B$21="Irrigação/Lavoura")*(Config_Equipamentos!$C$2:$C$21="Secadora/Silo")*Config_Equipamentos!$D$2:$D$21*Config_Equipamentos!$F$2:$F$21*Config_Equipamentos!$Q$2:$Q$21) -> 2.3482912 | N14: =SUMPRODUCT((Config_Equipamentos!$B$2:$B$21="Irrigação/Lavoura")*(Config_Equipamentos!$C$2:$C$21="Secadora/Silo")*Config_Equipamentos!$D$2:$D$21*Config_Equipamentos!$F$2:$F$21*Config_Equipamentos!$R$2:$R$21) -> 2.3179792 | O14: =SUMPRODUCT((Config_Equipamentos!$B$2:$B$21="Irrigação/Lavoura")*(Config_Equipamentos!$C$2:$C$21="Secadora/Silo")*Config_Equipamentos!$D$2:$D$21*Config_Equipamentos!$F$2:$F$21*Config_Equipamentos!$S$2:$S$21) -> 2.3090639 | P14: =SUMPRODUCT((Config_Equipamentos!$B$2:$B$21="Irrigação/Lavoura")*(Config_Equipamentos!$C$2:$C$21="Secadora/Silo")*Config_Equipamentos!$D$2:$D$21*Config_Equipamentos!$F$2:$F$21*Config_Equipamentos!$T$2:$T$21) -> 2.3777117 | Q14: =SUMPRODUCT((Config_Equipamentos!$B$2:$B$21="Irrigação/Lavoura")*(Config_Equipamentos!$C$2:$C$21="Secadora/Silo")*Config_Equipamentos!$D$2:$D$21*Config_Equipamentos!$F$2:$F$21*Config_Equipamentos!$U$2:$U$21) -> 2.4 | R14: =SUMPRODUCT((Config_Equipamentos!$B$2:$B$21="Irrigação/Lavoura")*(Config_Equipamentos!$C$2:$C$21="Secadora/Silo")*Config_Equipamentos!$D$2:$D$21*Config_Equipamentos!$F$2:$F$21*Config_Equipamentos!$V$2:$V$21) -> 2.3616642 | S14: =SUMPRODUCT((Config_Equipamentos!$B$2:$B$21="Irrigação/Lavoura")*(Config_Equipamentos!$C$2:$C$21="Secadora/Silo")*Config_Equipamentos!$D$2:$D$21*Config_Equipamentos!$F$2:$F$21*Config_Equipamentos!$W$2:$W$21) -> 2.3598811 | T14: =SUMPRODUCT((Config_Equipamentos!$B$2:$B$21="Irrigação/Lavoura")*(Config_Equipamentos!$C$2:$C$21="Secadora/Silo")*Config_Equipamentos!$D$2:$D$21*Config_Equipamentos!$F$2:$F$21*Config_Equipamentos!$X$2:$X$21) -> 2.3465082 | U14: =SUMPRODUCT((Config_Equipamentos!$B$2:$B$21="Irrigação/Lavoura")*(Config_Equipamentos!$C$2:$C$21="Secadora/Silo")*Config_Equipamentos!$D$2:$D$21*Config_Equipamentos!$F$2:$F$21*Config_Equipamentos!$Y$2:$Y$21) -> 2.3786033 | V14: =SUMPRODUCT((Config_Equipamentos!$B$2:$B$21="Irrigação/Lavoura")*(Config_Equipamentos!$C$2:$C$21="Secadora/Silo")*Config_Equipamentos!$D$2:$D$21*Config_Equipamentos!$F$2:$F$21*Config_Equipamentos!$Z$2:$Z$21) -> 2.3741456 | W14: =SUMPRODUCT((Config_Equipamentos!$B$2:$B$21="Irrigação/Lavoura")*(Config_Equipamentos!$C$2:$C$21="Secadora/Silo")*Config_Equipamentos!$D$2:$D$21*Config_Equipamentos!$F$2:$F$21*Config_Equipamentos!$AA$2:$AA$21) -> 2.3161961 | X14: =SUMPRODUCT((Config_Equipamentos!$B$2:$B$21="Irrigação/Lavoura")*(Config_Equipamentos!$C$2:$C$21="Secadora/Silo")*Config_Equipamentos!$D$2:$D$21*Config_Equipamentos!$F$2:$F$21*Config_Equipamentos!$AB$2:$AB$21) -> 2.3375929 | Y14: =SUMPRODUCT((Config_Equipamentos!$B$2:$B$21="Irrigação/Lavoura")*(Config_Equipamentos!$C$2:$C$21="Secadora/Silo")*Config_Equipamentos!$D$2:$D$21*Config_Equipamentos!$F$2:$F$21*Config_Equipamentos!$AC$2:$AC$21) -> 2.3830609 | Z14: =SUMPRODUCT((Config_Equipamentos!$B$2:$B$21="Irrigação/Lavoura")*(Config_Equipamentos!$C$2:$C$21="Secadora/Silo")*Config_Equipamentos!$D$2:$D$21*Config_Equipamentos!$F$2:$F$21*Config_Equipamentos!$AD$2:$AD$21) -> 2.3429421 | AA14: =SUM(C14:Z14) -> 56.41159
A15: Quadro_Auto | B15: Pequena | C15: =SUMPRODUCT((Config_Equipamentos!$B$2:$B$21="Irrigação/Lavoura")*(Config_Equipamentos!$C$2:$C$21="Quadro de automação")*Config_Equipamentos!$D$2:$D$21*Config_Equipamentos!$E$2:$E$21*Config_Equipamentos!$G$2:$G$21) -> 0.2 | D15: =SUMPRODUCT((Config_Equipamentos!$B$2:$B$21="Irrigação/Lavoura")*(Config_Equipamentos!$C$2:$C$21="Quadro de automação")*Config_Equipamentos!$D$2:$D$21*Config_Equipamentos!$E$2:$E$21*Config_Equipamentos!$H$2:$H$21) -> 0.2 | E15: =SUMPRODUCT((Config_Equipamentos!$B$2:$B$21="Irrigação/Lavoura")*(Config_Equipamentos!$C$2:$C$21="Quadro de automação")*Config_Equipamentos!$D$2:$D$21*Config_Equipamentos!$E$2:$E$21*Config_Equipamentos!$I$2:$I$21) -> 0.2 | F15: =SUMPRODUCT((Config_Equipamentos!$B$2:$B$21="Irrigação/Lavoura")*(Config_Equipamentos!$C$2:$C$21="Quadro de automação")*Config_Equipamentos!$D$2:$D$21*Config_Equipamentos!$E$2:$E$21*Config_Equipamentos!$J$2:$J$21) -> 0.2 | G15: =SUMPRODUCT((Config_Equipamentos!$B$2:$B$21="Irrigação/Lavoura")*(Config_Equipamentos!$C$2:$C$21="Quadro de automação")*Config_Equipamentos!$D$2:$D$21*Config_Equipamentos!$E$2:$E$21*Config_Equipamentos!$K$2:$K$21) -> 0.2 | H15: =SUMPRODUCT((Config_Equipamentos!$B$2:$B$21="Irrigação/Lavoura")*(Config_Equipamentos!$C$2:$C$21="Quadro de automação")*Config_Equipamentos!$D$2:$D$21*Config_Equipamentos!$E$2:$E$21*Config_Equipamentos!$L$2:$L$21) -> 0.2 | I15: =SUMPRODUCT((Config_Equipamentos!$B$2:$B$21="Irrigação/Lavoura")*(Config_Equipamentos!$C$2:$C$21="Quadro de automação")*Config_Equipamentos!$D$2:$D$21*Config_Equipamentos!$E$2:$E$21*Config_Equipamentos!$M$2:$M$21) -> 0.2 | J15: =SUMPRODUCT((Config_Equipamentos!$B$2:$B$21="Irrigação/Lavoura")*(Config_Equipamentos!$C$2:$C$21="Quadro de automação")*Config_Equipamentos!$D$2:$D$21*Config_Equipamentos!$E$2:$E$21*Config_Equipamentos!$N$2:$N$21) -> 0.2 | K15: =SUMPRODUCT((Config_Equipamentos!$B$2:$B$21="Irrigação/Lavoura")*(Config_Equipamentos!$C$2:$C$21="Quadro de automação")*Config_Equipamentos!$D$2:$D$21*Config_Equipamentos!$E$2:$E$21*Config_Equipamentos!$O$2:$O$21) -> 0.2 | L15: =SUMPRODUCT((Config_Equipamentos!$B$2:$B$21="Irrigação/Lavoura")*(Config_Equipamentos!$C$2:$C$21="Quadro de automação")*Config_Equipamentos!$D$2:$D$21*Config_Equipamentos!$E$2:$E$21*Config_Equipamentos!$P$2:$P$21) -> 0.2 | M15: =SUMPRODUCT((Config_Equipamentos!$B$2:$B$21="Irrigação/Lavoura")*(Config_Equipamentos!$C$2:$C$21="Quadro de automação")*Config_Equipamentos!$D$2:$D$21*Config_Equipamentos!$E$2:$E$21*Config_Equipamentos!$Q$2:$Q$21) -> 0.2 | N15: =SUMPRODUCT((Config_Equipamentos!$B$2:$B$21="Irrigação/Lavoura")*(Config_Equipamentos!$C$2:$C$21="Quadro de automação")*Config_Equipamentos!$D$2:$D$21*Config_Equipamentos!$E$2:$E$21*Config_Equipamentos!$R$2:$R$21) -> 0.2 | O15: =SUMPRODUCT((Config_Equipamentos!$B$2:$B$21="Irrigação/Lavoura")*(Config_Equipamentos!$C$2:$C$21="Quadro de automação")*Config_Equipamentos!$D$2:$D$21*Config_Equipamentos!$E$2:$E$21*Config_Equipamentos!$S$2:$S$21) -> 0.2 | P15: =SUMPRODUCT((Config_Equipamentos!$B$2:$B$21="Irrigação/Lavoura")*(Config_Equipamentos!$C$2:$C$21="Quadro de automação")*Config_Equipamentos!$D$2:$D$21*Config_Equipamentos!$E$2:$E$21*Config_Equipamentos!$T$2:$T$21) -> 0.2 | Q15: =SUMPRODUCT((Config_Equipamentos!$B$2:$B$21="Irrigação/Lavoura")*(Config_Equipamentos!$C$2:$C$21="Quadro de automação")*Config_Equipamentos!$D$2:$D$21*Config_Equipamentos!$E$2:$E$21*Config_Equipamentos!$U$2:$U$21) -> 0.2 | R15: =SUMPRODUCT((Config_Equipamentos!$B$2:$B$21="Irrigação/Lavoura")*(Config_Equipamentos!$C$2:$C$21="Quadro de automação")*Config_Equipamentos!$D$2:$D$21*Config_Equipamentos!$E$2:$E$21*Config_Equipamentos!$V$2:$V$21) -> 0.2 | S15: =SUMPRODUCT((Config_Equipamentos!$B$2:$B$21="Irrigação/Lavoura")*(Config_Equipamentos!$C$2:$C$21="Quadro de automação")*Config_Equipamentos!$D$2:$D$21*Config_Equipamentos!$E$2:$E$21*Config_Equipamentos!$W$2:$W$21) -> 0.2 | T15: =SUMPRODUCT((Config_Equipamentos!$B$2:$B$21="Irrigação/Lavoura")*(Config_Equipamentos!$C$2:$C$21="Quadro de automação")*Config_Equipamentos!$D$2:$D$21*Config_Equipamentos!$E$2:$E$21*Config_Equipamentos!$X$2:$X$21) -> 0.2 | U15: =SUMPRODUCT((Config_Equipamentos!$B$2:$B$21="Irrigação/Lavoura")*(Config_Equipamentos!$C$2:$C$21="Quadro de automação")*Config_Equipamentos!$D$2:$D$21*Config_Equipamentos!$E$2:$E$21*Config_Equipamentos!$Y$2:$Y$21) -> 0.2 | V15: =SUMPRODUCT((Config_Equipamentos!$B$2:$B$21="Irrigação/Lavoura")*(Config_Equipamentos!$C$2:$C$21="Quadro de automação")*Config_Equipamentos!$D$2:$D$21*Config_Equipamentos!$E$2:$E$21*Config_Equipamentos!$Z$2:$Z$21) -> 0.2 | W15: =SUMPRODUCT((Config_Equipamentos!$B$2:$B$21="Irrigação/Lavoura")*(Config_Equipamentos!$C$2:$C$21="Quadro de automação")*Config_Equipamentos!$D$2:$D$21*Config_Equipamentos!$E$2:$E$21*Config_Equipamentos!$AA$2:$AA$21) -> 0.2 | X15: =SUMPRODUCT((Config_Equipamentos!$B$2:$B$21="Irrigação/Lavoura")*(Config_Equipamentos!$C$2:$C$21="Quadro de automação")*Config_Equipamentos!$D$2:$D$21*Config_Equipamentos!$E$2:$E$21*Config_Equipamentos!$AB$2:$AB$21) -> 0.2 | Y15: =SUMPRODUCT((Config_Equipamentos!$B$2:$B$21="Irrigação/Lavoura")*(Config_Equipamentos!$C$2:$C$21="Quadro de automação")*Config_Equipamentos!$D$2:$D$21*Config_Equipamentos!$E$2:$E$21*Config_Equipamentos!$AC$2:$AC$21) -> 0.2 | Z15: =SUMPRODUCT((Config_Equipamentos!$B$2:$B$21="Irrigação/Lavoura")*(Config_Equipamentos!$C$2:$C$21="Quadro de automação")*Config_Equipamentos!$D$2:$D$21*Config_Equipamentos!$E$2:$E$21*Config_Equipamentos!$AD$2:$AD$21) -> 0.2 | AA15: =SUM(C15:Z15) -> 4.8
A16: Quadro_Auto | B16: Média | C16: =SUMPRODUCT((Config_Equipamentos!$B$2:$B$21="Irrigação/Lavoura")*(Config_Equipamentos!$C$2:$C$21="Quadro de automação")*Config_Equipamentos!$D$2:$D$21*Config_Equipamentos!$F$2:$F$21*Config_Equipamentos!$G$2:$G$21) -> 0.2 | D16: =SUMPRODUCT((Config_Equipamentos!$B$2:$B$21="Irrigação/Lavoura")*(Config_Equipamentos!$C$2:$C$21="Quadro de automação")*Config_Equipamentos!$D$2:$D$21*Config_Equipamentos!$F$2:$F$21*Config_Equipamentos!$H$2:$H$21) -> 0.2 | E16: =SUMPRODUCT((Config_Equipamentos!$B$2:$B$21="Irrigação/Lavoura")*(Config_Equipamentos!$C$2:$C$21="Quadro de automação")*Config_Equipamentos!$D$2:$D$21*Config_Equipamentos!$F$2:$F$21*Config_Equipamentos!$I$2:$I$21) -> 0.2 | F16: =SUMPRODUCT((Config_Equipamentos!$B$2:$B$21="Irrigação/Lavoura")*(Config_Equipamentos!$C$2:$C$21="Quadro de automação")*Config_Equipamentos!$D$2:$D$21*Config_Equipamentos!$F$2:$F$21*Config_Equipamentos!$J$2:$J$21) -> 0.2 | G16: =SUMPRODUCT((Config_Equipamentos!$B$2:$B$21="Irrigação/Lavoura")*(Config_Equipamentos!$C$2:$C$21="Quadro de automação")*Config_Equipamentos!$D$2:$D$21*Config_Equipamentos!$F$2:$F$21*Config_Equipamentos!$K$2:$K$21) -> 0.2 | H16: =SUMPRODUCT((Config_Equipamentos!$B$2:$B$21="Irrigação/Lavoura")*(Config_Equipamentos!$C$2:$C$21="Quadro de automação")*Config_Equipamentos!$D$2:$D$21*Config_Equipamentos!$F$2:$F$21*Config_Equipamentos!$L$2:$L$21) -> 0.2 | I16: =SUMPRODUCT((Config_Equipamentos!$B$2:$B$21="Irrigação/Lavoura")*(Config_Equipamentos!$C$2:$C$21="Quadro de automação")*Config_Equipamentos!$D$2:$D$21*Config_Equipamentos!$F$2:$F$21*Config_Equipamentos!$M$2:$M$21) -> 0.2 | J16: =SUMPRODUCT((Config_Equipamentos!$B$2:$B$21="Irrigação/Lavoura")*(Config_Equipamentos!$C$2:$C$21="Quadro de automação")*Config_Equipamentos!$D$2:$D$21*Config_Equipamentos!$F$2:$F$21*Config_Equipamentos!$N$2:$N$21) -> 0.2 | K16: =SUMPRODUCT((Config_Equipamentos!$B$2:$B$21="Irrigação/Lavoura")*(Config_Equipamentos!$C$2:$C$21="Quadro de automação")*Config_Equipamentos!$D$2:$D$21*Config_Equipamentos!$F$2:$F$21*Config_Equipamentos!$O$2:$O$21) -> 0.2 | L16: =SUMPRODUCT((Config_Equipamentos!$B$2:$B$21="Irrigação/Lavoura")*(Config_Equipamentos!$C$2:$C$21="Quadro de automação")*Config_Equipamentos!$D$2:$D$21*Config_Equipamentos!$F$2:$F$21*Config_Equipamentos!$P$2:$P$21) -> 0.2 | M16: =SUMPRODUCT((Config_Equipamentos!$B$2:$B$21="Irrigação/Lavoura")*(Config_Equipamentos!$C$2:$C$21="Quadro de automação")*Config_Equipamentos!$D$2:$D$21*Config_Equipamentos!$F$2:$F$21*Config_Equipamentos!$Q$2:$Q$21) -> 0.2 | N16: =SUMPRODUCT((Config_Equipamentos!$B$2:$B$21="Irrigação/Lavoura")*(Config_Equipamentos!$C$2:$C$21="Quadro de automação")*Config_Equipamentos!$D$2:$D$21*Config_Equipamentos!$F$2:$F$21*Config_Equipamentos!$R$2:$R$21) -> 0.2 | O16: =SUMPRODUCT((Config_Equipamentos!$B$2:$B$21="Irrigação/Lavoura")*(Config_Equipamentos!$C$2:$C$21="Quadro de automação")*Config_Equipamentos!$D$2:$D$21*Config_Equipamentos!$F$2:$F$21*Config_Equipamentos!$S$2:$S$21) -> 0.2 | P16: =SUMPRODUCT((Config_Equipamentos!$B$2:$B$21="Irrigação/Lavoura")*(Config_Equipamentos!$C$2:$C$21="Quadro de automação")*Config_Equipamentos!$D$2:$D$21*Config_Equipamentos!$F$2:$F$21*Config_Equipamentos!$T$2:$T$21) -> 0.2 | Q16: =SUMPRODUCT((Config_Equipamentos!$B$2:$B$21="Irrigação/Lavoura")*(Config_Equipamentos!$C$2:$C$21="Quadro de automação")*Config_Equipamentos!$D$2:$D$21*Config_Equipamentos!$F$2:$F$21*Config_Equipamentos!$U$2:$U$21) -> 0.2 | R16: =SUMPRODUCT((Config_Equipamentos!$B$2:$B$21="Irrigação/Lavoura")*(Config_Equipamentos!$C$2:$C$21="Quadro de automação")*Config_Equipamentos!$D$2:$D$21*Config_Equipamentos!$F$2:$F$21*Config_Equipamentos!$V$2:$V$21) -> 0.2 | S16: =SUMPRODUCT((Config_Equipamentos!$B$2:$B$21="Irrigação/Lavoura")*(Config_Equipamentos!$C$2:$C$21="Quadro de automação")*Config_Equipamentos!$D$2:$D$21*Config_Equipamentos!$F$2:$F$21*Config_Equipamentos!$W$2:$W$21) -> 0.2 | T16: =SUMPRODUCT((Config_Equipamentos!$B$2:$B$21="Irrigação/Lavoura")*(Config_Equipamentos!$C$2:$C$21="Quadro de automação")*Config_Equipamentos!$D$2:$D$21*Config_Equipamentos!$F$2:$F$21*Config_Equipamentos!$X$2:$X$21) -> 0.2 | U16: =SUMPRODUCT((Config_Equipamentos!$B$2:$B$21="Irrigação/Lavoura")*(Config_Equipamentos!$C$2:$C$21="Quadro de automação")*Config_Equipamentos!$D$2:$D$21*Config_Equipamentos!$F$2:$F$21*Config_Equipamentos!$Y$2:$Y$21) -> 0.2 | V16: =SUMPRODUCT((Config_Equipamentos!$B$2:$B$21="Irrigação/Lavoura")*(Config_Equipamentos!$C$2:$C$21="Quadro de automação")*Config_Equipamentos!$D$2:$D$21*Config_Equipamentos!$F$2:$F$21*Config_Equipamentos!$Z$2:$Z$21) -> 0.2 | W16: =SUMPRODUCT((Config_Equipamentos!$B$2:$B$21="Irrigação/Lavoura")*(Config_Equipamentos!$C$2:$C$21="Quadro de automação")*Config_Equipamentos!$D$2:$D$21*Config_Equipamentos!$F$2:$F$21*Config_Equipamentos!$AA$2:$AA$21) -> 0.2 | X16: =SUMPRODUCT((Config_Equipamentos!$B$2:$B$21="Irrigação/Lavoura")*(Config_Equipamentos!$C$2:$C$21="Quadro de automação")*Config_Equipamentos!$D$2:$D$21*Config_Equipamentos!$F$2:$F$21*Config_Equipamentos!$AB$2:$AB$21) -> 0.2 | Y16: =SUMPRODUCT((Config_Equipamentos!$B$2:$B$21="Irrigação/Lavoura")*(Config_Equipamentos!$C$2:$C$21="Quadro de automação")*Config_Equipamentos!$D$2:$D$21*Config_Equipamentos!$F$2:$F$21*Config_Equipamentos!$AC$2:$AC$21) -> 0.2 | Z16: =SUMPRODUCT((Config_Equipamentos!$B$2:$B$21="Irrigação/Lavoura")*(Config_Equipamentos!$C$2:$C$21="Quadro de automação")*Config_Equipamentos!$D$2:$D$21*Config_Equipamentos!$F$2:$F$21*Config_Equipamentos!$AD$2:$AD$21) -> 0.2 | AA16: =SUM(C16:Z16) -> 4.8

Sheet Config_Geracao
A1: ID | B1: Tipo | C1: Pot_Nominal_kWp | D1: Eficiência_% | E1: Ref_Conversão | F1: Gen_Max_kW | G1: Gen_Min_kW | K1: Observação
A2: SOL-PEQ | B2: Solar FV | C2: 10 | D2: 85 | E2: 1100 | F2: 10 | G2: 0.5 | K2: Solar: E = GHI_Ref em W/m² (irradiação nominal)
A3: SOL-MED | B3: Solar FV | C3: 40 | D3: 87 | E3: 1100 | F3: 40 | G3: 3 | K3: Solar: E = GHI_Ref em W/m² (irradiação nominal)
A4: EOL-PEQ | B4: Eólica | C4: 3 | D4: 85 | E4: 10 | F4: 3 | G4: 0.1 | K4: Eólica: E = Vento_Ref em m/s (vento de pleno aproveitamento)
A5: EOL-MED | B5: Eólica | C5: 10 | D5: 87 | E5: 10 | F5: 10 | G5: 0.3 | K5: Eólica: E = Vento_Ref em m/s (vento de pleno aproveitamento)

Sheet Geracao
A1: Data_Hora | B1: Hora | C1: ID_Fazenda | D1: ID_Gerador | E1: Tipo | F1: Energia_Gerada_kWh
A2: 45658 | B2: 0 | C2: FAZ-001 | D2: SOL-PEQ | E2: Solar FV | F2: =MIN(Config_Geracao!$F$2,IF((Base_Irradiacao!$D$2/Config_Geracao!$E$2)*Base_Irradiacao!$G$2*Config_Geracao!$C$2*(Config_Geracao!$D$2/100)<Config_Geracao!$G$2,0,MAX(Config_Geracao!$G$2,(Base_Irradiacao!$D$2/Config_Geracao!$E$2)*Base_Irradiacao!$G$2*Config_Geracao!$C$2*(Config_Geracao!$D$2/100)))) -> 0
A3: 45658 | B3: 0 | C3: FAZ-001 | D3: EOL-PEQ | E3: Eólica | F3: =MIN(Config_Geracao!$F$4,IF(Base_Irradiacao!$H$2*Config_Geracao!$C$4*(Config_Geracao!$D$4/100)<Config_Geracao!$G$4,0,MAX(Config_Geracao!$G$4,Base_Irradiacao!$H$2*Config_Geracao!$C$4*(Config_Geracao!$D$4/100)))) -> 1.04652
A4: 45658 | B4: 0 | C4: FAZ-002 | D4: SOL-MED | E4: Solar FV | F4: =MIN(Config_Geracao!$F$3,IF((Base_Irradiacao!$D$2/Config_Geracao!$E$3)*Base_Irradiacao!$G$2*Config_Geracao!$C$3*(Config_Geracao!$D$3/100)<Config_Geracao!$G$3,0,MAX(Config_Geracao!$G$3,(Base_Irradiacao!$D$2/Config_Geracao!$E$3)*Base_Irradiacao!$G$2*Config_Geracao!$C$3*(Config_Geracao!$D$3/100)))) -> 0
A5: 45658 | B5: 0 | C5: FAZ-002 | D5: EOL-MED | E5: Eólica | F5: =MIN(Config_Geracao!$F$5,IF(Base_Irradiacao!$H$2*Config_Geracao!$C$5*(Config_Geracao!$D$5/100)<Config_Geracao!$G$5,0,MAX(Config_Geracao!$G$5,Base_Irradiacao!$H$2*Config_Geracao!$C$5*(Config_Geracao!$D$5/100)))) -> 3.57048
A6: 45658.042 | B6: 1 | C6: FAZ-001 | D6: SOL-PEQ | E6: Solar FV | F6: =MIN(Config_Geracao!$F$2,IF((Base_Irradiacao!$D$3/Config_Geracao!$E$2)*Base_Irradiacao!$G$3*Config_Geracao!$C$2*(Config_Geracao!$D$2/100)<Config_Geracao!$G$2,0,MAX(Config_Geracao!$G$2,(Base_Irradiacao!$D$3/Config_Geracao!$E$2)*Base_Irradiacao!$G$3*Config_Geracao!$C$2*(Config_Geracao!$D$2/100)))) -> 0
A7: 45658.042 | B7: 1 | C7: FAZ-001 | D7: EOL-PEQ | E7: Eólica | F7: =MIN(Config_Geracao!$F$4,IF(Base_Irradiacao!$H$3*Config_Geracao!$C$4*(Config_Geracao!$D$4/100)<Config_Geracao!$G$4,0,MAX(Config_Geracao!$G$4,Base_Irradiacao!$H$3*Config_Geracao!$C$4*(Config_Geracao!$D$4/100)))) -> 0.9471975
A8: 45658.042 | B8: 1 | C8: FAZ-002 | D8: SOL-MED | E8: Solar FV | F8: =MIN(Config_Geracao!$F$3,IF((Base_Irradiacao!$D$3/Config_Geracao!$E$3)*Base_Irradiacao!$G$3*Config_Geracao!$C$3*(Config_Geracao!$D$3/100)<Config_Geracao!$G$3,0,MAX(Config_Geracao!$G$3,(Base_Irradiacao!$D$3/Config_Geracao!$E$3)*Base_Irradiacao!$G$3*Config_Geracao!$C$3*(Config_Geracao!$D$3/100)))) -> 0
A9: 45658.042 | B9: 1 | C9: FAZ-002 | D9: EOL-MED | E9: Eólica | F9: =MIN(Config_Geracao!$F$5,IF(Base_Irradiacao!$H$3*Config_Geracao!$C$5*(Config_Geracao!$D$5/100)<Config_Geracao!$G$5,0,MAX(Config_Geracao!$G$5,Base_Irradiacao!$H$3*Config_Geracao!$C$5*(Config_Geracao!$D$5/100)))) -> 3.231615
A10: 45658.083 | B10: 2 | C10: FAZ-001 | D10: SOL-PEQ | E10: Solar FV | F10: =MIN(Config_Geracao!$F$2,IF((Base_Irradiacao!$D$4/Config_Geracao!$E$2)*Base_Irradiacao!$G$4*Config_Geracao!$C$2*(Config_Geracao!$D$2/100)<Config_Geracao!$G$2,0,MAX(Config_Geracao!$G$2,(Base_Irradiacao!$D$4/Config_Geracao!$E$2)*Base_Irradiacao!$G$4*Config_Geracao!$C$2*(Config_Geracao!$D$2/100)))) -> 0
A11: 45658.083 | B11: 2 | C11: FAZ-001 | D11: EOL-PEQ | E11: Eólica | F11: =MIN(Config_Geracao!$F$4,IF(Base_Irradiacao!$H$4*Config_Geracao!$C$4*(Config_Geracao!$D$4/100)<Config_Geracao!$G$4,0,MAX(Config_Geracao!$G$4,Base_Irradiacao!$H$4*Config_Geracao!$C$4*(Config_Geracao!$D$4/100)))) -> 0.741285
A12: 45658.083 | B12: 2 | C12: FAZ-002 | D12: SOL-MED | E12: Solar FV | F12: =MIN(Config_Geracao!$F$3,IF((Base_Irradiacao!$D$4/Config_Geracao!$E$3)*Base_Irradiacao!$G$4*Config_Geracao!$C$3*(Config_Geracao!$D$3/100)<Config_Geracao!$G$3,0,MAX(Config_Geracao!$G$3,(Base_Irradiacao!$D$4/Config_Geracao!$E$3)*Base_Irradiacao!$G$4*Config_Geracao!$C$3*(Config_Geracao!$D$3/100)))) -> 0
A13: 45658.083 | B13: 2 | C13: FAZ-002 | D13: EOL-MED | E13: Eólica | F13: =MIN(Config_Geracao!$F$5,IF(Base_Irradiacao!$H$4*Config_Geracao!$C$5*(Config_Geracao!$D$5/100)<Config_Geracao!$G$5,0,MAX(Config_Geracao!$G$5,Base_Irradiacao!$H$4*Config_Geracao!$C$5*(Config_Geracao!$D$5/100)))) -> 2.52909
A14: 45658.125 | B14: 3 | C14: FAZ-001 | D14: SOL-PEQ | E14: Solar FV | F14: =MIN(Config_Geracao!$F$2,IF((Base_Irradiacao!$D$5/Config_Geracao!$E$2)*Base_Irradiacao!$G$5*Config_Geracao!$C$2*(Config_Geracao!$D$2/100)<Config_Geracao!$G$2,0,MAX(Config_Geracao!$G$2,(Base_Irradiacao!$D$5/Config_Geracao!$E$2)*Base_Irradiacao!$G$5*Config_Geracao!$C$2*(Config_Geracao!$D$2/100)))) -> 0
A15: 45658.125 | B15: 3 | C15: FAZ-001 | D15: EOL-PEQ | E15: Eólica | F15: =MIN(Config_Geracao!$F$4,IF(Base_Irradiacao!$H$5*Config_Geracao!$C$4*(Config_Geracao!$D$4/100)<Config_Geracao!$G$4,0,MAX(Config_Geracao!$G$4,Base_Irradiacao!$H$5*Config_Geracao!$C$4*(Config_Geracao!$D$4/100)))) -> 1.2136725
A16: 45658.125 | B16: 3 | C16: FAZ-002 | D16: SOL-MED | E16: Solar FV | F16: =MIN(Config_Geracao!$F$3,IF((Base_Irradiacao!$D$5/Config_Geracao!$E$3)*Base_Irradiacao!$G$5*Config_Geracao!$C$3*(Config_Geracao!$D$3/100)<Config_Geracao!$G$3,0,MAX(Config_Geracao!$G$3,(Base_Irradiacao!$D$5/Config_Geracao!$E$3)*Base_Irradiacao!$G$5*Config_Geracao!$C$3*(Config_Geracao!$D$3/100)))) -> 0
A17: 45658.125 | B17: 3 | C17: FAZ-002 | D17: EOL-MED | E17: Eólica | F17: =MIN(Config_Geracao!$F$5,IF(Base_Irradiacao!$H$5*Config_Geracao!$C$5*(Config_Geracao!$D$5/100)<Config_Geracao!$G$5,0,MAX(Config_Geracao!$G$5,Base_Irradiacao!$H$5*Config_Geracao!$C$5*(Config_Geracao!$D$5/100)))) -> 4.140765
A18: 45658.167 | B18: 4 | C18: FAZ-001 | D18: SOL-PEQ | E18: Solar FV | F18: =MIN(Config_Geracao!$F$2,IF((Base_Irradiacao!$D$6/Config_Geracao!$E$2)*Base_Irradiacao!$G$6*Config_Geracao!$C$2*(Config_Geracao!$D$2/100)<Config_Geracao!$G$2,0,MAX(Config_Geracao!$G$2,(Base_Irradiacao!$D$6/Config_Geracao!$E$2)*Base_Irradiacao!$G$6*Config_Geracao!$C$2*(Config_Geracao!$D$2/100)))) -> 0
A19: 45658.167 | B19: 4 | C19: FAZ-001 | D19: EOL-PEQ | E19: Eólica | F19: =MIN(Config_Geracao!$F$4,IF(Base_Irradiacao!$H$6*Config_Geracao!$C$4*(Config_Geracao!$D$4/100)<Config_Geracao!$G$4,0,MAX(Config_Geracao!$G$4,Base_Irradiacao!$H$6*Config_Geracao!$C$4*(Config_Geracao!$D$4/100)))) -> 0.731595
A20: 45658.167 | B20: 4 | C20: FAZ-002 | D20: SOL-MED | E20: Solar FV | F20: =MIN(Config_Geracao!$F$3,IF((Base_Irradiacao!$D$6/Config_Geracao!$E$3)*Base_Irradiacao!$G$6*Config_Geracao!$C$3*(Config_Geracao!$D$3/100)<Config_Geracao!$G$3,0,MAX(Config_Geracao!$G$3,(Base_Irradiacao!$D$6/Config_Geracao!$E$3)*Base_Irradiacao!$G$6*Config_Geracao!$C$3*(Config_Geracao!$D$3/100)))) -> 0
A21: 45658.167 | B21: 4 | C21: FAZ-002 | D21: EOL-MED | E21: Eólica | F21: =MIN(Config_Geracao!$F$5,IF(Base_Irradiacao!$H$6*Config_Geracao!$C$5*(Config_Geracao!$D$5/100)<Config_Geracao!$G$5,0,MAX(Config_Geracao!$G$5,Base_Irradiacao!$H$6*Config_Geracao!$C$5*(Config_Geracao!$D$5/100)))) -> 2.49603
A22: 45658.208 | B22: 5 | C22: FAZ-001 | D22: SOL-PEQ | E22: Solar FV | F22: =MIN(Config_Geracao!$F$2,IF((Base_Irradiacao!$D$7/Config_Geracao!$E$2)*Base_Irradiacao!$G$7*Config_Geracao!$C$2*(Config_Geracao!$D$2/100)<Config_Geracao!$G$2,0,MAX(Config_Geracao!$G$2,(Base_Irradiacao!$D$7/Config_Geracao!$E$2)*Base_Irradiacao!$G$7*Config_Geracao!$C$2*(Config_Geracao!$D$2/100)))) -> 0
A23: 45658.208 | B23: 5 | C23: FAZ-001 | D23: EOL-PEQ | E23: Eólica | F23: =MIN(Config_Geracao!$F$4,IF(Base_Irradiacao!$H$7*Config_Geracao!$C$4*(Config_Geracao!$D$4/100)<Config_Geracao!$G$4,0,MAX(Config_Geracao!$G$4,Base_Irradiacao!$H$7*Config_Geracao!$C$4*(Config_Geracao!$D$4/100)))) -> 0.7752
A24: 45658.208 | B24: 5 | C24: FAZ-002 | D24: SOL-MED | E24: Solar FV | F24: =MIN(Config_Geracao!$F$3,IF((Base_Irradiacao!$D$7/Config_Geracao!$E$3)*Base_Irradiacao!$G$7*Config_Geracao!$C$3*(Config_Geracao!$D$3/100)<Config_Geracao!$G$3,0,MAX(Config_Geracao!$G$3,(Base_Irradiacao!$D$7/Config_Geracao!$E$3)*Base_Irradiacao!$G$7*Config_Geracao!$C$3*(Config_Geracao!$D$3/100)))) -> 0
A25: 45658.208 | B25: 5 | C25: FAZ-002 | D25: EOL-MED | E25: Eólica | F25: =MIN(Config_Geracao!$F$5,IF(Base_Irradiacao!$H$7*Config_Geracao!$C$5*(Config_Geracao!$D$5/100)<Config_Geracao!$G$5,0,MAX(Config_Geracao!$G$5,Base_Irradiacao!$H$7*Config_Geracao!$C$5*(Config_Geracao!$D$5/100)))) -> 2.6448
A26: 45658.25 | B26: 6 | C26: FAZ-001 | D26: SOL-PEQ | E26: Solar FV | F26: =MIN(Config_Geracao!$F$2,IF((Base_Irradiacao!$D$8/Config_Geracao!$E$2)*Base_Irradiacao!$G$8*Config_Geracao!$C$2*(Config_Geracao!$D$2/100)<Config_Geracao!$G$2,0,MAX(Config_Geracao!$G$2,(Base_Irradiacao!$D$8/Config_Geracao!$E$2)*Base_Irradiacao!$G$8*Config_Geracao!$C$2*(Config_Geracao!$D$2/100)))) -> 0.67316136
A27: 45658.25 | B27: 6 | C27: FAZ-001 | D27: EOL-PEQ | E27: Eólica | F27: =MIN(Config_Geracao!$F$4,IF(Base_Irradiacao!$H$8*Config_Geracao!$C$4*(Config_Geracao!$D$4/100)<Config_Geracao!$G$4,0,MAX(Config_Geracao!$G$4,Base_Irradiacao!$H$8*Config_Geracao!$C$4*(Config_Geracao!$D$4/100)))) -> 0.7146375
A28: 45658.25 | B28: 6 | C28: FAZ-002 | D28: SOL-MED | E28: Solar FV | F28: =MIN(Config_Geracao!$F$3,IF((Base_Irradiacao!$D$8/Config_Geracao!$E$3)*Base_Irradiacao!$G$8*Config_Geracao!$C$3*(Config_Geracao!$D$3/100)<Config_Geracao!$G$3,0,MAX(Config_Geracao!$G$3,(Base_Irradiacao!$D$8/Config_Geracao!$E$3)*Base_Irradiacao!$G$8*Config_Geracao!$C$3*(Config_Geracao!$D$3/100)))) -> 0
A29: 45658.25 | B29: 6 | C29: FAZ-002 | D29: EOL-MED | E29: Eólica | F29: =MIN(Config_Geracao!$F$5,IF(Base_Irradiacao!$H$8*Config_Geracao!$C$5*(Config_Geracao!$D$5/100)<Config_Geracao!$G$5,0,MAX(Config_Geracao!$G$5,Base_Irradiacao!$H$8*Config_Geracao!$C$5*(Config_Geracao!$D$5/100)))) -> 2.438175
A30: 45658.292 | B30: 7 | C30: FAZ-001 | D30: SOL-PEQ | E30: Solar FV | F30: =MIN(Config_Geracao!$F$2,IF((Base_Irradiacao!$D$9/Config_Geracao!$E$2)*Base_Irradiacao!$G$9*Config_Geracao!$C$2*(Config_Geracao!$D$2/100)<Config_Geracao!$G$2,0,MAX(Config_Geracao!$G$2,(Base_Irradiacao!$D$9/Config_Geracao!$E$2)*Base_Irradiacao!$G$9*Config_Geracao!$C$2*(Config_Geracao!$D$2/100)))) -> 1.7698932
A31: 45658.292 | B31: 7 | C31: FAZ-001 | D31: EOL-PEQ | E31: Eólica | F31: =MIN(Config_Geracao!$F$4,IF(Base_Irradiacao!$H$9*Config_Geracao!$C$4*(Config_Geracao!$D$4/100)<Config_Geracao!$G$4,0,MAX(Config_Geracao!$G$4,Base_Irradiacao!$H$9*Config_Geracao!$C$4*(Config_Geracao!$D$4/100)))) -> 0.857565
A32: 45658.292 | B32: 7 | C32: FAZ-002 | D32: SOL-MED | E32: Solar FV | F32: =MIN(Config_Geracao!$F$3,IF((Base_Irradiacao!$D$9/Config_Geracao!$E$3)*Base_Irradiacao!$G$9*Config_Geracao!$C$3*(Config_Geracao!$D$3/100)<Config_Geracao!$G$3,0,MAX(Config_Geracao!$G$3,(Base_Irradiacao!$D$9/Config_Geracao!$E$3)*Base_Irradiacao!$G$9*Config_Geracao!$C$3*(Config_Geracao!$D$3/100)))) -> 7.2461509
A33: 45658.292 | B33: 7 | C33: FAZ-002 | D33: EOL-MED | E33: Eólica | F33: =MIN(Config_Geracao!$F$5,IF(Base_Irradiacao!$H$9*Config_Geracao!$C$5*(Config_Geracao!$D$5/100)<Config_Geracao!$G$5,0,MAX(Config_Geracao!$G$5,Base_Irradiacao!$H$9*Config_Geracao!$C$5*(Config_Geracao!$D$5/100)))) -> 2.92581
A34: 45658.333 | B34: 8 | C34: FAZ-001 | D34: SOL-PEQ | E34: Solar FV | F34: =MIN(Config_Geracao!$F$2,IF((Base_Irradiacao!$D$10/Config_Geracao!$E$2)*Base_Irradiacao!$G$10*Config_Geracao!$C$2*(Config_Geracao!$D$2/100)<Config_Geracao!$G$2,0,MAX(Config_Geracao!$G$2,(Base_Irradiacao!$D$10/Config_Geracao!$E$2)*Base_Irradiacao!$G$10*Config_Geracao!$C$2*(Config_Geracao!$D$2/100)))) -> 1.8139386
A35: 45658.333 | B35: 8 | C35: FAZ-001 | D35: EOL-PEQ | E35: Eólica | F35: =MIN(Config_Geracao!$F$4,IF(Base_Irradiacao!$H$10*Config_Geracao!$C$4*(Config_Geracao!$D$4/100)<Config_Geracao!$G$4,0,MAX(Config_Geracao!$G$4,Base_Irradiacao!$H$10*Config_Geracao!$C$4*(Config_Geracao!$D$4/100)))) -> 0.712215
A36: 45658.333 | B36: 8 | C36: FAZ-002 | D36: SOL-MED | E36: Solar FV | F36: =MIN(Config_Geracao!$F$3,IF((Base_Irradiacao!$D$10/Config_Geracao!$E$3)*Base_Irradiacao!$G$10*Config_Geracao!$C$3*(Config_Geracao!$D$3/100)<Config_Geracao!$G$3,0,MAX(Config_Geracao!$G$3,(Base_Irradiacao!$D$10/Config_Geracao!$E$3)*Base_Irradiacao!$G$10*Config_Geracao!$C$3*(Config_Geracao!$D$3/100)))) -> 7.4264782
A37: 45658.333 | B37: 8 | C37: FAZ-002 | D37: EOL-MED | E37: Eólica | F37: =MIN(Config_Geracao!$F$5,IF(Base_Irradiacao!$H$10*Config_Geracao!$C$5*(Config_Geracao!$D$5/100)<Config_Geracao!$G$5,0,MAX(Config_Geracao!$G$5,Base_Irradiacao!$H$10*Config_Geracao!$C$5*(Config_Geracao!$D$5/100)))) -> 2.42991
A38: 45658.375 | B38: 9 | C38: FAZ-001 | D38: SOL-PEQ | E38: Solar FV | F38: =MIN(Config_Geracao!$F$2,IF((Base_Irradiacao!$D$11/Config_Geracao!$E$2)*Base_Irradiacao!$G$11*Config_Geracao!$C$2*(Config_Geracao!$D$2/100)<Config_Geracao!$G$2,0,MAX(Config_Geracao!$G$2,(Base_Irradiacao!$D$11/Config_Geracao!$E$2)*Base_Irradiacao!$G$11*Config_Geracao!$C$2*(Config_Geracao!$D$2/100)))) -> 4.0389682
A39: 45658.375 | B39: 9 | C39: FAZ-001 | D39: EOL-PEQ | E39: Eólica | F39: =MIN(Config_Geracao!$F$4,IF(Base_Irradiacao!$H$11*Config_Geracao!$C$4*(Config_Geracao!$D$4/100)<Config_Geracao!$G$4,0,MAX(Config_Geracao!$G$4,Base_Irradiacao!$H$11*Config_Geracao!$C$4*(Config_Geracao!$D$4/100)))) -> 0.508725
A40: 45658.375 | B40: 9 | C40: FAZ-002 | D40: SOL-MED | E40: Solar FV | F40: =MIN(Config_Geracao!$F$3,IF((Base_Irradiacao!$D$11/Config_Geracao!$E$3)*Base_Irradiacao!$G$11*Config_Geracao!$C$3*(Config_Geracao!$D$3/100)<Config_Geracao!$G$3,0,MAX(Config_Geracao!$G$3,(Base_Irradiacao!$D$11/Config_Geracao!$E$3)*Base_Irradiacao!$G$11*Config_Geracao!$C$3*(Config_Geracao!$D$3/100)))) -> 16.536011
A41: 45658.375 | B41: 9 | C41: FAZ-002 | D41: EOL-MED | E41: Eólica | F41: =MIN(Config_Geracao!$F$5,IF(Base_Irradiacao!$H$11*Config_Geracao!$C$5*(Config_Geracao!$D$5/100)<Config_Geracao!$G$5,0,MAX(Config_Geracao!$G$5,Base_Irradiacao!$H$11*Config_Geracao!$C$5*(Config_Geracao!$D$5/100)))) -> 1.73565
A42: 45658.417 | B42: 10 | C42: FAZ-001 | D42: SOL-PEQ | E42: Solar FV | F42: =MIN(Config_Geracao!$F$2,IF((Base_Irradiacao!$D$12/Config_Geracao!$E$2)*Base_Irradiacao!$G$12*Config_Geracao!$C$2*(Config_Geracao!$D$2/100)<Config_Geracao!$G$2,0,MAX(Config_Geracao!$G$2,(Base_Irradiacao!$D$12/Config_Geracao!$E$2)*Base_Irradiacao!$G$12*Config_Geracao!$C$2*(Config_Geracao!$D$2/100)))) -> 7.0839773
A43: 45658.417 | B43: 10 | C43: FAZ-001 | D43: EOL-PEQ | E43: Eólica | F43: =MIN(Config_Geracao!$F$4,IF(Base_Irradiacao!$H$12*Config_Geracao!$C$4*(Config_Geracao!$D$4/100)<Config_Geracao!$G$4,0,MAX(Config_Geracao!$G$4,Base_Irradiacao!$H$12*Config_Geracao!$C$4*(Config_Geracao!$D$4/100)))) -> 0.4917675
A44: 45658.417 | B44: 10 | C44: FAZ-002 | D44: SOL-MED | E44: Solar FV | F44: =MIN(Config_Geracao!$F$3,IF((Base_Irradiacao!$D$12/Config_Geracao!$E$3)*Base_Irradiacao!$G$12*Config_Geracao!$C$3*(Config_Geracao!$D$3/100)<Config_Geracao!$G$3,0,MAX(Config_Geracao!$G$3,(Base_Irradiacao!$D$12/Config_Geracao!$E$3)*Base_Irradiacao!$G$12*Config_Geracao!$C$3*(Config_Geracao!$D$3/100)))) -> 29.002636
A45: 45658.417 | B45: 10 | C45: FAZ-002 | D45: EOL-MED | E45: Eólica | F45: =MIN(Config_Geracao!$F$5,IF(Base_Irradiacao!$H$12*Config_Geracao!$C$5*(Config_Geracao!$D$5/100)<Config_Geracao!$G$5,0,MAX(Config_Geracao!$G$5,Base_Irradiacao!$H$12*Config_Geracao!$C$5*(Config_Geracao!$D$5/100)))) -> 1.677795
A46: 45658.458 | B46: 11 | C46: FAZ-001 | D46: SOL-PEQ | E46: Solar FV | F46: =MIN(Config_Geracao!$F$2,IF((Base_Irradiacao!$D$13/Config_Geracao!$E$2)*Base_Irradiacao!$G$13*Config_Geracao!$C$2*(Config_Geracao!$D$2/100)<Config_Geracao!$G$2,0,MAX(Config_Geracao!$G$2,(Base_Irradiacao!$D$13/Config_Geracao!$E$2)*Base_Irradiacao!$G$13*Config_Geracao!$C$2*(Config_Geracao!$D$2/100)))) -> 7.3592614
A47: 45658.458 | B47: 11 | C47: FAZ-001 | D47: EOL-PEQ | E47: Eólica | F47: =MIN(Config_Geracao!$F$4,IF(Base_Irradiacao!$H$13*Config_Geracao!$C$4*(Config_Geracao!$D$4/100)<Config_Geracao!$G$4,0,MAX(Config_Geracao!$G$4,Base_Irradiacao!$H$13*Config_Geracao!$C$4*(Config_Geracao!$D$4/100)))) -> 0.6613425
A48: 45658.458 | B48: 11 | C48: FAZ-002 | D48: SOL-MED | E48: Solar FV | F48: =MIN(Config_Geracao!$F$3,IF((Base_Irradiacao!$D$13/Config_Geracao!$E$3)*Base_Irradiacao!$G$13*Config_Geracao!$C$3*(Config_Geracao!$D$3/100)<Config_Geracao!$G$3,0,MAX(Config_Geracao!$G$3,(Base_Irradiacao!$D$13/Config_Geracao!$E$3)*Base_Irradiacao!$G$13*Config_Geracao!$C$3*(Config_Geracao!$D$3/100)))) -> 30.129682
A49: 45658.458 | B49: 11 | C49: FAZ-002 | D49: EOL-MED | E49: Eólica | F49: =MIN(Config_Geracao!$F$5,IF(Base_Irradiacao!$H$13*Config_Geracao!$C$5*(Config_Geracao!$D$5/100)<Config_Geracao!$G$5,0,MAX(Config_Geracao!$G$5,Base_Irradiacao!$H$13*Config_Geracao!$C$5*(Config_Geracao!$D$5/100)))) -> 2.256345
A50: 45658.5 | B50: 12 | C50: FAZ-001 | D50: SOL-PEQ | E50: Solar FV | F50: =MIN(Config_Geracao!$F$2,IF((Base_Irradiacao!$D$14/Config_Geracao!$E$2)*Base_Irradiacao!$G$14*Config_Geracao!$C$2*(Config_Geracao!$D$2/100)<Config_Geracao!$G$2,0,MAX(Config_Geracao!$G$2,(Base_Irradiacao!$D$14/Config_Geracao!$E$2)*Base_Irradiacao!$G$14*Config_Geracao!$C$2*(Config_Geracao!$D$2/100)))) -> 7.8679864
A51: 45658.5 | B51: 12 | C51: FAZ-001 | D51: EOL-PEQ | E51: Eólica | F51: =MIN(Config_Geracao!$F$4,IF(Base_Irradiacao!$H$14*Config_Geracao!$C$4*(Config_Geracao!$D$4/100)<Config_Geracao!$G$4,0,MAX(Config_Geracao!$G$4,Base_Irradiacao!$H$14*Config_Geracao!$C$4*(Config_Geracao!$D$4/100)))) -> 0.5063025
A52: 45658.5 | B52: 12 | C52: FAZ-002 | D52: SOL-MED | E52: Solar FV | F52: =MIN(Config_Geracao!$F$3,IF((Base_Irradiacao!$D$14/Config_Geracao!$E$3)*Base_Irradiacao!$G$14*Config_Geracao!$C$3*(Config_Geracao!$D$3/100)<Config_Geracao!$G$3,0,MAX(Config_Geracao!$G$3,(Base_Irradiacao!$D$14/Config_Geracao!$E$3)*Base_Irradiacao!$G$14*Config_Geracao!$C$3*(Config_Geracao!$D$3/100)))) -> 32.212462
A53: 45658.5 | B53: 12 | C53: FAZ-002 | D53: EOL-MED | E53: Eólica | F53: =MIN(Config_Geracao!$F$5,IF(Base_Irradiacao!$H$14*Config_Geracao!$C$5*(Config_Geracao!$D$5/100)<Config_Geracao!$G$5,0,MAX(Config_Geracao!$G$5,Base_Irradiacao!$H$14*Config_Geracao!$C$5*(Config_Geracao!$D$5/100)))) -> 1.727385
A54: 45658.542 | B54: 13 | C54: FAZ-001 | D54: SOL-PEQ | E54: Solar FV | F54: =MIN(Config_Geracao!$F$2,IF((Base_Irradiacao!$D$15/Config_Geracao!$E$2)*Base_Irradiacao!$G$15*Config_Geracao!$C$2*(Config_Geracao!$D$2/100)<Config_Geracao!$G$2,0,MAX(Config_Geracao!$G$2,(Base_Irradiacao!$D$15/Config_Geracao!$E$2)*Base_Irradiacao!$G$15*Config_Geracao!$C$2*(Config_Geracao!$D$2/100)))) -> 5.1158795
A55: 45658.542 | B55: 13 | C55: FAZ-001 | D55: EOL-PEQ | E55: Eólica | F55: =MIN(Config_Geracao!$F$4,IF(Base_Irradiacao!$H$15*Config_Geracao!$C$4*(Config_Geracao!$D$4/100)<Config_Geracao!$G$4,0,MAX(Config_Geracao!$G$4,Base_Irradiacao!$H$15*Config_Geracao!$C$4*(Config_Geracao!$D$4/100)))) -> 0.56202
A56: 45658.542 | B56: 13 | C56: FAZ-002 | D56: SOL-MED | E56: Solar FV | F56: =MIN(Config_Geracao!$F$3,IF((Base_Irradiacao!$D$15/Config_Geracao!$E$3)*Base_Irradiacao!$G$15*Config_Geracao!$C$3*(Config_Geracao!$D$3/100)<Config_Geracao!$G$3,0,MAX(Config_Geracao!$G$3,(Base_Irradiacao!$D$15/Config_Geracao!$E$3)*Base_Irradiacao!$G$15*Config_Geracao!$C$3*(Config_Geracao!$D$3/100)))) -> 20.945013
A57: 45658.542 | B57: 13 | C57: FAZ-002 | D57: EOL-MED | E57: Eólica | F57: =MIN(Config_Geracao!$F$5,IF(Base_Irradiacao!$H$15*Config_Geracao!$C$5*(Config_Geracao!$D$5/100)<Config_Geracao!$G$5,0,MAX(Config_Geracao!$G$5,Base_Irradiacao!$H$15*Config_Geracao!$C$5*(Config_Geracao!$D$5/100)))) -> 1.91748
A58: 45658.583 | B58: 14 | C58: FAZ-001 | D58: SOL-PEQ | E58: Solar FV | F58: =MIN(Config_Geracao!$F$2,IF((Base_Irradiacao!$D$16/Config_Geracao!$E$2)*Base_Irradiacao!$G$16*Config_Geracao!$C$2*(Config_Geracao!$D$2/100)<Config_Geracao!$G$2,0,MAX(Config_Geracao!$G$2,(Base_Irradiacao!$D$16/Config_Geracao!$E$2)*Base_Irradiacao!$G$16*Config_Geracao!$C$2*(Config_Geracao!$D$2/100)))) -> 6.7125273
A59: 45658.583 | B59: 14 | C59: FAZ-001 | D59: EOL-PEQ | E59: Eólica | F59: =MIN(Config_Geracao!$F$4,IF(Base_Irradiacao!$H$16*Config_Geracao!$C$4*(Config_Geracao!$D$4/100)<Config_Geracao!$G$4,0,MAX(Config_Geracao!$G$4,Base_Irradiacao!$H$16*Config_Geracao!$C$4*(Config_Geracao!$D$4/100)))) -> 0.5208375
A60: 45658.583 | B60: 14 | C60: FAZ-002 | D60: SOL-MED | E60: Solar FV | F60: =MIN(Config_Geracao!$F$3,IF((Base_Irradiacao!$D$16/Config_Geracao!$E$3)*Base_Irradiacao!$G$16*Config_Geracao!$C$3*(Config_Geracao!$D$3/100)<Config_Geracao!$G$3,0,MAX(Config_Geracao!$G$3,(Base_Irradiacao!$D$16/Config_Geracao!$E$3)*Base_Irradiacao!$G$16*Config_Geracao!$C$3*(Config_Geracao!$D$3/100)))) -> 27.481876
A61: 45658.583 | B61: 14 | C61: FAZ-002 | D61: EOL-MED | E61: Eólica | F61: =MIN(Config_Geracao!$F$5,IF(Base_Irradiacao!$H$16*Config_Geracao!$C$5*(Config_Geracao!$D$5/100)<Config_Geracao!$G$5,0,MAX(Config_Geracao!$G$5,Base_Irradiacao!$H$16*Config_Geracao!$C$5*(Config_Geracao!$D$5/100)))) -> 1.776975
A62: 45658.625 | B62: 15 | C62: FAZ-001 | D62: SOL-PEQ | E62: Solar FV | F62: =MIN(Config_Geracao!$F$2,IF((Base_Irradiacao!$D$17/Config_Geracao!$E$2)*Base_Irradiacao!$G$17*Config_Geracao!$C$2*(Config_Geracao!$D$2/100)<Config_Geracao!$G$2,0,MAX(Config_Geracao!$G$2,(Base_Irradiacao!$D$17/Config_Geracao!$E$2)*Base_Irradiacao!$G$17*Config_Geracao!$C$2*(Config_Geracao!$D$2/100)))) -> 5.7677523
A63: 45658.625 | B63: 15 | C63: FAZ-001 | D63: EOL-PEQ | E63: Eólica | F63: =MIN(Config_Geracao!$F$4,IF(Base_Irradiacao!$H$17*Config_Geracao!$C$4*(Config_Geracao!$D$4/100)<Config_Geracao!$G$4,0,MAX(Config_Geracao!$G$4,Base_Irradiacao!$H$17*Config_Geracao!$C$4*(Config_Geracao!$D$4/100)))) -> 0.8018475
A64: 45658.625 | B64: 15 | C64: FAZ-002 | D64: SOL-MED | E64: Solar FV | F64: =MIN(Config_Geracao!$F$3,IF((Base_Irradiacao!$D$17/Config_Geracao!$E$3)*Base_Irradiacao!$G$17*Config_Geracao!$C$3*(Config_Geracao!$D$3/100)<Config_Geracao!$G$3,0,MAX(Config_Geracao!$G$3,(Base_Irradiacao!$D$17/Config_Geracao!$E$3)*Base_Irradiacao!$G$17*Config_Geracao!$C$3*(Config_Geracao!$D$3/100)))) -> 23.613856
A65: 45658.625 | B65: 15 | C65: FAZ-002 | D65: EOL-MED | E65: Eólica | F65: =MIN(Config_Geracao!$F$5,IF(Base_Irradiacao!$H$17*Config_Geracao!$C$5*(Config_Geracao!$D$5/100)<Config_Geracao!$G$5,0,MAX(Config_Geracao!$G$5,Base_Irradiacao!$H$17*Config_Geracao!$C$5*(Config_Geracao!$D$5/100)))) -> 2.735715
A66: 45658.667 | B66: 16 | C66: FAZ-001 | D66: SOL-PEQ | E66: Solar FV | F66: =MIN(Config_Geracao!$F$2,IF((Base_Irradiacao!$D$18/Config_Geracao!$E$2)*Base_Irradiacao!$G$18*Config_Geracao!$C$2*(Config_Geracao!$D$2/100)<Config_Geracao!$G$2,0,MAX(Config_Geracao!$G$2,(Base_Irradiacao!$D$18/Config_Geracao!$E$2)*Base_Irradiacao!$G$18*Config_Geracao!$C$2*(Config_Geracao!$D$2/100)))) -> 4.9360273
A67: 45658.667 | B67: 16 | C67: FAZ-001 | D67: EOL-PEQ | E67: Eólica | F67: =MIN(Config_Geracao!$F$4,IF(Base_Irradiacao!$H$18*Config_Geracao!$C$4*(Config_Geracao!$D$4/100)<Config_Geracao!$G$4,0,MAX(Config_Geracao!$G$4,Base_Irradiacao!$H$18*Config_Geracao!$C$4*(Config_Geracao!$D$4/100)))) -> 0.9665775
A68: 45658.667 | B68: 16 | C68: FAZ-002 | D68: SOL-MED | E68: Solar FV | F68: =MIN(Config_Geracao!$F$3,IF((Base_Irradiacao!$D$18/Config_Geracao!$E$3)*Base_Irradiacao!$G$18*Config_Geracao!$C$3*(Config_Geracao!$D$3/100)<Config_Geracao!$G$3,0,MAX(Config_Geracao!$G$3,(Base_Irradiacao!$D$18/Config_Geracao!$E$3)*Base_Irradiacao!$G$18*Config_Geracao!$C$3*(Config_Geracao!$D$3/100)))) -> 20.208676
A69: 45658.667 | B69: 16 | C69: FAZ-002 | D69: EOL-MED | E69: Eólica | F69: =MIN(Config_Geracao!$F$5,IF(Base_Irradiacao!$H$18*Config_Geracao!$C$5*(Config_Geracao!$D$5/100)<Config_Geracao!$G$5,0,MAX(Config_Geracao!$G$5,Base_Irradiacao!$H$18*Config_Geracao!$C$5*(Config_Geracao!$D$5/100)))) -> 3.297735
A70: 45658.708 | B70: 17 | C70: FAZ-001 | D70: SOL-PEQ | E70: Solar FV | F70: =MIN(Config_Geracao!$F$2,IF((Base_Irradiacao!$D$19/Config_Geracao!$E$2)*Base_Irradiacao!$G$19*Config_Geracao!$C$2*(Config_Geracao!$D$2/100)<Config_Geracao!$G$2,0,MAX(Config_Geracao!$G$2,(Base_Irradiacao!$D$19/Config_Geracao!$E$2)*Base_Irradiacao!$G$19*Config_Geracao!$C$2*(Config_Geracao!$D$2/100)))) -> 3.2990045
A71: 45658.708 | B71: 17 | C71: FAZ-001 | D71: EOL-PEQ | E71: Eólica | F71: =MIN(Config_Geracao!$F$4,IF(Base_Irradiacao!$H$19*Config_Geracao!$C$4*(Config_Geracao!$D$4/100)<Config_Geracao!$G$4,0,MAX(Config_Geracao!$G$4,Base_Irradiacao!$H$19*Config_Geracao!$C$4*(Config_Geracao!$D$4/100)))) -> 0.5789775
A72: 45658.708 | B72: 17 | C72: FAZ-002 | D72: SOL-MED | E72: Solar FV | F72: =MIN(Config_Geracao!$F$3,IF((Base_Irradiacao!$D$19/Config_Geracao!$E$3)*Base_Irradiacao!$G$19*Config_Geracao!$C$3*(Config_Geracao!$D$3/100)<Config_Geracao!$G$3,0,MAX(Config_Geracao!$G$3,(Base_Irradiacao!$D$19/Config_Geracao!$E$3)*Base_Irradiacao!$G$19*Config_Geracao!$C$3*(Config_Geracao!$D$3/100)))) -> 13.506513
A73: 45658.708 | B73: 17 | C73: FAZ-002 | D73: EOL-MED | E73: Eólica | F73: =MIN(Config_Geracao!$F$5,IF(Base_Irradiacao!$H$19*Config_Geracao!$C$5*(Config_Geracao!$D$5/100)<Config_Geracao!$G$5,0,MAX(Config_Geracao!$G$5,Base_Irradiacao!$H$19*Config_Geracao!$C$5*(Config_Geracao!$D$5/100)))) -> 1.975335
A74: 45658.75 | B74: 18 | C74: FAZ-001 | D74: SOL-PEQ | E74: Solar FV | F74: =MIN(Config_Geracao!$F$2,IF((Base_Irradiacao!$D$20/Config_Geracao!$E$2)*Base_Irradiacao!$G$20*Config_Geracao!$C$2*(Config_Geracao!$D$2/100)<Config_Geracao!$G$2,0,MAX(Config_Geracao!$G$2,(Base_Irradiacao!$D$20/Config_Geracao!$E$2)*Base_Irradiacao!$G$20*Config_Geracao!$C$2*(Config_Geracao!$D$2/100)))) -> 1.6546409
A75: 45658.75 | B75: 18 | C75: FAZ-001 | D75: EOL-PEQ | E75: Eólica | F75: =MIN(Config_Geracao!$F$4,IF(Base_Irradiacao!$H$20*Config_Geracao!$C$4*(Config_Geracao!$D$4/100)<Config_Geracao!$G$4,0,MAX(Config_Geracao!$G$4,Base_Irradiacao!$H$20*Config_Geracao!$C$4*(Config_Geracao!$D$4/100)))) -> 0.5159925
A76: 45658.75 | B76: 18 | C76: FAZ-002 | D76: SOL-MED | E76: Solar FV | F76: =MIN(Config_Geracao!$F$3,IF((Base_Irradiacao!$D$20/Config_Geracao!$E$3)*Base_Irradiacao!$G$20*Config_Geracao!$C$3*(Config_Geracao!$D$3/100)<Config_Geracao!$G$3,0,MAX(Config_Geracao!$G$3,(Base_Irradiacao!$D$20/Config_Geracao!$E$3)*Base_Irradiacao!$G$20*Config_Geracao!$C$3*(Config_Geracao!$D$3/100)))) -> 6.7742945
A77: 45658.75 | B77: 18 | C77: FAZ-002 | D77: EOL-MED | E77: Eólica | F77: =MIN(Config_Geracao!$F$5,IF(Base_Irradiacao!$H$20*Config_Geracao!$C$5*(Config_Geracao!$D$5/100)<Config_Geracao!$G$5,0,MAX(Config_Geracao!$G$5,Base_Irradiacao!$H$20*Config_Geracao!$C$5*(Config_Geracao!$D$5/100)))) -> 1.760445
A78: 45658.792 | B78: 19 | C78: FAZ-001 | D78: SOL-PEQ | E78: Solar FV | F78: =MIN(Config_Geracao!$F$2,IF((Base_Irradiacao!$D$21/Config_Geracao!$E$2)*Base_Irradiacao!$G$21*Config_Geracao!$C$2*(Config_Geracao!$D$2/100)<Config_Geracao!$G$2,0,MAX(Config_Geracao!$G$2,(Base_Irradiacao!$D$21/Config_Geracao!$E$2)*Base_Irradiacao!$G$21*Config_Geracao!$C$2*(Config_Geracao!$D$2/100)))) -> 0
A79: 45658.792 | B79: 19 | C79: FAZ-001 | D79: EOL-PEQ | E79: Eólica | F79: =MIN(Config_Geracao!$F$4,IF(Base_Irradiacao!$H$21*Config_Geracao!$C$4*(Config_Geracao!$D$4/100)<Config_Geracao!$G$4,0,MAX(Config_Geracao!$G$4,Base_Irradiacao!$H$21*Config_Geracao!$C$4*(Config_Geracao!$D$4/100)))) -> 0.64923
A80: 45658.792 | B80: 19 | C80: FAZ-002 | D80: SOL-MED | E80: Solar FV | F80: =MIN(Config_Geracao!$F$3,IF((Base_Irradiacao!$D$21/Config_Geracao!$E$3)*Base_Irradiacao!$G$21*Config_Geracao!$C$3*(Config_Geracao!$D$3/100)<Config_Geracao!$G$3,0,MAX(Config_Geracao!$G$3,(Base_Irradiacao!$D$21/Config_Geracao!$E$3)*Base_Irradiacao!$G$21*Config_Geracao!$C$3*(Config_Geracao!$D$3/100)))) -> 0
A81: 45658.792 | B81: 19 | C81: FAZ-002 | D81: EOL-MED | E81: Eólica | F81: =MIN(Config_Geracao!$F$5,IF(Base_Irradiacao!$H$21*Config_Geracao!$C$5*(Config_Geracao!$D$5/100)<Config_Geracao!$G$5,0,MAX(Config_Geracao!$G$5,Base_Irradiacao!$H$21*Config_Geracao!$C$5*(Config_Geracao!$D$5/100)))) -> 2.21502
A82: 45658.833 | B82: 20 | C82: FAZ-001 | D82: SOL-PEQ | E82: Solar FV | F82: =MIN(Config_Geracao!$F$2,IF((Base_Irradiacao!$D$22/Config_Geracao!$E$2)*Base_Irradiacao!$G$22*Config_Geracao!$C$2*(Config_Geracao!$D$2/100)<Config_Geracao!$G$2,0,MAX(Config_Geracao!$G$2,(Base_Irradiacao!$D$22/Config_Geracao!$E$2)*Base_Irradiacao!$G$22*Config_Geracao!$C$2*(Config_Geracao!$D$2/100)))) -> 0
A83: 45658.833 | B83: 20 | C83: FAZ-001 | D83: EOL-PEQ | E83: Eólica | F83: =MIN(Config_Geracao!$F$4,IF(Base_Irradiacao!$H$22*Config_Geracao!$C$4*(Config_Geracao!$D$4/100)<Config_Geracao!$G$4,0,MAX(Config_Geracao!$G$4,Base_Irradiacao!$H$22*Config_Geracao!$C$4*(Config_Geracao!$D$4/100)))) -> 0.663765
A84: 45658.833 | B84: 20 | C84: FAZ-002 | D84: SOL-MED | E84: Solar FV | F84: =MIN(Config_Geracao!$F$3,IF((Base_Irradiacao!$D$22/Config_Geracao!$E$3)*Base_Irradiacao!$G$22*Config_Geracao!$C$3*(Config_Geracao!$D$3/100)<Config_Geracao!$G$3,0,MAX(Config_Geracao!$G$3,(Base_Irradiacao!$D$22/Config_Geracao!$E$3)*Base_Irradiacao!$G$22*Config_Geracao!$C$3*(Config_Geracao!$D$3/100)))) -> 0
A85: 45658.833 | B85: 20 | C85: FAZ-002 | D85: EOL-MED | E85: Eólica | F85: =MIN(Config_Geracao!$F$5,IF(Base_Irradiacao!$H$22*Config_Geracao!$C$5*(Config_Geracao!$D$5/100)<Config_Geracao!$G$5,0,MAX(Config_Geracao!$G$5,Base_Irradiacao!$H$22*Config_Geracao!$C$5*(Config_Geracao!$D$5/100)))) -> 2.26461
A86: 45658.875 | B86: 21 | C86: FAZ-001 | D86: SOL-PEQ | E86: Solar FV | F86: =MIN(Config_Geracao!$F$2,IF((Base_Irradiacao!$D$23/Config_Geracao!$E$2)*Base_Irradiacao!$G$23*Config_Geracao!$C$2*(Config_Geracao!$D$2/100)<Config_Geracao!$G$2,0,MAX(Config_Geracao!$G$2,(Base_Irradiacao!$D$23/Config_Geracao!$E$2)*Base_Irradiacao!$G$23*Config_Geracao!$C$2*(Config_Geracao!$D$2/100)))) -> 0
A87: 45658.875 | B87: 21 | C87: FAZ-001 | D87: EOL-PEQ | E87: Eólica | F87: =MIN(Config_Geracao!$F$4,IF(Base_Irradiacao!$H$23*Config_Geracao!$C$4*(Config_Geracao!$D$4/100)<Config_Geracao!$G$4,0,MAX(Config_Geracao!$G$4,Base_Irradiacao!$H$23*Config_Geracao!$C$4*(Config_Geracao!$D$4/100)))) -> 0.7533975
A88: 45658.875 | B88: 21 | C88: FAZ-002 | D88: SOL-MED | E88: Solar FV | F88: =MIN(Config_Geracao!$F$3,IF((Base_Irradiacao!$D$23/Config_Geracao!$E$3)*Base_Irradiacao!$G$23*Config_Geracao!$C$3*(Config_Geracao!$D$3/100)<Config_Geracao!$G$3,0,MAX(Config_Geracao!$G$3,(Base_Irradiacao!$D$23/Config_Geracao!$E$3)*Base_Irradiacao!$G$23*Config_Geracao!$C$3*(Config_Geracao!$D$3/100)))) -> 0
A89: 45658.875 | B89: 21 | C89: FAZ-002 | D89: EOL-MED | E89: Eólica | F89: =MIN(Config_Geracao!$F$5,IF(Base_Irradiacao!$H$23*Config_Geracao!$C$5*(Config_Geracao!$D$5/100)<Config_Geracao!$G$5,0,MAX(Config_Geracao!$G$5,Base_Irradiacao!$H$23*Config_Geracao!$C$5*(Config_Geracao!$D$5/100)))) -> 2.570415
A90: 45658.917 | B90: 22 | C90: FAZ-001 | D90: SOL-PEQ | E90: Solar FV | F90: =MIN(Config_Geracao!$F$2,IF((Base_Irradiacao!$D$24/Config_Geracao!$E$2)*Base_Irradiacao!$G$24*Config_Geracao!$C$2*(Config_Geracao!$D$2/100)<Config_Geracao!$G$2,0,MAX(Config_Geracao!$G$2,(Base_Irradiacao!$D$24/Config_Geracao!$E$2)*Base_Irradiacao!$G$24*Config_Geracao!$C$2*(Config_Geracao!$D$2/100)))) -> 0
A91: 45658.917 | B91: 22 | C91: FAZ-001 | D91: EOL-PEQ | E91: Eólica | F91: =MIN(Config_Geracao!$F$4,IF(Base_Irradiacao!$H$24*Config_Geracao!$C$4*(Config_Geracao!$D$4/100)<Config_Geracao!$G$4,0,MAX(Config_Geracao!$G$4,Base_Irradiacao!$H$24*Config_Geracao!$C$4*(Config_Geracao!$D$4/100)))) -> 0.7340175
A92: 45658.917 | B92: 22 | C92: FAZ-002 | D92: SOL-MED | E92: Solar FV | F92: =MIN(Config_Geracao!$F$3,IF((Base_Irradiacao!$D$24/Config_Geracao!$E$3)*Base_Irradiacao!$G$24*Config_Geracao!$C$3*(Config_Geracao!$D$3/100)<Config_Geracao!$G$3,0,MAX(Config_Geracao!$G$3,(Base_Irradiacao!$D$24/Config_Geracao!$E$3)*Base_Irradiacao!$G$24*Config_Geracao!$C$3*(Config_Geracao!$D$3/100)))) -> 0
A93: 45658.917 | B93: 22 | C93: FAZ-002 | D93: EOL-MED | E93: Eólica | F93: =MIN(Config_Geracao!$F$5,IF(Base_Irradiacao!$H$24*Config_Geracao!$C$5*(Config_Geracao!$D$5/100)<Config_Geracao!$G$5,0,MAX(Config_Geracao!$G$5,Base_Irradiacao!$H$24*Config_Geracao!$C$5*(Config_Geracao!$D$5/100)))) -> 2.504295
A94: 45658.958 | B94: 23 | C94: FAZ-001 | D94: SOL-PEQ | E94: Solar FV | F94: =MIN(Config_Geracao!$F$2,IF((Base_Irradiacao!$D$25/Config_Geracao!$E$2)*Base_Irradiacao!$G$25*Config_Geracao!$C$2*(Config_Geracao!$D$2/100)<Config_Geracao!$G$2,0,MAX(Config_Geracao!$G$2,(Base_Irradiacao!$D$25/Config_Geracao!$E$2)*Base_Irradiacao!$G$25*Config_Geracao!$C$2*(Config_Geracao!$D$2/100)))) -> 0
A95: 45658.958 | B95: 23 | C95: FAZ-001 | D95: EOL-PEQ | E95: Eólica | F95: =MIN(Config_Geracao!$F$4,IF(Base_Irradiacao!$H$25*Config_Geracao!$C$4*(Config_Geracao!$D$4/100)<Config_Geracao!$G$4,0,MAX(Config_Geracao!$G$4,Base_Irradiacao!$H$25*Config_Geracao!$C$4*(Config_Geracao!$D$4/100)))) -> 0.8987475
A96: 45658.958 | B96: 23 | C96: FAZ-002 | D96: SOL-MED | E96: Solar FV | F96: =MIN(Config_Geracao!$F$3,IF((Base_Irradiacao!$D$25/Config_Geracao!$E$3)*Base_Irradiacao!$G$25*Config_Geracao!$C$3*(Config_Geracao!$D$3/100)<Config_Geracao!$G$3,0,MAX(Config_Geracao!$G$3,(Base_Irradiacao!$D$25/Config_Geracao!$E$3)*Base_Irradiacao!$G$25*Config_Geracao!$C$3*(Config_Geracao!$D$3/100)))) -> 0
A97: 45658.958 | B97: 23 | C97: FAZ-002 | D97: EOL-MED | E97: Eólica | F97: =MIN(Config_Geracao!$F$5,IF(Base_Irradiacao!$H$25*Config_Geracao!$C$5*(Config_Geracao!$D$5/100)<Config_Geracao!$G$5,0,MAX(Config_Geracao!$G$5,Base_Irradiacao!$H$25*Config_Geracao!$C$5*(Config_Geracao!$D$5/100)))) -> 3.066315
A98: 45659 | B98: 0 | C98: FAZ-001 | D98: SOL-PEQ | E98: Solar FV | F98: =MIN(Config_Geracao!$F$2,IF((Base_Irradiacao!$D$26/Config_Geracao!$E$2)*Base_Irradiacao!$G$26*Config_Geracao!$C$2*(Config_Geracao!$D$2/100)<Config_Geracao!$G$2,0,MAX(Config_Geracao!$G$2,(Base_Irradiacao!$D$26/Config_Geracao!$E$2)*Base_Irradiacao!$G$26*Config_Geracao!$C$2*(Config_Geracao!$D$2/100)))) -> 0
A99: 45659 | B99: 0 | C99: FAZ-001 | D99: EOL-PEQ | E99: Eólica | F99: =MIN(Config_Geracao!$F$4,IF(Base_Irradiacao!$H$26*Config_Geracao!$C$4*(Config_Geracao!$D$4/100)<Config_Geracao!$G$4,0,MAX(Config_Geracao!$G$4,Base_Irradiacao!$H$26*Config_Geracao!$C$4*(Config_Geracao!$D$4/100)))) -> 1.303305
A100: 45659 | B100: 0 | C100: FAZ-002 | D100: SOL-MED | E100: Solar FV | F100: =MIN(Config_Geracao!$F$3,IF((Base_Irradiacao!$D$26/Config_Geracao!$E$3)*Base_Irradiacao!$G$26*Config_Geracao!$C$3*(Config_Geracao!$D$3/100)<Config_Geracao!$G$3,0,MAX(Config_Geracao!$G$3,(Base_Irradiacao!$D$26/Config_Geracao!$E$3)*Base_Irradiacao!$G$26*Config_Geracao!$C$3*(Config_Geracao!$D$3/100)))) -> 0
...

Sheet Tarifa
A1: Hora | B1: Energia_R$/kWh | C1: Tipo
A2: 00:00 | B2: 0.6813 | C2: Fora Ponta
A3: 01:00 | B3: 0.6813 | C3: Fora Ponta
A4: 02:00 | B4: 0.6813 | C4: Fora Ponta
A5: 03:00 | B5: 0.6813 | C5: Fora Ponta
A6: 04:00 | B6: 0.6813 | C6: Fora Ponta
A7: 05:00 | B7: 0.6813 | C7: Fora Ponta
A8: 06:00 | B8: 0.6813 | C8: Fora Ponta
A9: 07:00 | B9: 0.6813 | C9: Fora Ponta
A10: 08:00 | B10: 0.6813 | C10: Fora Ponta
A11: 09:00 | B11: 0.6813 | C11: Fora Ponta
A12: 10:00 | B12: 0.6813 | C12: Fora Ponta
A13: 11:00 | B13: 0.6813 | C13: Fora Ponta
... A25: 23:00 | B25: 0.6813 | C25: Fora Ponta

Sheet Cadastro_Fazenda
A1: ID_Fazenda | B1: Nome | C1: Tamanho_ha | D1: Tipo | E1: Tem_Escritório | F1: Tem_Cozinha | G1: Tem_Quarto | H1: Tem_Irrigação | I1: ID_Solar | J1: ID_Eólica | K1: ID_Bateria
A2: FAZ-001 | B2: Fazenda Boa Vista | C2: 80 | D2: Pequena | E2: 1 | F2: 1 | G2: 1 | H2: 1 | I2: SOL-PEQ | J2: EOL-PEQ | K2: BAT-001
A3: FAZ-002 | B3: Fazenda São Pedro | C3: 320 | D3: Média | E3: 1 | F3: 1 | G3: 1 | H3: 1 | I3: SOL-MED | J3: EOL-MED | K3: BAT-001

Sheet Cadastro_Cargas
A1: ID_Fazenda | B1: Nome_Fazenda | C1: Carga | D1: Tipo | E1: Cons_Max_kW | F1: Cons_Min_kW | G1: Status
A2: =Cadastro_Fazenda!A2 -> FAZ-001 | B2: =Cadastro_Fazenda!B2 -> Fazenda Boa Vista | C2: Pivô | D2: Agrícola | E2: =MAX(SUMPRODUCT((Perfil_Area!$A$3:$A$16=C2)*(Perfil_Area!$B$3:$B$16=IF(Cadastro_Fazenda!$D$2="Pequena","Pequena","Média"))*Perfil_Area!$C$3:$C$16),SUMPRODUCT((Perfil_Area!$A$3:$A$16=C2)*(Perfil_Area!$B$3:$B$16=IF(Cadastro_Fazenda!$D$2="Pequena","Pequena","Média"))*Perfil_Area!$D$3:$D$16),SUMPRODUCT((Perfil_Area!$A$3:$A$16=C2)*(Perfil_Area!$B$3:$B$16=IF(Cadastro_Fazenda!$D$2="Pequena","Pequena","Média"))*Perfil_Area!$N$3:$N$16)) -> 4 | F2: =E2*0.3 -> 1.2 | G2: =IF(E2=0,"Inativo",IF(Cadastro_Fazenda!$H$2=1,"Ativo","Inativo")) -> Ativo
A3: =Cadastro_Fazenda!A2 -> FAZ-001 | B3: =Cadastro_Fazenda!B2 -> Fazenda Boa Vista | C3: Bomba_Aux | D3: Agrícola | E3: =MAX(SUMPRODUCT((Perfil_Area!$A$3:$A$16=C3)*(Perfil_Area!$B$3:$B$16=IF(Cadastro_Fazenda!$D$2="Pequena","Pequena","Média"))*Perfil_Area!$C$3:$C$16),SUMPRODUCT((Perfil_Area!$A$3:$A$16=C3)*(Perfil_Area!$B$3:$B$16=IF(Cadastro_Fazenda!$D$2="Pequena","Pequena","Média"))*Perfil_Area!$D$3:$D$16),SUMPRODUCT((Perfil_Area!$A$3:$A$16=C3)*(Perfil_Area!$B$3:$B$16=IF(Cadastro_Fazenda!$D$2="Pequena","Pequena","Média"))*Perfil_Area!$N$3:$N$16)) -> 0 | F3: =E3*0.3 -> 0 | G3: =IF(E3=0,"Inativo",IF(Cadastro_Fazenda!$H$2=1,"Ativo","Inativo")) -> Inativo
A4: =Cadastro_Fazenda!A2 -> FAZ-001 | B4: =Cadastro_Fazenda!B2 -> Fazenda Boa Vista | C4: Secadora | D4: Agrícola | E4: =MAX(SUMPRODUCT((Perfil_Area!$A$3:$A$16=C4)*(Perfil_Area!$B$3:$B$16=IF(Cadastro_Fazenda!$D$2="Pequena","Pequena","Média"))*Perfil_Area!$C$3:$C$16),SUMPRODUCT((Perfil_Area!$A$3:$A$16=C4)*(Perfil_Area!$B$3:$B$16=IF(Cadastro_Fazenda!$D$2="Pequena","Pequena","Média"))*Perfil_Area!$D$3:$D$16),SUMPRODUCT((Perfil_Area!$A$3:$A$16=C4)*(Perfil_Area!$B$3:$B$16=IF(Cadastro_Fazenda!$D$2="Pequena","Pequena","Média"))*Perfil_Area!$N$3:$N$16)) -> 0 | F4: =E4*0.3 -> 0 | G4: =IF(E4=0,"Inativo",IF(Cadastro_Fazenda!$H$2=1,"Ativo","Inativo")) -> Inativo
A5: =Cadastro_Fazenda!A2 -> FAZ-001 | B5: =Cadastro_Fazenda!B2 -> Fazenda Boa Vista | C5: Quadro_Auto | D5: Agrícola | E5: =MAX(SUMPRODUCT((Perfil_Area!$A$3:$A$16=C5)*(Perfil_Area!$B$3:$B$16=IF(Cadastro_Fazenda!$D$2="Pequena","Pequena","Média"))*Perfil_Area!$C$3:$C$16),SUMPRODUCT((Perfil_Area!$A$3:$A$16=C5)*(Perfil_Area!$B$3:$B$16=IF(Cadastro_Fazenda!$D$2="Pequena","Pequena","Média"))*Perfil_Area!$D$3:$D$16),SUMPRODUCT((Perfil_Area!$A$3:$A$16=C5)*(Perfil_Area!$B$3:$B$16=IF(Cadastro_Fazenda!$D$2="Pequena","Pequena","Média"))*Perfil_Area!$N$3:$N$16)) -> 0.2 | F5: =E5*0.3 -> 0.06 | G5: =IF(E5=0,"Inativo",IF(Cadastro_Fazenda!$H$2=1,"Ativo","Inativo")) -> Ativo
A6: =Cadastro_Fazenda!A2 -> FAZ-001 | B6: =Cadastro_Fazenda!B2 -> Fazenda Boa Vista | C6: Escritório | D6: Sede | E6: =MAX(SUMPRODUCT((Perfil_Area!$A$3:$A$16=C6)*(Perfil_Area!$B$3:$B$16=IF(Cadastro_Fazenda!$D$2="Pequena","Pequena","Média"))*Perfil_Area!$C$3:$C$16),SUMPRODUCT((Perfil_Area!$A$3:$A$16=C6)*(Perfil_Area!$B$3:$B$16=IF(Cadastro_Fazenda!$D$2="Pequena","Pequena","Média"))*Perfil_Area!$D$3:$D$16),SUMPRODUCT((Perfil_Area!$A$3:$A$16=C6)*(Perfil_Area!$B$3:$B$16=IF(Cadastro_Fazenda!$D$2="Pequena","Pequena","Média"))*Perfil_Area!$N$3:$N$16)) -> 2.02 | F6: =E6*0.3 -> 0.606 | G6: =IF(E6=0,"Inativo",IF(Cadastro_Fazenda!$E$2=1,"Ativo","Inativo")) -> Ativo
A7: =Cadastro_Fazenda!A2 -> FAZ-001 | B7: =Cadastro_Fazenda!B2 -> Fazenda Boa Vista | C7: Cozinha | D7: Sede | E7: =MAX(SUMPRODUCT((Perfil_Area!$A$3:$A$16=C7)*(Perfil_Area!$B$3:$B$16=IF(Cadastro_Fazenda!$D$2="Pequena","Pequena","Média"))*Perfil_Area!$C$3:$C$16),SUMPRODUCT((Perfil_Area!$A$3:$A$16=C7)*(Perfil_Area!$B$3:$B$16=IF(Cadastro_Fazenda!$D$2="Pequena","Pequena","Média"))*Perfil_Area!$D$3:$D$16),SUMPRODUCT((Perfil_Area!$A$3:$A$16=C7)*(Perfil_Area!$B$3:$B$16=IF(Cadastro_Fazenda!$D$2="Pequena","Pequena","Média"))*Perfil_Area!$N$3:$N$16)) -> 0.354 | F7: =E7*0.3 -> 0.1062 | G7: =IF(E7=0,"Inativo",IF(Cadastro_Fazenda!$F$2=1,"Ativo","Inativo")) -> Ativo
A8: =Cadastro_Fazenda!A2 -> FAZ-001 | B8: =Cadastro_Fazenda!B2 -> Fazenda Boa Vista | C8: Quarto | D8: Sede | E8: =MAX(SUMPRODUCT((Perfil_Area!$A$3:$A$16=C8)*(Perfil_Area!$B$3:$B$16=IF(Cadastro_Fazenda!$D$2="Pequena","Pequena","Média"))*Perfil_Area!$C$3:$C$16),SUMPRODUCT((Perfil_Area!$A$3:$A$16=C8)*(Perfil_Area!$B$3:$B$16=IF(Cadastro_Fazenda!$D$2="Pequena","Pequena","Média"))*Perfil_Area!$D$3:$D$16),SUMPRODUCT((Perfil_Area!$A$3:$A$16=C8)*(Perfil_Area!$B$3:$B$16=IF(Cadastro_Fazenda!$D$2="Pequena","Pequena","Média"))*Perfil_Area!$N$3:$N$16)) -> 0.176 | F8: =E8*0.3 -> 0.0528 | G8: =IF(E8=0,"Inativo",IF(Cadastro_Fazenda!$G$2=1,"Ativo","Inativo")) -> Ativo
A9: =Cadastro_Fazenda!A3 -> FAZ-002 | B9: =Cadastro_Fazenda!B3 -> Fazenda São Pedro | C9: Pivô | D9: Agrícola | E9: =MAX(SUMPRODUCT((Perfil_Area!$A$3:$A$16=C9)*(Perfil_Area!$B$3:$B$16=IF(Cadastro_Fazenda!$D$3="Pequena","Pequena","Média"))*Perfil_Area!$C$3:$C$16),SUMPRODUCT((Perfil_Area!$A$3:$A$16=C9)*(Perfil_Area!$B$3:$B$16=IF(Cadastro_Fazenda!$D$3="Pequena","Pequena","Média"))*Perfil_Area!$D$3:$D$16),SUMPRODUCT((Perfil_Area!$A$3:$A$16=C9)*(Perfil_Area!$B$3:$B$16=IF(Cadastro_Fazenda!$D$3="Pequena","Pequena","Média"))*Perfil_Area!$N$3:$N$16)) -> 8 | F9: =E9*0.3 -> 2.4 | G9: =IF(E9=0,"Inativo",IF(Cadastro_Fazenda!$H$3=1,"Ativo","Inativo")) -> Ativo
A10: =Cadastro_Fazenda!A3 -> FAZ-002 | B10: =Cadastro_Fazenda!B3 -> Fazenda São Pedro | C10: Bomba_Aux | D10: Agrícola | E10: =MAX(SUMPRODUCT((Perfil_Area!$A$3:$A$16=C10)*(Perfil_Area!$B$3:$B$16=IF(Cadastro_Fazenda!$D$3="Pequena","Pequena","Média"))*Perfil_Area!$C$3:$C$16),SUMPRODUCT((Perfil_Area!$A$3:$A$16=C10)*(Perfil_Area!$B$3:$B$16=IF(Cadastro_Fazenda!$D$3="Pequena","Pequena","Média"))*Perfil_Area!$D$3:$D$16),SUMPRODUCT((Perfil_Area!$A$3:$A$16=C10)*(Perfil_Area!$B$3:$B$16=IF(Cadastro_Fazenda!$D$3="Pequena","Pequena","Média"))*Perfil_Area!$N$3:$N$16)) -> 17.6 | F10: =E10*0.3 -> 5.28 | G10: =IF(E10=0,"Inativo",IF(Cadastro_Fazenda!$H$3=1,"Ativo","Inativo")) -> Ativo
A11: =Cadastro_Fazenda!A3 -> FAZ-002 | B11: =Cadastro_Fazenda!B3 -> Fazenda São Pedro | C11: Secadora | D11: Agrícola | E11: =MAX(SUMPRODUCT((Perfil_Area!$A$3:$A$16=C11)*(Perfil_Area!$B$3:$B$16=IF(Cadastro_Fazenda!$D$3="Pequena","Pequena","Média"))*Perfil_Area!$C$3:$C$16),SUMPRODUCT((Perfil_Area!$A$3:$A$16=C11)*(Perfil_Area!$B$3:$B$16=IF(Cadastro_Fazenda!$D$3="Pequena","Pequena","Média"))*Perfil_Area!$D$3:$D$16),SUMPRODUCT((Perfil_Area!$A$3:$A$16=C11)*(Perfil_Area!$B$3:$B$16=IF(Cadastro_Fazenda!$D$3="Pequena","Pequena","Média"))*Perfil_Area!$N$3:$N$16)) -> 2.3670134 | F11: =E11*0.3 -> 0.71010401 | G11: =IF(E11=0,"Inativo",IF(Cadastro_Fazenda!$H$3=1,"Ativo","Inativo")) -> Ativo
A12: =Cadastro_Fazenda!A3 -> FAZ-002 | B12: =Cadastro_Fazenda!B3 -> Fazenda São Pedro | C12: Quadro_Auto | D12: Agrícola | E12: =MAX(SUMPRODUCT((Perfil_Area!$A$3:$A$16=C12)*(Perfil_Area!$B$3:$B$16=IF(Cadastro_Fazenda!$D$3="Pequena","Pequena","Média"))*Perfil_Area!$C$3:$C$16),SUMPRODUCT((Perfil_Area!$A$3:$A$16=C12)*(Perfil_Area!$B$3:$B$16=IF(Cadastro_Fazenda!$D$3="Pequena","Pequena","Média"))*Perfil_Area!$D$3:$D$16),SUMPRODUCT((Perfil_Area!$A$3:$A$16=C12)*(Perfil_Area!$B$3:$B$16=IF(Cadastro_Fazenda!$D$3="Pequena","Pequena","Média"))*Perfil_Area!$N$3:$N$16)) -> 0.2 | F12: =E12*0.3 -> 0.06 | G12: =IF(E12=0,"Inativo",IF(Cadastro_Fazenda!$H$3=1,"Ativo","Inativo")) -> Ativo
A13: =Cadastro_Fazenda!A3 -> FAZ-002 | B13: =Cadastro_Fazenda!B3 -> Fazenda São Pedro | C13: Escritório | D13: Sede | E13: =MAX(SUMPRODUCT((Perfil_Area!$A$3:$A$16=C13)*(Perfil_Area!$B$3:$B$16=IF(Cadastro_Fazenda!$D$3="Pequena","Pequena","Média"))*Perfil_Area!$C$3:$C$16),SUMPRODUCT((Perfil_Area!$A$3:$A$16=C13)*(Perfil_Area!$B$3:$B$16=IF(Cadastro_Fazenda!$D$3="Pequena","Pequena","Média"))*Perfil_Area!$D$3:$D$16),SUMPRODUCT((Perfil_Area!$A$3:$A$16=C13)*(Perfil_Area!$B$3:$B$16=IF(Cadastro_Fazenda!$D$3="Pequena","Pequena","Média"))*Perfil_Area!$N$3:$N$16)) -> 3.725 | F13: =E13*0.3 -> 1.1175 | G13: =IF(E13=0,"Inativo",IF(Cadastro_Fazenda!$E$3=1,"Ativo","Inativo")) -> Ativo
A14: =Cadastro_Fazenda!A3 -> FAZ-002 | B14: =Cadastro_Fazenda!B3 -> Fazenda São Pedro | C14: Cozinha | D14: Sede | E14: =MAX(SUMPRODUCT((Perfil_Area!$A$3:$A$16=C14)*(Perfil_Area!$B$3:$B$16=IF(Cadastro_Fazenda!$D$3="Pequena","Pequena","Média"))*Perfil_Area!$C$3:$C$16),SUMPRODUCT((Perfil_Area!$A$3:$A$16=C14)*(Perfil_Area!$B$3:$B$16=IF(Cadastro_Fazenda!$D$3="Pequena","Pequena","Média"))*Perfil_Area!$D$3:$D$16),SUMPRODUCT((Perfil_Area!$A$3:$A$16=C14)*(Perfil_Area!$B$3:$B$16=IF(Cadastro_Fazenda!$D$3="Pequena","Pequena","Média"))*Perfil_Area!$N$3:$N$16)) -> 0.514 | F14: =E14*0.3 -> 0.1542 | G14: =IF(E14=0,"Inativo",IF(Cadastro_Fazenda!$F$3=1,"Ativo","Inativo")) -> Ativo
A15: =Cadastro_Fazenda!A3 -> FAZ-002 | B15: =Cadastro_Fazenda!B3 -> Fazenda São Pedro | C15: Quarto | D15: Sede | E15: =MAX(SUMPRODUCT((Perfil_Area!$A$3:$A$16=C15)*(Perfil_Area!$B$3:$B$16=IF(Cadastro_Fazenda!$D$3="Pequena","Pequena","Média"))*Perfil_Area!$C$3:$C$16),SUMPRODUCT((Perfil_Area!$A$3:$A$16=C15)*(Perfil_Area!$B$3:$B$16=IF(Cadastro_Fazenda!$D$3="Pequena","Pequena","Média"))*Perfil_Area!$D$3:$D$16),SUMPRODUCT((Perfil_Area!$A$3:$A$16=C15)*(Perfil_Area!$B$3:$B$16=IF(Cadastro_Fazenda!$D$3="Pequena","Pequena","Média"))*Perfil_Area!$N$3:$N$16)) -> 0.336 | F15: =E15*0.3 -> 0.1008 | G15: =IF(E15=0,"Inativo",IF(Cadastro_Fazenda!$G$3=1,"Ativo","Inativo")) -> Ativo
A16: FAZ-001 | B16: Fazenda Boa Vista | C16: Bateria | D16: Armazenamento | E16: =ROUND(SUMPRODUCT(($A$2:$A$8="FAZ-001")*$E$2:$E$8)*0.66/5,0)*5 -> 5 | F16: =E16*0.175 -> 0.875 | G16: Ativo
A17: FAZ-002 | B17: Fazenda São Pedro | C17: Bateria | D17: Armazenamento | E17: =ROUND(SUMPRODUCT(($A$9:$A$15="FAZ-002")*$E$9:$E$15)*0.66/5,0)*5 -> 20 | F17: =E17*0.175 -> 3.5 | G17: Ativo

Sheet Base_Irradiacao
A1: Data_Hora | B1: Mês | C1: Hora | D1: GHI_W/m² | E1: Temp_°C | F1: Vento_m/s | G1: FP | H1: Vento_Normalizado
A2: 45658 | B2: 1 | C2: 0 | D2: 0 | E2: 28.7 | F2: 4.32 | G2: 0.95 | H2: =MIN(1,F2/Config_Geracao!$E$4)*G2 -> 0.4104
A3: 45658.042 | B3: 1 | C3: 1 | D3: 0 | E3: 27.7 | F3: 3.91 | G3: 0.95 | H3: =MIN(1,F3/Config_Geracao!$E$4)*G3 -> 0.37145
A4: 45658.083 | B4: 1 | C4: 2 | D4: 0 | E4: 27.2 | F4: 3.06 | G4: 0.95 | H4: =MIN(1,F4/Config_Geracao!$E$4)*G4 -> 0.2907
A5: 45658.125 | B5: 1 | C5: 3 | D5: 0 | E5: 26.8 | F5: 5.01 | G5: 0.95 | H5: =MIN(1,F5/Config_Geracao!$E$4)*G5 -> 0.47595
A6: 45658.167 | B6: 1 | C6: 4 | D6: 0 | E6: 28.9 | F6: 3.02 | G6: 0.95 | H6: =MIN(1,F6/Config_Geracao!$E$4)*G6 -> 0.2869
A7: 45658.208 | B7: 1 | C7: 5 | D7: 15.3 | E7: 24.9 | F7: 3.2 | G7: 0.95 | H7: =MIN(1,F7/Config_Geracao!$E$4)*G7 -> 0.304
A8: 45658.25 | B8: 1 | C8: 6 | D8: 91.7 | E8: 22.4 | F8: 2.95 | G8: 0.95 | H8: =MIN(1,F8/Config_Geracao!$E$4)*G8 -> 0.28025
A9: 45658.292 | B9: 1 | C9: 7 | D9: 241.1 | E9: 25.5 | F9: 3.54 | G9: 0.95 | H9: =MIN(1,F9/Config_Geracao!$E$4)*G9 -> 0.3363
A10: 45658.333 | B10: 1 | C10: 8 | D10: 247.1 | E10: 27.2 | F10: 2.94 | G10: 0.95 | H10: =MIN(1,F10/Config_Geracao!$E$4)*G10 -> 0.2793
A11: 45658.375 | B11: 1 | C11: 9 | D11: 550.2 | E11: 28.3 | F11: 2.1 | G11: 0.95 | H11: =MIN(1,F11/Config_Geracao!$E$4)*G11 -> 0.1995
A12: 45658.417 | B12: 1 | C12: 10 | D12: 965 | E12: 30.2 | F12: 2.03 | G12: 0.95 | H12: =MIN(1,F12/Config_Geracao!$E$4)*G12 -> 0.19285
A13: 45658.458 | B13: 1 | C13: 11 | D13: 1002.5 | E13: 28.9 | F13: 2.73 | G13: 0.95 | H13: =MIN(1,F13/Config_Geracao!$E$4)*G13 -> 0.25935
... A8761: 46022.958 | B8761: 12 | C8761: 23 | D8761: 0 | E8761: 29.1 | F8761: 3.79 | G8761: 0.95 | H8761: =MIN(1,F8761/Config_Geracao!$E$4)*G8761 -> 0.36005

Sheet Cargas
A1: Data_Hora | B1: Hora | C1: ID_Fazenda | D1: Carga | E1: Tipo | F1: Consumo_kWh
A2: 45658 | B2: 0 | C2: FAZ-001 | D2: Pivô | E2: Agrícola | F2: =IF(Cadastro_Cargas!$E$2=0,0,IF(Perfil_Area!$C$9=0,0,MIN(Cadastro_Cargas!$E$2,MAX(Cadastro_Cargas!$F$2,Perfil_Area!$C$9*RANDBETWEEN(85,115)/100)))) -> 3.76
A3: 45658 | B3: 0 | C3: FAZ-001 | D3: Bomba_Aux | E3: Agrícola | F3: =IF(Cadastro_Cargas!$E$3=0,0,IF(Perfil_Area!$C$11=0,0,MIN(Cadastro_Cargas!$E$3,MAX(Cadastro_Cargas!$F$3,Perfil_Area!$C$11*RANDBETWEEN(85,115)/100)))) -> 0
A4: 45658 | B4: 0 | C4: FAZ-001 | D4: Secadora | E4: Agrícola | F4: =IF(Cadastro_Cargas!$E$4=0,0,IF(Perfil_Area!$C$13=0,0,MIN(Cadastro_Cargas!$E$4,MAX(Cadastro_Cargas!$F$4,Perfil_Area!$C$13*RANDBETWEEN(85,115)/100)))) -> 0
A5: 45658 | B5: 0 | C5: FAZ-001 | D5: Quadro_Auto | E5: Agrícola | F5: =IF(Cadastro_Cargas!$E$5=0,0,IF(Perfil_Area!$C$15=0,0,MIN(Cadastro_Cargas!$E$5,MAX(Cadastro_Cargas!$F$5,Perfil_Area!$C$15*RANDBETWEEN(85,115)/100)))) -> 0.2
A6: 45658 | B6: 0 | C6: FAZ-001 | D6: Escritório | E6: Sede | F6: =IF(Cadastro_Cargas!$E$6=0,0,IF(Perfil_Area!$C$3=0,0,MIN(Cadastro_Cargas!$E$6,MAX(Cadastro_Cargas!$F$6,Perfil_Area!$C$3*RANDBETWEEN(85,115)/100)))) -> 0.606
A7: 45658 | B7: 0 | C7: FAZ-001 | D7: Cozinha | E7: Sede | F7: =IF(Cadastro_Cargas!$E$7=0,0,IF(Perfil_Area!$C$5=0,0,MIN(Cadastro_Cargas!$E$7,MAX(Cadastro_Cargas!$F$7,Perfil_Area!$C$5*RANDBETWEEN(85,115)/100)))) -> 0.24934
A8: 45658 | B8: 0 | C8: FAZ-001 | D8: Quarto | E8: Sede | F8: =IF(Cadastro_Cargas!$E$8=0,0,IF(Perfil_Area!$C$7=0,0,MIN(Cadastro_Cargas!$E$8,MAX(Cadastro_Cargas!$F$8,Perfil_Area!$C$7*RANDBETWEEN(85,115)/100)))) -> 0.176
A9: 45658 | B9: 0 | C9: FAZ-002 | D9: Pivô | E9: Agrícola | F9: =IF(Cadastro_Cargas!$E$9=0,0,IF(Perfil_Area!$C$10=0,0,MIN(Cadastro_Cargas!$E$9,MAX(Cadastro_Cargas!$F$9,Perfil_Area!$C$10*RANDBETWEEN(85,115)/100)))) -> 8
A10: 45658 | B10: 0 | C10: FAZ-002 | D10: Bomba_Aux | E10: Agrícola | F10: =IF(Cadastro_Cargas!$E$10=0,0,IF(Perfil_Area!$C$12=0,0,MIN(Cadastro_Cargas!$E$10,MAX(Cadastro_Cargas!$F$10,Perfil_Area!$C$12*RANDBETWEEN(85,115)/100)))) -> 17.424
A11: 45658 | B11: 0 | C11: FAZ-002 | D11: Secadora | E11: Agrícola | F11: =IF(Cadastro_Cargas!$E$11=0,0,IF(Perfil_Area!$C$14=0,0,MIN(Cadastro_Cargas!$E$11,MAX(Cadastro_Cargas!$F$11,Perfil_Area!$C$14*RANDBETWEEN(85,115)/100)))) -> 2.3670134
A12: 45658 | B12: 0 | C12: FAZ-002 | D12: Quadro_Auto | E12: Agrícola | F12: =IF(Cadastro_Cargas!$E$12=0,0,IF(Perfil_Area!$C$16=0,0,MIN(Cadastro_Cargas!$E$12,MAX(Cadastro_Cargas!$F$12,Perfil_Area!$C$16*RANDBETWEEN(85,115)/100)))) -> 0.18
A13: 45658 | B13: 0 | C13: FAZ-002 | D13: Escritório | E13: Sede | F13: =IF(Cadastro_Cargas!$E$13=0,0,IF(Perfil_Area!$C$4=0,0,MIN(Cadastro_Cargas!$E$13,MAX(Cadastro_Cargas!$F$13,Perfil_Area!$C$4*RANDBETWEEN(85,115)/100)))) -> 1.1175
A14: 45658 | B14: 0 | C14: FAZ-002 | D14: Cozinha | E14: Sede | F14: =IF(Cadastro_Cargas!$E$14=0,0,IF(Perfil_Area!$C$6=0,0,MIN(Cadastro_Cargas!$E$14,MAX(Cadastro_Cargas!$F$14,Perfil_Area!$C$6*RANDBETWEEN(85,115)/100)))) -> 0.36248
A15: 45658 | B15: 0 | C15: FAZ-002 | D15: Quarto | E15: Sede | F15: =IF(Cadastro_Cargas!$E$15=0,0,IF(Perfil_Area!$C$8=0,0,MIN(Cadastro_Cargas!$E$15,MAX(Cadastro_Cargas!$F$15,Perfil_Area!$C$8*RANDBETWEEN(85,115)/100)))) -> 0.30912
A16: 45658.042 | B16: 1 | C16: FAZ-001 | D16: Pivô | E16: Agrícola | F16: =IF(Cadastro_Cargas!$E$2=0,0,IF(Perfil_Area!$D$9=0,0,MIN(Cadastro_Cargas!$E$2,MAX(Cadastro_Cargas!$F$2,Perfil_Area!$D$9*RANDBETWEEN(85,115)/100)))) -> 3.4
A17: 45658.042 | B17: 1 | C17: FAZ-001 | D17: Bomba_Aux | E17: Agrícola | F17: =IF(Cadastro_Cargas!$E$3=0,0,IF(Perfil_Area!$D$11=0,0,MIN(Cadastro_Cargas!$E$3,MAX(Cadastro_Cargas!$F$3,Perfil_Area!$D$11*RANDBETWEEN(85,115)/100)))) -> 0
A18: 45658.042 | B18: 1 | C18: FAZ-001 | D18: Secadora | E18: Agrícola | F18: =IF(Cadastro_Cargas!$E$4=0,0,IF(Perfil_Area!$D$13=0,0,MIN(Cadastro_Cargas!$E$4,MAX(Cadastro_Cargas!$F$4,Perfil_Area!$D$13*RANDBETWEEN(85,115)/100)))) -> 0
A19: 45658.042 | B19: 1 | C19: FAZ-001 | D19: Quadro_Auto | E19: Agrícola | F19: =IF(Cadastro_Cargas!$E$5=0,0,IF(Perfil_Area!$D$15=0,0,MIN(Cadastro_Cargas!$E$5,MAX(Cadastro_Cargas!$F$5,Perfil_Area!$D$15*RANDBETWEEN(85,115)/100)))) -> 0.2
A20: 45658.042 | B20: 1 | C20: FAZ-001 | D20: Escritório | E20: Sede | F20: =IF(Cadastro_Cargas!$E$6=0,0,IF(Perfil_Area!$D$3=0,0,MIN(Cadastro_Cargas!$E$6,MAX(Cadastro_Cargas!$F$6,Perfil_Area!$D$3*RANDBETWEEN(85,115)/100)))) -> 0.606
A21: 45658.042 | B21: 1 | C21: FAZ-001 | D21: Cozinha | E21: Sede | F21: =IF(Cadastro_Cargas!$E$7=0,0,IF(Perfil_Area!$D$5=0,0,MIN(Cadastro_Cargas!$E$7,MAX(Cadastro_Cargas!$F$7,Perfil_Area!$D$5*RANDBETWEEN(85,115)/100)))) -> 0.26304
A22: 45658.042 | B22: 1 | C22: FAZ-001 | D22: Quarto | E22: Sede | F22: =IF(Cadastro_Cargas!$E$8=0,0,IF(Perfil_Area!$D$7=0,0,MIN(Cadastro_Cargas!$E$8,MAX(Cadastro_Cargas!$F$8,Perfil_Area!$D$7*RANDBETWEEN(85,115)/100)))) -> 0.176
A23: 45658.042 | B23: 1 | C23: FAZ-002 | D23: Pivô | E23: Agrícola | F23: =IF(Cadastro_Cargas!$E$9=0,0,IF(Perfil_Area!$D$10=0,0,MIN(Cadastro_Cargas!$E$9,MAX(Cadastro_Cargas!$F$9,Perfil_Area!$D$10*RANDBETWEEN(85,115)/100)))) -> 8
A24: 45658.042 | B24: 1 | C24: FAZ-002 | D24: Bomba_Aux | E24: Agrícola | F24: =IF(Cadastro_Cargas!$E$10=0,0,IF(Perfil_Area!$D$12=0,0,MIN(Cadastro_Cargas!$E$10,MAX(Cadastro_Cargas!$F$10,Perfil_Area!$D$12*RANDBETWEEN(85,115)/100)))) -> 15.488
A25: 45658.042 | B25: 1 | C25: FAZ-002 | D25: Secadora | E25: Agrícola | F25: =IF(Cadastro_Cargas!$E$11=0,0,IF(Perfil_Area!$D$14=0,0,MIN(Cadastro_Cargas!$E$11,MAX(Cadastro_Cargas!$F$11,Perfil_Area!$D$14*RANDBETWEEN(85,115)/100)))) -> 2.1694502
A26: 45658.042 | B26: 1 | C26: FAZ-002 | D26: Quadro_Auto | E26: Agrícola | F26: =IF(Cadastro_Cargas!$E$12=0,0,IF(Perfil_Area!$D$16=0,0,MIN(Cadastro_Cargas!$E$12,MAX(Cadastro_Cargas!$F$12,Perfil_Area!$D$16*RANDBETWEEN(85,115)/100)))) -> 0.184
A27: 45658.042 | B27: 1 | C27: FAZ-002 | D27: Escritório | E27: Sede | F27: =IF(Cadastro_Cargas!$E$13=0,0,IF(Perfil_Area!$D$4=0,0,MIN(Cadastro_Cargas!$E$13,MAX(Cadastro_Cargas!$F$13,Perfil_Area!$D$4*RANDBETWEEN(85,115)/100)))) -> 1.1175
A28: 45658.042 | B28: 1 | C28: FAZ-002 | D28: Cozinha | E28: Sede | F28: =IF(Cadastro_Cargas!$E$14=0,0,IF(Perfil_Area!$D$6=0,0,MIN(Cadastro_Cargas!$E$14,MAX(Cadastro_Cargas!$F$14,Perfil_Area!$D$6*RANDBETWEEN(85,115)/100)))) -> 0.38218
A29: 45658.042 | B29: 1 | C29: FAZ-002 | D29: Quarto | E29: Sede | F29: =IF(Cadastro_Cargas!$E$15=0,0,IF(Perfil_Area!$D$8=0,0,MIN(Cadastro_Cargas!$E$15,MAX(Cadastro_Cargas!$F$15,Perfil_Area!$D$8*RANDBETWEEN(85,115)/100)))) -> 0.336
A30: 45658.083 | B30: 2 | C30: FAZ-001 | D30: Pivô | E30: Agrícola | F30: =IF(Cadastro_Cargas!$E$2=0,0,IF(Perfil_Area!$E$9=0,0,MIN(Cadastro_Cargas!$E$2,MAX(Cadastro_Cargas!$F$2,Perfil_Area!$E$9*RANDBETWEEN(85,115)/100)))) -> 4
A31: 45658.083 | B31: 2 | C31: FAZ-001 | D31: Bomba_Aux | E31: Agrícola | F31: =IF(Cadastro_Cargas!$E$3=0,0,IF(Perfil_Area!$E$11=0,0,MIN(Cadastro_Cargas!$E$3,MAX(Cadastro_Cargas!$F$3,Perfil_Area!$E$11*RANDBETWEEN(85,115)/100)))) -> 0
A32: 45658.083 | B32: 2 | C32: FAZ-001 | D32: Secadora | E32: Agrícola | F32: =IF(Cadastro_Cargas!$E$4=0,0,IF(Perfil_Area!$E$13=0,0,MIN(Cadastro_Cargas!$E$4,MAX(Cadastro_Cargas!$F$4,Perfil_Area!$E$13*RANDBETWEEN(85,115)/100)))) -> 0
A33: 45658.083 | B33: 2 | C33: FAZ-001 | D33: Quadro_Auto | E33: Agrícola | F33: =IF(Cadastro_Cargas!$E$5=0,0,IF(Perfil_Area!$E$15=0,0,MIN(Cadastro_Cargas!$E$5,MAX(Cadastro_Cargas!$F$5,Perfil_Area!$E$15*RANDBETWEEN(85,115)/100)))) -> 0.2
A34: 45658.083 | B34: 2 | C34: FAZ-001 | D34: Escritório | E34: Sede | F34: =IF(Cadastro_Cargas!$E$6=0,0,IF(Perfil_Area!$E$3=0,0,MIN(Cadastro_Cargas!$E$6,MAX(Cadastro_Cargas!$F$6,Perfil_Area!$E$3*RANDBETWEEN(85,115)/100)))) -> 0.606
A35: 45658.083 | B35: 2 | C35: FAZ-001 | D35: Cozinha | E35: Sede | F35: =IF(Cadastro_Cargas!$E$7=0,0,IF(Perfil_Area!$E$5=0,0,MIN(Cadastro_Cargas!$E$7,MAX(Cadastro_Cargas!$F$7,Perfil_Area!$E$5*RANDBETWEEN(85,115)/100)))) -> 0.24934
A36: 45658.083 | B36: 2 | C36: FAZ-001 | D36: Quarto | E36: Sede | F36: =IF(Cadastro_Cargas!$E$8=0,0,IF(Perfil_Area!$E$7=0,0,MIN(Cadastro_Cargas!$E$8,MAX(Cadastro_Cargas!$F$8,Perfil_Area!$E$7*RANDBETWEEN(85,115)/100)))) -> 0.176
A37: 45658.083 | B37: 2 | C37: FAZ-002 | D37: Pivô | E37: Agrícola | F37: =IF(Cadastro_Cargas!$E$9=0,0,IF(Perfil_Area!$E$10=0,0,MIN(Cadastro_Cargas!$E$9,MAX(Cadastro_Cargas!$F$9,Perfil_Area!$E$10*RANDBETWEEN(85,115)/100)))) -> 7.44
A38: 45658.083 | B38: 2 | C38: FAZ-002 | D38: Bomba_Aux | E38: Agrícola | F38: =IF(Cadastro_Cargas!$E$10=0,0,IF(Perfil_Area!$E$12=0,0,MIN(Cadastro_Cargas!$E$10,MAX(Cadastro_Cargas!$F$10,Perfil_Area!$E$12*RANDBETWEEN(85,115)/100)))) -> 0
A39: 45658.083 | B39: 2 | C39: FAZ-002 | D39: Secadora | E39: Agrícola | F39: =IF(Cadastro_Cargas!$E$11=0,0,IF(Perfil_Area!$E$14=0,0,MIN(Cadastro_Cargas!$E$11,MAX(Cadastro_Cargas!$F$11,Perfil_Area!$E$14*RANDBETWEEN(85,115)/100)))) -> 2.3670134
A40: 45658.083 | B40: 2 | C40: FAZ-002 | D40: Quadro_Auto | E40: Agrícola | F40: =IF(Cadastro_Cargas!$E$12=0,0,IF(Perfil_Area!$E$16=0,0,MIN(Cadastro_Cargas!$E$12,MAX(Cadastro_Cargas!$F$12,Perfil_Area!$E$16*RANDBETWEEN(85,115)/100)))) -> 0.2
A41: 45658.083 | B41: 2 | C41: FAZ-002 | D41: Escritório | E41: Sede | F41: =IF(Cadastro_Cargas!$E$13=0,0,IF(Perfil_Area!$E$4=0,0,MIN(Cadastro_Cargas!$E$13,MAX(Cadastro_Cargas!$F$13,Perfil_Area!$E$4*RANDBETWEEN(85,115)/100)))) -> 1.1175
A42: 45658.083 | B42: 2 | C42: FAZ-002 | D42: Cozinha | E42: Sede | F42: =IF(Cadastro_Cargas!$E$14=0,0,IF(Perfil_Area!$E$6=0,0,MIN(Cadastro_Cargas!$E$14,MAX(Cadastro_Cargas!$F$14,Perfil_Area!$E$6*RANDBETWEEN(85,115)/100)))) -> 0.4137
A43: 45658.083 | B43: 2 | C43: FAZ-002 | D43: Quarto | E43: Sede | F43: =IF(Cadastro_Cargas!$E$15=0,0,IF(Perfil_Area!$E$8=0,0,MIN(Cadastro_Cargas!$E$15,MAX(Cadastro_Cargas!$F$15,Perfil_Area!$E$8*RANDBETWEEN(85,115)/100)))) -> 0.336
A44: 45658.125 | B44: 3 | C44: FAZ-001 | D44: Pivô | E44: Agrícola | F44: =IF(Cadastro_Cargas!$E$2=0,0,IF(Perfil_Area!$F$9=0,0,MIN(Cadastro_Cargas!$E$2,MAX(Cadastro_Cargas!$F$2,Perfil_Area!$F$9*RANDBETWEEN(85,115)/100)))) -> 4
A45: 45658.125 | B45: 3 | C45: FAZ-001 | D45: Bomba_Aux | E45: Agrícola | F45: =IF(Cadastro_Cargas!$E$3=0,0,IF(Perfil_Area!$F$11=0,0,MIN(Cadastro_Cargas!$E$3,MAX(Cadastro_Cargas!$F$3,Perfil_Area!$F$11*RANDBETWEEN(85,115)/100)))) -> 0
A46: 45658.125 | B46: 3 | C46: FAZ-001 | D46: Secadora | E46: Agrícola | F46: =IF(Cadastro_Cargas!$E$4=0,0,IF(Perfil_Area!$F$13=0,0,MIN(Cadastro_Cargas!$E$4,MAX(Cadastro_Cargas!$F$4,Perfil_Area!$F$13*RANDBETWEEN(85,115)/100)))) -> 0
A47: 45658.125 | B47: 3 | C47: FAZ-001 | D47: Quadro_Auto | E47: Agrícola | F47: =IF(Cadastro_Cargas!$E$5=0,0,IF(Perfil_Area!$F$15=0,0,MIN(Cadastro_Cargas!$E$5,MAX(Cadastro_Cargas!$F$5,Perfil_Area!$F$15*RANDBETWEEN(85,115)/100)))) -> 0.172
A48: 45658.125 | B48: 3 | C48: FAZ-001 | D48: Escritório | E48: Sede | F48: =IF(Cadastro_Cargas!$E$6=0,0,IF(Perfil_Area!$F$3=0,0,MIN(Cadastro_Cargas!$E$6,MAX(Cadastro_Cargas!$F$6,Perfil_Area!$F$3*RANDBETWEEN(85,115)/100)))) -> 0.606
A49: 45658.125 | B49: 3 | C49: FAZ-001 | D49: Cozinha | E49: Sede | F49: =IF(Cadastro_Cargas!$E$7=0,0,IF(Perfil_Area!$F$5=0,0,MIN(Cadastro_Cargas!$E$7,MAX(Cadastro_Cargas!$F$7,Perfil_Area!$F$5*RANDBETWEEN(85,115)/100)))) -> 0.30688
A50: 45658.125 | B50: 3 | C50: FAZ-001 | D50: Quarto | E50: Sede | F50: =IF(Cadastro_Cargas!$E$8=0,0,IF(Perfil_Area!$F$7=0,0,MIN(Cadastro_Cargas!$E$8,MAX(Cadastro_Cargas!$F$8,Perfil_Area!$F$7*RANDBETWEEN(85,115)/100)))) -> 0.16016
A51: 45658.125 | B51: 3 | C51: FAZ-002 | D51: Pivô | E51: Agrícola | F51: =IF(Cadastro_Cargas!$E$9=0,0,IF(Perfil_Area!$F$10=0,0,MIN(Cadastro_Cargas!$E$9,MAX(Cadastro_Cargas!$F$9,Perfil_Area!$F$10*RANDBETWEEN(85,115)/100)))) -> 8
A52: 45658.125 | B52: 3 | C52: FAZ-002 | D52: Bomba_Aux | E52: Agrícola | F52: =IF(Cadastro_Cargas!$E$10=0,0,IF(Perfil_Area!$F$12=0,0,MIN(Cadastro_Cargas!$E$10,MAX(Cadastro_Cargas!$F$10,Perfil_Area!$F$12*RANDBETWEEN(85,115)/100)))) -> 0
A53: 45658.125 | B53: 3 | C53: FAZ-002 | D53: Secadora | E53: Agrícola | F53: =IF(Cadastro_Cargas!$E$11=0,0,IF(Perfil_Area!$F$14=0,0,MIN(Cadastro_Cargas!$E$11,MAX(Cadastro_Cargas!$F$11,Perfil_Area!$F$14*RANDBETWEEN(85,115)/100)))) -> 2.2469688
A54: 45658.125 | B54: 3 | C54: FAZ-002 | D54: Quadro_Auto | E54: Agrícola | F54: =IF(Cadastro_Cargas!$E$12=0,0,IF(Perfil_Area!$F$16=0,0,MIN(Cadastro_Cargas!$E$12,MAX(Cadastro_Cargas!$F$12,Perfil_Area!$F$16*RANDBETWEEN(85,115)/100)))) -> 0.2
A55: 45658.125 | B55: 3 | C55: FAZ-002 | D55: Escritório | E55: Sede | F55: =IF(Cadastro_Cargas!$E$13=0,0,IF(Perfil_Area!$F$4=0,0,MIN(Cadastro_Cargas!$E$13,MAX(Cadastro_Cargas!$F$13,Perfil_Area!$F$4*RANDBETWEEN(85,115)/100)))) -> 1.1175
A56: 45658.125 | B56: 3 | C56: FAZ-002 | D56: Cozinha | E56: Sede | F56: =IF(Cadastro_Cargas!$E$14=0,0,IF(Perfil_Area!$F$6=0,0,MIN(Cadastro_Cargas!$E$14,MAX(Cadastro_Cargas!$F$14,Perfil_Area!$F$6*RANDBETWEEN(85,115)/100)))) -> 0.37824
A57: 45658.125 | B57: 3 | C57: FAZ-002 | D57: Quarto | E57: Sede | F57: =IF(Cadastro_Cargas!$E$15=0,0,IF(Perfil_Area!$F$8=0,0,MIN(Cadastro_Cargas!$E$15,MAX(Cadastro_Cargas!$F$15,Perfil_Area!$F$8*RANDBETWEEN(85,115)/100)))) -> 0.3192
A58: 45658.167 | B58: 4 | C58: FAZ-001 | D58: Pivô | E58: Agrícola | F58: =IF(Cadastro_Cargas!$E$2=0,0,IF(Perfil_Area!$G$9=0,0,MIN(Cadastro_Cargas!$E$2,MAX(Cadastro_Cargas!$F$2,Perfil_Area!$G$9*RANDBETWEEN(85,115)/100)))) -> 3.88
A59: 45658.167 | B59: 4 | C59: FAZ-001 | D59: Bomba_Aux | E59: Agrícola | F59: =IF(Cadastro_Cargas!$E$3=0,0,IF(Perfil_Area!$G$11=0,0,MIN(Cadastro_Cargas!$E$3,MAX(Cadastro_Cargas!$F$3,Perfil_Area!$G$11*RANDBETWEEN(85,115)/100)))) -> 0
A60: 45658.167 | B60: 4 | C60: FAZ-001 | D60: Secadora | E60: Agrícola | F60: =IF(Cadastro_Cargas!$E$4=0,0,IF(Perfil_Area!$G$13=0,0,MIN(Cadastro_Cargas!$E$4,MAX(Cadastro_Cargas!$F$4,Perfil_Area!$G$13*RANDBETWEEN(85,115)/100)))) -> 0
A61: 45658.167 | B61: 4 | C61: FAZ-001 | D61: Quadro_Auto | E61: Agrícola | F61: =IF(Cadastro_Cargas!$E$5=0,0,IF(Perfil_Area!$G$15=0,0,MIN(Cadastro_Cargas!$E$5,MAX(Cadastro_Cargas!$F$5,Perfil_Area!$G$15*RANDBETWEEN(85,115)/100)))) -> 0.184
A62: 45658.167 | B62: 4 | C62: FAZ-001 | D62: Escritório | E62: Sede | F62: =IF(Cadastro_Cargas!$E$6=0,0,IF(Perfil_Area!$G$3=0,0,MIN(Cadastro_Cargas!$E$6,MAX(Cadastro_Cargas!$F$6,Perfil_Area!$G$3*RANDBETWEEN(85,115)/100)))) -> 0.606
A63: 45658.167 | B63: 4 | C63: FAZ-001 | D63: Cozinha | E63: Sede | F63: =IF(Cadastro_Cargas!$E$7=0,0,IF(Perfil_Area!$G$5=0,0,MIN(Cadastro_Cargas!$E$7,MAX(Cadastro_Cargas!$F$7,Perfil_Area!$G$5*RANDBETWEEN(85,115)/100)))) -> 0.23564
A64: 45658.167 | B64: 4 | C64: FAZ-001 | D64: Quarto | E64: Sede | F64: =IF(Cadastro_Cargas!$E$8=0,0,IF(Perfil_Area!$G$7=0,0,MIN(Cadastro_Cargas!$E$8,MAX(Cadastro_Cargas!$F$8,Perfil_Area!$G$7*RANDBETWEEN(85,115)/100)))) -> 0.16274
A65: 45658.167 | B65: 4 | C65: FAZ-002 | D65: Pivô | E65: Agrícola | F65: =IF(Cadastro_Cargas!$E$9=0,0,IF(Perfil_Area!$G$10=0,0,MIN(Cadastro_Cargas!$E$9,MAX(Cadastro_Cargas!$F$9,Perfil_Area!$G$10*RANDBETWEEN(85,115)/100)))) -> 8
A66: 45658.167 | B66: 4 | C66: FAZ-002 | D66: Bomba_Aux | E66: Agrícola | F66: =IF(Cadastro_Cargas!$E$10=0,0,IF(Perfil_Area!$G$12=0,0,MIN(Cadastro_Cargas!$E$10,MAX(Cadastro_Cargas!$F$10,Perfil_Area!$G$12*RANDBETWEEN(85,115)/100)))) -> 0
A67: 45658.167 | B67: 4 | C67: FAZ-002 | D67: Secadora | E67: Agrícola | F67: =IF(Cadastro_Cargas!$E$11=0,0,IF(Perfil_Area!$G$14=0,0,MIN(Cadastro_Cargas!$E$11,MAX(Cadastro_Cargas!$F$11,Perfil_Area!$G$14*RANDBETWEEN(85,115)/100)))) -> 1.9445171
A68: 45658.167 | B68: 4 | C68: FAZ-002 | D68: Quadro_Auto | E68: Agrícola | F68: =IF(Cadastro_Cargas!$E$12=0,0,IF(Perfil_Area!$G$16=0,0,MIN(Cadastro_Cargas!$E$12,MAX(Cadastro_Cargas!$F$12,Perfil_Area!$G$16*RANDBETWEEN(85,115)/100)))) -> 0.2
A69: 45658.167 | B69: 4 | C69: FAZ-002 | D69: Escritório | E69: Sede | F69: =IF(Cadastro_Cargas!$E$13=0,0,IF(Perfil_Area!$G$4=0,0,MIN(Cadastro_Cargas!$E$13,MAX(Cadastro_Cargas!$F$13,Perfil_Area!$G$4*RANDBETWEEN(85,115)/100)))) -> 1.1175
A70: 45658.167 | B70: 4 | C70: FAZ-002 | D70: Cozinha | E70: Sede | F70: =IF(Cadastro_Cargas!$E$14=0,0,IF(Perfil_Area!$G$6=0,0,MIN(Cadastro_Cargas!$E$14,MAX(Cadastro_Cargas!$F$14,Perfil_Area!$G$6*RANDBETWEEN(85,115)/100)))) -> 0.38612
A71: 45658.167 | B71: 4 | C71: FAZ-002 | D71: Quarto | E71: Sede | F71: =IF(Cadastro_Cargas!$E$15=0,0,IF(Perfil_Area!$G$8=0,0,MIN(Cadastro_Cargas!$E$15,MAX(Cadastro_Cargas!$F$15,Perfil_Area!$G$8*RANDBETWEEN(85,115)/100)))) -> 0.27846
A72: 45658.208 | B72: 5 | C72: FAZ-001 | D72: Pivô | E72: Agrícola | F72: =IF(Cadastro_Cargas!$E$2=0,0,IF(Perfil_Area!$H$9=0,0,MIN(Cadastro_Cargas!$E$2,MAX(Cadastro_Cargas!$F$2,Perfil_Area!$H$9*RANDBETWEEN(85,115)/100)))) -> 0
A73: 45658.208 | B73: 5 | C73: FAZ-001 | D73: Bomba_Aux | E73: Agrícola | F73: =IF(Cadastro_Cargas!$E$3=0,0,IF(Perfil_Area!$H$11=0,0,MIN(Cadastro_Cargas!$E$3,MAX(Cadastro_Cargas!$F$3,Perfil_Area!$H$11*RANDBETWEEN(85,115)/100)))) -> 0
A74: 45658.208 | B74: 5 | C74: FAZ-001 | D74: Secadora | E74: Agrícola | F74: =IF(Cadastro_Cargas!$E$4=0,0,IF(Perfil_Area!$H$13=0,0,MIN(Cadastro_Cargas!$E$4,MAX(Cadastro_Cargas!$F$4,Perfil_Area!$H$13*RANDBETWEEN(85,115)/100)))) -> 0
A75: 45658.208 | B75: 5 | C75: FAZ-001 | D75: Quadro_Auto | E75: Agrícola | F75: =IF(Cadastro_Cargas!$E$5=0,0,IF(Perfil_Area!$H$15=0,0,MIN(Cadastro_Cargas!$E$5,MAX(Cadastro_Cargas!$F$5,Perfil_Area!$H$15*RANDBETWEEN(85,115)/100)))) -> 0.19
A76: 45658.208 | B76: 5 | C76: FAZ-001 | D76: Escritório | E76: Sede | F76: =IF(Cadastro_Cargas!$E$6=0,0,IF(Perfil_Area!$H$3=0,0,MIN(Cadastro_Cargas!$E$6,MAX(Cadastro_Cargas!$F$6,Perfil_Area!$H$3*RANDBETWEEN(85,115)/100)))) -> 0.606
A77: 45658.208 | B77: 5 | C77: FAZ-001 | D77: Cozinha | E77: Sede | F77: =IF(Cadastro_Cargas!$E$7=0,0,IF(Perfil_Area!$H$5=0,0,MIN(Cadastro_Cargas!$E$7,MAX(Cadastro_Cargas!$F$7,Perfil_Area!$H$5*RANDBETWEEN(85,115)/100)))) -> 0.354
A78: 45658.208 | B78: 5 | C78: FAZ-001 | D78: Quarto | E78: Sede | F78: =IF(Cadastro_Cargas!$E$8=0,0,IF(Perfil_Area!$H$7=0,0,MIN(Cadastro_Cargas!$E$8,MAX(Cadastro_Cargas!$F$8,Perfil_Area!$H$7*RANDBETWEEN(85,115)/100)))) -> 0.1254
A79: 45658.208 | B79: 5 | C79: FAZ-002 | D79: Pivô | E79: Agrícola | F79: =IF(Cadastro_Cargas!$E$9=0,0,IF(Perfil_Area!$H$10=0,0,MIN(Cadastro_Cargas!$E$9,MAX(Cadastro_Cargas!$F$9,Perfil_Area!$H$10*RANDBETWEEN(85,115)/100)))) -> 0
A80: 45658.208 | B80: 5 | C80: FAZ-002 | D80: Bomba_Aux | E80: Agrícola | F80: =IF(Cadastro_Cargas!$E$10=0,0,IF(Perfil_Area!$H$12=0,0,MIN(Cadastro_Cargas!$E$10,MAX(Cadastro_Cargas!$F$10,Perfil_Area!$H$12*RANDBETWEEN(85,115)/100)))) -> 0
A81: 45658.208 | B81: 5 | C81: FAZ-002 | D81: Secadora | E81: Agrícola | F81: =IF(Cadastro_Cargas!$E$11=0,0,IF(Perfil_Area!$H$14=0,0,MIN(Cadastro_Cargas!$E$11,MAX(Cadastro_Cargas!$F$11,Perfil_Area!$H$14*RANDBETWEEN(85,115)/100)))) -> 2.0701605
A82: 45658.208 | B82: 5 | C82: FAZ-002 | D82: Quadro_Auto | E82: Agrícola | F82: =IF(Cadastro_Cargas!$E$12=0,0,IF(Perfil_Area!$H$16=0,0,MIN(Cadastro_Cargas!$E$12,MAX(Cadastro_Cargas!$F$12,Perfil_Area!$H$16*RANDBETWEEN(85,115)/100)))) -> 0.178
A83: 45658.208 | B83: 5 | C83: FAZ-002 | D83: Escritório | E83: Sede | F83: =IF(Cadastro_Cargas!$E$13=0,0,IF(Perfil_Area!$H$4=0,0,MIN(Cadastro_Cargas!$E$13,MAX(Cadastro_Cargas!$F$13,Perfil_Area!$H$4*RANDBETWEEN(85,115)/100)))) -> 1.1175
A84: 45658.208 | B84: 5 | C84: FAZ-002 | D84: Cozinha | E84: Sede | F84: =IF(Cadastro_Cargas!$E$14=0,0,IF(Perfil_Area!$H$6=0,0,MIN(Cadastro_Cargas!$E$14,MAX(Cadastro_Cargas!$F$14,Perfil_Area!$H$6*RANDBETWEEN(85,115)/100)))) -> 0.514
A85: 45658.208 | B85: 5 | C85: FAZ-002 | D85: Quarto | E85: Sede | F85: =IF(Cadastro_Cargas!$E$15=0,0,IF(Perfil_Area!$H$8=0,0,MIN(Cadastro_Cargas!$E$15,MAX(Cadastro_Cargas!$F$15,Perfil_Area!$H$8*RANDBETWEEN(85,115)/100)))) -> 0.22422
A86: 45658.25 | B86: 6 | C86: FAZ-001 | D86: Pivô | E86: Agrícola | F86: =IF(Cadastro_Cargas!$E$2=0,0,IF(Perfil_Area!$I$9=0,0,MIN(Cadastro_Cargas!$E$2,MAX(Cadastro_Cargas!$F$2,Perfil_Area!$I$9*RANDBETWEEN(85,115)/100)))) -> 0
A87: 45658.25 | B87: 6 | C87: FAZ-001 | D87: Bomba_Aux | E87: Agrícola | F87: =IF(Cadastro_Cargas!$E$3=0,0,IF(Perfil_Area!$I$11=0,0,MIN(Cadastro_Cargas!$E$3,MAX(Cadastro_Cargas!$F$3,Perfil_Area!$I$11*RANDBETWEEN(85,115)/100)))) -> 0
A88: 45658.25 | B88: 6 | C88: FAZ-001 | D88: Secadora | E88: Agrícola | F88: =IF(Cadastro_Cargas!$E$4=0,0,IF(Perfil_Area!$I$13=0,0,MIN(Cadastro_Cargas!$E$4,MAX(Cadastro_Cargas!$F$4,Perfil_Area!$I$13*RANDBETWEEN(85,115)/100)))) -> 0
A89: 45658.25 | B89: 6 | C89: FAZ-001 | D89: Quadro_Auto | E89: Agrícola | F89: =IF(Cadastro_Cargas!$E$5=0,0,IF(Perfil_Area!$I$15=0,0,MIN(Cadastro_Cargas!$E$5,MAX(Cadastro_Cargas!$F$5,Perfil_Area!$I$15*RANDBETWEEN(85,115)/100)))) -> 0.18
A90: 45658.25 | B90: 6 | C90: FAZ-001 | D90: Escritório | E90: Sede | F90: =IF(Cadastro_Cargas!$E$6=0,0,IF(Perfil_Area!$I$3=0,0,MIN(Cadastro_Cargas!$E$6,MAX(Cadastro_Cargas!$F$6,Perfil_Area!$I$3*RANDBETWEEN(85,115)/100)))) -> 0.606
A91: 45658.25 | B91: 6 | C91: FAZ-001 | D91: Cozinha | E91: Sede | F91: =IF(Cadastro_Cargas!$E$7=0,0,IF(Perfil_Area!$I$5=0,0,MIN(Cadastro_Cargas!$E$7,MAX(Cadastro_Cargas!$F$7,Perfil_Area!$I$5*RANDBETWEEN(85,115)/100)))) -> 0.354
A92: 45658.25 | B92: 6 | C92: FAZ-001 | D92: Quarto | E92: Sede | F92: =IF(Cadastro_Cargas!$E$8=0,0,IF(Perfil_Area!$I$7=0,0,MIN(Cadastro_Cargas!$E$8,MAX(Cadastro_Cargas!$F$8,Perfil_Area!$I$7*RANDBETWEEN(85,115)/100)))) -> 0.0528
A93: 45658.25 | B93: 6 | C93: FAZ-002 | D93: Pivô | E93: Agrícola | F93: =IF(Cadastro_Cargas!$E$9=0,0,IF(Perfil_Area!$I$10=0,0,MIN(Cadastro_Cargas!$E$9,MAX(Cadastro_Cargas!$F$9,Perfil_Area!$I$10*RANDBETWEEN(85,115)/100)))) -> 0
A94: 45658.25 | B94: 6 | C94: FAZ-002 | D94: Bomba_Aux | E94: Agrícola | F94: =IF(Cadastro_Cargas!$E$10=0,0,IF(Perfil_Area!$I$12=0,0,MIN(Cadastro_Cargas!$E$10,MAX(Cadastro_Cargas!$F$10,Perfil_Area!$I$12*RANDBETWEEN(85,115)/100)))) -> 0
A95: 45658.25 | B95: 6 | C95: FAZ-002 | D95: Secadora | E95: Agrícola | F95: =IF(Cadastro_Cargas!$E$11=0,0,IF(Perfil_Area!$I$14=0,0,MIN(Cadastro_Cargas!$E$11,MAX(Cadastro_Cargas!$F$11,Perfil_Area!$I$14*RANDBETWEEN(85,115)/100)))) -> 2.3670134
A96: 45658.25 | B96: 6 | C96: FAZ-002 | D96: Quadro_Auto | E96: Agrícola | F96: =IF(Cadastro_Cargas!$E$12=0,0,IF(Perfil_Area!$I$16=0,0,MIN(Cadastro_Cargas!$E$12,MAX(Cadastro_Cargas!$F$12,Perfil_Area!$I$16*RANDBETWEEN(85,115)/100)))) -> 0.196
A97: 45658.25 | B97: 6 | C97: FAZ-002 | D97: Escritório | E97: Sede | F97: =IF(Cadastro_Cargas!$E$13=0,0,IF(Perfil_Area!$I$4=0,0,MIN(Cadastro_Cargas!$E$13,MAX(Cadastro_Cargas!$F$13,Perfil_Area!$I$4*RANDBETWEEN(85,115)/100)))) -> 1.1175
A98: 45658.25 | B98: 6 | C98: FAZ-002 | D98: Cozinha | E98: Sede | F98: =IF(Cadastro_Cargas!$E$14=0,0,IF(Perfil_Area!$I$6=0,0,MIN(Cadastro_Cargas!$E$14,MAX(Cadastro_Cargas!$F$14,Perfil_Area!$I$6*RANDBETWEEN(85,115)/100)))) -> 0.514
A99: 45658.25 | B99: 6 | C99: FAZ-002 | D99: Quarto | E99: Sede | F99: =IF(Cadastro_Cargas!$E$15=0,0,IF(Perfil_Area!$I$8=0,0,MIN(Cadastro_Cargas!$E$15,MAX(Cadastro_Cargas!$F$15,Perfil_Area!$I$8*RANDBETWEEN(85,115)/100)))) -> 0.1008
A100: 45658.292 | B100: 7 | C100: FAZ-001 | D100: Pivô | E100: Agrícola | F100: =IF(Cadastro_Cargas!$E$2=0,0,IF(Perfil_Area!$J$9=0,0,MIN(Cadastro_Cargas!$E$2,MAX(Cadastro_Cargas!$F$2,Perfil_Area!$J$9*RANDBETWEEN(85,115)/100)))) -> 0
...

Sheet Consumo_Fatura
A1: ID_Fazenda | B1: Data_Hora | C1: Hora | D1: Consumo_kWh | E1: Geração_kWh | F1: Saldo_Rede_kWh | G1: Tarifa_R$ | H1: Custo_R$ | I1: Tipo_Horário | J1: Bateria_Descarga_kWh | K1: Saldo_Liquido_kWh
A2: FAZ-001 | B2: 45658 | C2: 00:00 | D2: =SUM(Cargas!$F$2:$F$8) -> 4.99134 | E2: =Geracao!F2+Geracao!F3 -> 1.04652 | F2: =D2-E2 -> 3.94482 | G2: =Tarifa!$B$2 -> 0.6813 | H2: =K2*G2 -> 2.6876059 | I2: =Tarifa!$C$2 -> Fora Ponta | J2: =IF(I2="Ponta",Cadastro_Cargas!$F$16,0) -> 0 | K2: =MAX(0,D2-E2-J2) -> 3.94482
A3: FAZ-001 | B3: 45658.042 | C3: 01:00 | D3: =SUM(Cargas!$F$16:$F$22) -> 4.64504 | E3: =Geracao!F6+Geracao!F7 -> 0.9471975 | F3: =D3-E3 -> 3.6978425 | G3: =Tarifa!$B$3 -> 0.6813 | H3: =K3*G3 -> 2.5193401 | I3: =Tarifa!$C$3 -> Fora Ponta | J3: =IF(I3="Ponta",Cadastro_Cargas!$F$16,0) -> 0 | K3: =MAX(0,D3-E3-J3) -> 3.6978425
A4: FAZ-001 | B4: 45658.083 | C4: 02:00 | D4: =SUM(Cargas!$F$30:$F$36) -> 5.23134 | E4: =Geracao!F10+Geracao!F11 -> 0.741285 | F4: =D4-E4 -> 4.490055 | G4: =Tarifa!$B$4 -> 0.6813 | H4: =K4*G4 -> 3.0590745 | I4: =Tarifa!$C$4 -> Fora Ponta | J4: =IF(I4="Ponta",Cadastro_Cargas!$F$16,0) -> 0 | K4: =MAX(0,D4-E4-J4) -> 4.490055
A5: FAZ-001 | B5: 45658.125 | C5: 03:00 | D5: =SUM(Cargas!$F$44:$F$50) -> 5.24504 | E5: =Geracao!F14+Geracao!F15 -> 1.2136725 | F5: =D5-E5 -> 4.0313675 | G5: =Tarifa!$B$5 -> 0.6813 | H5: =K5*G5 -> 2.7465707 | I5: =Tarifa!$C$5 -> Fora Ponta | J5: =IF(I5="Ponta",Cadastro_Cargas!$F$16,0) -> 0 | K5: =MAX(0,D5-E5-J5) -> 4.0313675
A6: FAZ-001 | B6: 45658.167 | C6: 04:00 | D6: =SUM(Cargas!$F$58:$F$64) -> 5.06838 | E6: =Geracao!F18+Geracao!F19 -> 0.731595 | F6: =D6-E6 -> 4.336785 | G6: =Tarifa!$B$6 -> 0.6813 | H6: =K6*G6 -> 2.9546516 | I6: =Tarifa!$C$6 -> Fora Ponta | J6: =IF(I6="Ponta",Cadastro_Cargas!$F$16,0) -> 0 | K6: =MAX(0,D6-E6-J6) -> 4.336785
A7: FAZ-001 | B7: 45658.208 | C7: 05:00 | D7: =SUM(Cargas!$F$72:$F$78) -> 1.2754 | E7: =Geracao!F22+Geracao!F23 -> 0.7752 | F7: =D7-E7 -> 0.5002 | G7: =Tarifa!$B$7 -> 0.6813 | H7: =K7*G7 -> 0.34078626 | I7: =Tarifa!$C$7 -> Fora Ponta | J7: =IF(I7="Ponta",Cadastro_Cargas!$F$16,0) -> 0 | K7: =MAX(0,D7-E7-J7) -> 0.5002
A8: FAZ-001 | B8: 45658.25 | C8: 06:00 | D8: =SUM(Cargas!$F$86:$F$92) -> 1.1928 | E8: =Geracao!F26+Geracao!F27 -> 1.3877989 | F8: =D8-E8 -> -0.19499886 | G8: =Tarifa!$B$8 -> 0.6813 | H8: =K8*G8 -> 0 | I8: =Tarifa!$C$8 -> Fora Ponta | J8: =IF(I8="Ponta",Cadastro_Cargas!$F$16,0) -> 0 | K8: =MAX(0,D8-E8-J8) -> 0
A9: FAZ-001 | B9: 45658.292 | C9: 07:00 | D9: =SUM(Cargas!$F$100:$F$106) -> 1.158 | E9: =Geracao!F30+Geracao!F31 -> 2.6274582 | F9: =D9-E9 -> -1.4694582 | G9: =Tarifa!$B$9 -> 0.6813 | H9: =K9*G9 -> 0 | I9: =Tarifa!$C$9 -> Fora Ponta | J9: =IF(I9="Ponta",Cadastro_Cargas!$F$16,0) -> 0 | K9: =MAX(0,D9-E9-J9) -> 0
A10: FAZ-001 | B10: 45658.333 | C10: 08:00 | D10: =SUM(Cargas!$F$114:$F$120) -> 1.765 | E10: =Geracao!F34+Geracao!F35 -> 2.5261536 | F10: =D10-E10 -> -0.76115364 | G10: =Tarifa!$B$10 -> 0.6813 | H10: =K10*G10 -> 0 | I10: =Tarifa!$C$10 -> Fora Ponta | J10: =IF(I10="Ponta",Cadastro_Cargas!$F$16,0) -> 0 | K10: =MAX(0,D10-E10-J10) -> 0
A11: FAZ-001 | B11: 45658.375 | C11: 09:00 | D11: =SUM(Cargas!$F$128:$F$134) -> 2.27024 | E11: =Geracao!F38+Geracao!F39 -> 4.5476932 | F11: =D11-E11 -> -2.2774532 | G11: =Tarifa!$B$11 -> 0.6813 | H11: =K11*G11 -> 0 | I11: =Tarifa!$C$11 -> Fora Ponta | J11: =IF(I11="Ponta",Cadastro_Cargas!$F$16,0) -> 0 | K11: =MAX(0,D11-E11-J11) -> 0
A12: FAZ-001 | B12: 45658.417 | C12: 10:00 | D12: =SUM(Cargas!$F$142:$F$148) -> 2.47482 | E12: =Geracao!F42+Geracao!F43 -> 7.5757448 | F12: =D12-E12 -> -5.1009248 | G12: =Tarifa!$B$12 -> 0.6813 | H12: =K12*G12 -> 0 | I12: =Tarifa!$C$12 -> Fora Ponta | J12: =IF(I12="Ponta",Cadastro_Cargas!$F$16,0) -> 0 | K12: =MAX(0,D12-E12-J12) -> 0
A13: FAZ-001 | B13: 45658.458 | C13: 11:00 | D13: =SUM(Cargas!$F$156:$F$162) -> 2.55 | E13: =Geracao!F46+Geracao!F47 -> 8.0206039 | F13: =D13-E13 -> -5.4706039 | G13: =Tarifa!$B$13 -> 0.6813 | H13: =K13*G13 -> 0 | I13: =Tarifa!$C$13 -> Fora Ponta | J13: =IF(I13="Ponta",Cadastro_Cargas!$F$16,0) -> 0 | K13: =MAX(0,D13-E13-J13) -> 0
A14: FAZ-001 | B14: 45658.5 | C14: 12:00 | D14: =SUM(Cargas!$F$170:$F$176) -> 2.574 | E14: =Geracao!F50+Geracao!F51 -> 8.3742889 | F14: =D14-E14 -> -5.8002889 | G14: =Tarifa!$B$14 -> 0.6813 | H14: =K14*G14 -> 0 | I14: =Tarifa!$C$14 -> Fora Ponta | J14: =IF(I14="Ponta",Cadastro_Cargas!$F$16,0) -> 0 | K14: =MAX(0,D14-E14-J14) -> 0
A15: FAZ-001 | B15: 45658.542 | C15: 13:00 | D15: =SUM(Cargas!$F$184:$F$190) -> 2.5076 | E15: =Geracao!F54+Geracao!F55 -> 5.6778995 | F15: =D15-E15 -> -3.1702995 | G15: =Tarifa!$B$15 -> 0.6813 | H15: =K15*G15 -> 0 | I15: =Tarifa!$C$15 -> Fora Ponta | J15: =IF(I15="Ponta",Cadastro_Cargas!$F$16,0) -> 0 | K15: =MAX(0,D15-E15-J15) -> 0
A16: FAZ-001 | B16: 45658.583 | C16: 14:00 | D16: =SUM(Cargas!$F$198:$F$204) -> 2.3518 | E16: =Geracao!F58+Geracao!F59 -> 7.2333648 | F16: =D16-E16 -> -4.8815648 | G16: =Tarifa!$B$16 -> 0.6813 | H16: =K16*G16 -> 0 | I16: =Tarifa!$C$16 -> Fora Ponta | J16: =IF(I16="Ponta",Cadastro_Cargas!$F$16,0) -> 0 | K16: =MAX(0,D16-E16-J16) -> 0
A17: FAZ-001 | B17: 45658.625 | C17: 15:00 | D17: =SUM(Cargas!$F$212:$F$218) -> 2.574 | E17: =Geracao!F62+Geracao!F63 -> 6.5695998 | F17: =D17-E17 -> -3.9955998 | G17: =Tarifa!$B$17 -> 0.6813 | H17: =K17*G17 -> 0 | I17: =Tarifa!$C$17 -> Fora Ponta | J17: =IF(I17="Ponta",Cadastro_Cargas!$F$16,0) -> 0 | K17: =MAX(0,D17-E17-J17) -> 0
A18: FAZ-001 | B18: 45658.667 | C18: 16:00 | D18: =SUM(Cargas!$F$226:$F$232) -> 2.21438 | E18: =Geracao!F66+Geracao!F67 -> 5.9026048 | F18: =D18-E18 -> -3.6882248 | G18: =Tarifa!$B$18 -> 0.6813 | H18: =K18*G18 -> 0 | I18: =Tarifa!$C$18 -> Fora Ponta | J18: =IF(I18="Ponta",Cadastro_Cargas!$F$16,0) -> 0 | K18: =MAX(0,D18-E18-J18) -> 0
A19: FAZ-001 | B19: 45658.708 | C19: 17:00 | D19: =SUM(Cargas!$F$240:$F$246) -> 1.14 | E19: =Geracao!F70+Geracao!F71 -> 3.877982 | F19: =D19-E19 -> -2.737982 | G19: =Tarifa!$B$19 -> 0.6813 | H19: =K19*G19 -> 0 | I19: =Tarifa!$C$19 -> Fora Ponta | J19: =IF(I19="Ponta",Cadastro_Cargas!$F$16,0) -> 0 | K19: =MAX(0,D19-E19-J19) -> 0
A20: FAZ-001 | B20: 45658.75 | C20: 18:00 | D20: =SUM(Cargas!$F$254:$F$260) -> 1.312 | E20: =Geracao!F74+Geracao!F75 -> 2.1706334 | F20: =D20-E20 -> -0.85863341 | G20: =Tarifa!$B$20 -> 1.1039 | H20: =K20*G20 -> 0 | I20: =Tarifa!$C$20 -> Ponta | J20: =IF(I20="Ponta",Cadastro_Cargas!$F$16,0) -> 0.875 | K20: =MAX(0,D20-E20-J20) -> 0
A21: FAZ-001 | B21: 45658.792 | C21: 19:00 | D21: =SUM(Cargas!$F$268:$F$274) -> 1.316 | E21: =Geracao!F78+Geracao!F79 -> 0.64923 | F21: =D21-E21 -> 0.66677 | G21: =Tarifa!$B$21 -> 1.1039 | H21: =K21*G21 -> 0 | I21: =Tarifa!$C$21 -> Ponta | J21: =IF(I21="Ponta",Cadastro_Cargas!$F$16,0) -> 0.875 | K21: =MAX(0,D21-E21-J21) -> 0
A22: FAZ-001 | B22: 45658.833 | C22: 20:00 | D22: =SUM(Cargas!$F$282:$F$288) -> 4.84174 | E22: =Geracao!F82+Geracao!F83 -> 0.663765 | F22: =D22-E22 -> 4.177975 | G22: =Tarifa!$B$22 -> 1.1039 | H22: =K22*G22 -> 3.6461541 | I22: =Tarifa!$C$22 -> Ponta | J22: =IF(I22="Ponta",Cadastro_Cargas!$F$16,0) -> 0.875 | K22: =MAX(0,D22-E22-J22) -> 3.302975
A23: FAZ-001 | B23: 45658.875 | C23: 21:00 | D23: =SUM(Cargas!$F$296:$F$302) -> 4.74178 | E23: =Geracao!F86+Geracao!F87 -> 0.7533975 | F23: =D23-E23 -> 3.9883825 | G23: =Tarifa!$B$23 -> 0.6813 | H23: =K23*G23 -> 2.717285 | I23: =Tarifa!$C$23 -> Fora Ponta | J23: =IF(I23="Ponta",Cadastro_Cargas!$F$16,0) -> 0 | K23: =MAX(0,D23-E23-J23) -> 3.9883825
A24: FAZ-001 | B24: 45658.917 | C24: 22:00 | D24: =SUM(Cargas!$F$310:$F$316) -> 4.87682 | E24: =Geracao!F90+Geracao!F91 -> 0.7340175 | F24: =D24-E24 -> 4.1428025 | G24: =Tarifa!$B$24 -> 0.6813 | H24: =K24*G24 -> 2.8224913 | I24: =Tarifa!$C$24 -> Fora Ponta | J24: =IF(I24="Ponta",Cadastro_Cargas!$F$16,0) -> 0 | K24: =MAX(0,D24-E24-J24) -> 4.1428025
A25: FAZ-001 | B25: 45658.958 | C25: 23:00 | D25: =SUM(Cargas!$F$324:$F$330) -> 5.27488 | E25: =Geracao!F94+Geracao!F95 -> 0.8987475 | F25: =D25-E25 -> 4.3761325 | G25: =Tarifa!$B$25 -> 0.6813 | H25: =K25*G25 -> 2.9814591 | I25: =Tarifa!$C$25 -> Fora Ponta | J25: =IF(I25="Ponta",Cadastro_Cargas!$F$16,0) -> 0 | K25: =MAX(0,D25-E25-J25) -> 4.3761325
A26: FAZ-001 | B26: 45659 | C26: 00:00 | D26: =SUM(Cargas!$F$338:$F$344) -> 5.23372 | E26: =Geracao!F98+Geracao!F99 -> 1.303305 | F26: =D26-E26 -> 3.930415 | G26: =Tarifa!$B$2 -> 0.6813 | H26: =K26*G26 -> 2.6777917 | I26: =Tarifa!$C$2 -> Fora Ponta | J26: =IF(I26="Ponta",Cadastro_Cargas!$F$16,0) -> 0 | K26: =MAX(0,D26-E26-J26) -> 3.930415
A27: FAZ-001 | B27: 45659.042 | C27: 01:00 | D27: =SUM(Cargas!$F$352:$F$358) -> 4.77022 | E27: =Geracao!F102+Geracao!F103 -> 1.0683225 | F27: =D27-E27 -> 3.7018975 | G27: =Tarifa!$B$3 -> 0.6813 | H27: =K27*G27 -> 2.5221028 | I27: =Tarifa!$C$3 -> Fora Ponta | J27: =IF(I27="Ponta",Cadastro_Cargas!$F$16,0) -> 0 | K27: =MAX(0,D27-E27-J27) -> 3.7018975
A28: FAZ-001 | B28: 45659.083 | C28: 02:00 | D28: =SUM(Cargas!$F$366:$F$372) -> 5.24426 | E28: =Geracao!F106+Geracao!F107 -> 0.789735 | F28: =D28-E28 -> 4.454525 | G28: =Tarifa!$B$4 -> 0.6813 | H28: =K28*G28 -> 3.0348679 | I28: =Tarifa!$C$4 -> Fora Ponta | J28: =IF(I28="Ponta",Cadastro_Cargas!$F$16,0) -> 0 | K28: =MAX(0,D28-E28-J28) -> 4.454525
A29: FAZ-001 | B29: 45659.125 | C29: 03:00 | D29: =SUM(Cargas!$F$380:$F$386) -> 5.2881 | E29: =Geracao!F110+Geracao!F111 -> 0.770355 | F29: =D29-E29 -> 4.517745 | G29: =Tarifa!$B$5 -> 0.6813 | H29: =K29*G29 -> 3.0779397 | I29: =Tarifa!$C$5 -> Fora Ponta | J29: =IF(I29="Ponta",Cadastro_Cargas!$F$16,0) -> 0 | K29: =MAX(0,D29-E29-J29) -> 4.517745
A30: FAZ-001 | B30: 45659.167 | C30: 04:00 | D30: =SUM(Cargas!$F$394:$F$400) -> 5.25898 | E30: =Geracao!F114+Geracao!F115 -> 1.3687125 | F30: =D30-E30 -> 3.8902675 | G30: =Tarifa!$B$6 -> 0.6813 | H30: =K30*G30 -> 2.6504392 | I30: =Tarifa!$C$6 -> Fora Ponta | J30: =IF(I30="Ponta",Cadastro_Cargas!$F$16,0) -> 0 | K30: =MAX(0,D30-E30-J30) -> 3.8902675
A31: FAZ-001 | B31: 45659.208 | C31: 05:00 | D31: =SUM(Cargas!$F$408:$F$414) -> 1.2694 | E31: =Geracao!F118+Geracao!F119 -> 0.7776225 | F31: =D31-E31 -> 0.4917775 | G31: =Tarifa!$B$7 -> 0.6813 | H31: =K31*G31 -> 0.33504801 | I31: =Tarifa!$C$7 -> Fora Ponta | J31: =IF(I31="Ponta",Cadastro_Cargas!$F$16,0) -> 0 | K31: =MAX(0,D31-E31-J31) -> 0.4917775
A32: FAZ-001 | B32: 45659.25 | C32: 06:00 | D32: =SUM(Cargas!$F$422:$F$428) -> 1.2048 | E32: =Geracao!F122+Geracao!F123 -> 2.1595486 | F32: =D32-E32 -> -0.95474864 | G32: =Tarifa!$B$8 -> 0.6813 | H32: =K32*G32 -> 0 | I32: =Tarifa!$C$8 -> Fora Ponta | J32: =IF(I32="Ponta",Cadastro_Cargas!$F$16,0) -> 0 | K32: =MAX(0,D32-E32-J32) -> 0
A33: FAZ-001 | B33: 45659.292 | C33: 07:00 | D33: =SUM(Cargas!$F$436:$F$442) -> 1.205 | E33: =Geracao!F126+Geracao!F127 -> 1.1286648 | F33: =D33-E33 -> 0.076335227 | G33: =Tarifa!$B$9 -> 0.6813 | H33: =K33*G33 -> 0.05200719 | I33: =Tarifa!$C$9 -> Fora Ponta | J33: =IF(I33="Ponta",Cadastro_Cargas!$F$16,0) -> 0 | K33: =MAX(0,D33-E33-J33) -> 0.076335227
A34: FAZ-001 | B34: 45659.333 | C34: 08:00 | D34: =SUM(Cargas!$F$450:$F$456) -> 1.773 | E34: =Geracao!F130+Geracao!F131 -> 3.1902857 | F34: =D34-E34 -> -1.4172857 | G34: =Tarifa!$B$10 -> 0.6813 | H34: =K34*G34 -> 0 | I34: =Tarifa!$C$10 -> Fora Ponta | J34: =IF(I34="Ponta",Cadastro_Cargas!$F$16,0) -> 0 | K34: =MAX(0,D34-E34-J34) -> 0
A35: FAZ-001 | B35: 45659.375 | C35: 09:00 | D35: =SUM(Cargas!$F$464:$F$470) -> 2.4191 | E35: =Geracao!F134+Geracao!F135 -> 6.59566 | F35: =D35-E35 -> -4.17656 | G35: =Tarifa!$B$11 -> 0.6813 | H35: =K35*G35 -> 0 | I35: =Tarifa!$C$11 -> Fora Ponta | J35: =IF(I35="Ponta",Cadastro_Cargas!$F$16,0) -> 0 | K35: =MAX(0,D35-E35-J35) -> 0
A36: FAZ-001 | B36: 45659.417 | C36: 10:00 | D36: =SUM(Cargas!$F$478:$F$484) -> 2.52962 | E36: =Geracao!F138+Geracao!F139 -> 5.2388398 | F36: =D36-E36 -> -2.7092198 | G36: =Tarifa!$B$12 -> 0.6813 | H36: =K36*G36 -> 0 | I36: =Tarifa!$C$12 -> Fora Ponta | J36: =IF(I36="Ponta",Cadastro_Cargas!$F$16,0) -> 0 | K36: =MAX(0,D36-E36-J36) -> 0
A37: FAZ-001 | B37: 45659.458 | C37: 11:00 | D37: =SUM(Cargas!$F$492:$F$498) -> 2.556 | E37: =Geracao!F142+Geracao!F143 -> 2.4100939 | F37: =D37-E37 -> 0.14590614 | G37: =Tarifa!$B$13 -> 0.6813 | H37: =K37*G37 -> 0.099405851 | I37: =Tarifa!$C$13 -> Fora Ponta | J37: =IF(I37="Ponta",Cadastro_Cargas!$F$16,0) -> 0 | K37: =MAX(0,D37-E37-J37) -> 0.14590614
A38: FAZ-001 | B38: 45659.5 | C38: 12:00 | D38: =SUM(Cargas!$F$506:$F$512) -> 2.574 | E38: =Geracao!F146+Geracao!F147 -> 8.4259689 | F38: =D38-E38 -> -5.8519689 | G38: =Tarifa!$B$14 -> 0.6813 | H38: =K38*G38 -> 0 | I38: =Tarifa!$C$14 -> Fora Ponta | J38: =IF(I38="Ponta",Cadastro_Cargas!$F$16,0) -> 0 | K38: =MAX(0,D38-E38-J38) -> 0
A39: FAZ-001 | B39: 45659.542 | C39: 13:00 | D39: =SUM(Cargas!$F$520:$F$526) -> 2.4408 | E39: =Geracao!F150+Geracao!F151 -> 8.3922007 | F39: =D39-E39 -> -5.9514007 | G39: =Tarifa!$B$15 -> 0.6813 | H39: =K39*G39 -> 0 | I39: =Tarifa!$C$15 -> Fora Ponta | J39: =IF(I39="Ponta",Cadastro_Cargas!$F$16,0) -> 0 | K39: =MAX(0,D39-E39-J39) -> 0
A40: FAZ-001 | B40: 45659.583 | C40: 14:00 | D40: =SUM(Cargas!$F$534:$F$540) -> 2.56 | E40: =Geracao!F154+Geracao!F155 -> 2.3095968 | F40: =D40-E40 -> 0.25040318 | G40: =Tarifa!$B$16 -> 0.6813 | H40: =K40*G40 -> 0.17059969 | I40: =Tarifa!$C$16 -> Fora Ponta | J40: =IF(I40="Ponta",Cadastro_Cargas!$F$16,0) -> 0 | K40: =MAX(0,D40-E40-J40) -> 0.25040318
A41: FAZ-001 | B41: 45659.625 | C41: 15:00 | D41: =SUM(Cargas!$F$548:$F$554) -> 2.5538 | E41: =Geracao!F158+Geracao!F159 -> 6.5751055 | F41: =D41-E41 -> -4.0213055 | G41: =Tarifa!$B$17 -> 0.6813 | H41: =K41*G41 -> 0 | I41: =Tarifa!$C$17 -> Fora Ponta | J41: =IF(I41="Ponta",Cadastro_Cargas!$F$16,0) -> 0 | K41: =MAX(0,D41-E41-J41) -> 0
A42: FAZ-001 | B42: 45659.667 | C42: 16:00 | D42: =SUM(Cargas!$F$562:$F$568) -> 2.5017 | E42: =Geracao!F162+Geracao!F163 -> 5.8241305 | F42: =D42-E42 -> -3.3224305 | G42: =Tarifa!$B$18 -> 0.6813 | H42: =K42*G42 -> 0 | I42: =Tarifa!$C$18 -> Fora Ponta | J42: =IF(I42="Ponta",Cadastro_Cargas!$F$16,0) -> 0 | K42: =MAX(0,D42-E42-J42) -> 0
A43: FAZ-001 | B43: 45659.708 | C43: 17:00 | D43: =SUM(Cargas!$F$576:$F$582) -> 1.1436 | E43: =Geracao!F166+Geracao!F167 -> 2.4646368 | F43: =D43-E43 -> -1.3210368 | G43: =Tarifa!$B$19 -> 0.6813 | H43: =K43*G43 -> 0 | I43: =Tarifa!$C$19 -> Fora Ponta | J43: =IF(I43="Ponta",Cadastro_Cargas!$F$16,0) -> 0 | K43: =MAX(0,D43-E43-J43) -> 0
A44: FAZ-001 | B44: 45659.75 | C44: 18:00 | D44: =SUM(Cargas!$F$590:$F$596) -> 1.316 | E44: =Geracao!F170+Geracao!F171 -> 1.9879182 | F44: =D44-E44 -> -0.67191818 | G44: =Tarifa!$B$20 -> 1.1039 | H44: =K44*G44 -> 0 | I44: =Tarifa!$C$20 -> Ponta | J44: =IF(I44="Ponta",Cadastro_Cargas!$F$16,0) -> 0.875 | K44: =MAX(0,D44-E44-J44) -> 0
A45: FAZ-001 | B45: 45659.792 | C45: 19:00 | D45: =SUM(Cargas!$F$604:$F$610) -> 1.336 | E45: =Geracao!F174+Geracao!F175 -> 0.5886675 | F45: =D45-E45 -> 0.7473325 | G45: =Tarifa!$B$21 -> 1.1039 | H45: =K45*G45 -> 0 | I45: =Tarifa!$C$21 -> Ponta | J45: =IF(I45="Ponta",Cadastro_Cargas!$F$16,0) -> 0.875 | K45: =MAX(0,D45-E45-J45) -> 0
A46: FAZ-001 | B46: 45659.833 | C46: 20:00 | D46: =SUM(Cargas!$F$618:$F$624) -> 5.23632 | E46: =Geracao!F178+Geracao!F179 -> 1.012605 | F46: =D46-E46 -> 4.223715 | G46: =Tarifa!$B$22 -> 1.1039 | H46: =K46*G46 -> 3.6966465 | I46: =Tarifa!$C$22 -> Ponta | J46: =IF(I46="Ponta",Cadastro_Cargas!$F$16,0) -> 0.875 | K46: =MAX(0,D46-E46-J46) -> 3.348715
A47: FAZ-001 | B47: 45659.875 | C47: 21:00 | D47: =SUM(Cargas!$F$632:$F$638) -> 5.26696 | E47: =Geracao!F182+Geracao!F183 -> 1.0925475 | F47: =D47-E47 -> 4.1744125 | G47: =Tarifa!$B$23 -> 0.6813 | H47: =K47*G47 -> 2.8440272 | I47: =Tarifa!$C$23 -> Fora Ponta | J47: =IF(I47="Ponta",Cadastro_Cargas!$F$16,0) -> 0 | K47: =MAX(0,D47-E47-J47) -> 4.1744125
A48: FAZ-001 | B48: 45659.917 | C48: 22:00 | D48: =SUM(Cargas!$F$646:$F$652) -> 5.27518 | E48: =Geracao!F186+Geracao!F187 -> 0.770355 | F48: =D48-E48 -> 4.504825 | G48: =Tarifa!$B$24 -> 0.6813 | H48: =K48*G48 -> 3.0691373 | I48: =Tarifa!$C$24 -> Fora Ponta | J48: =IF(I48="Ponta",Cadastro_Cargas!$F$16,0) -> 0 | K48: =MAX(0,D48-E48-J48) -> 4.504825
A49: FAZ-001 | B49: 45659.958 | C49: 23:00 | D49: =SUM(Cargas!$F$660:$F$666) -> 4.75866 | E49: =Geracao!F190+Geracao!F191 -> 1.2815025 | F49: =D49-E49 -> 3.4771575 | G49: =Tarifa!$B$25 -> 0.6813 | H49: =K49*G49 -> 2.3689874 | I49: =Tarifa!$C$25 -> Fora Ponta | J49: =IF(I49="Ponta",Cadastro_Cargas!$F$16,0) -> 0 | K49: =MAX(0,D49-E49-J49) -> 3.4771575
A50: FAZ-001 | B50: 45660 | C50: 00:00 | D50: =SUM(Cargas!$F$674:$F$680) -> 4.91958 | E50: =Geracao!F194+Geracao!F195 -> 0.7291725 | F50: =D50-E50 -> 4.1904075 | G50: =Tarifa!$B$2 -> 0.6813 | H50: =K50*G50 -> 2.8549246 | I50: =Tarifa!$C$2 -> Fora Ponta | J50: =IF(I50="Ponta",Cadastro_Cargas!$F$16,0) -> 0 | K50: =MAX(0,D50-E50-J50) -> 4.1904075
A51: FAZ-001 | B51: 45660.042 | C51: 01:00 | D51: =SUM(Cargas!$F$688:$F$694) -> 5.08066 | E51: =Geracao!F198+Geracao!F199 -> 0.770355 | F51: =D51-E51 -> 4.310305 | G51: =Tarifa!$B$3 -> 0.6813 | H51: =K51*G51 -> 2.9366108 | I51: =Tarifa!$C$3 -> Fora Ponta | J51: =IF(I51="Ponta",Cadastro_Cargas!$F$16,0) -> 0 | K51: =MAX(0,D51-E51-J51) -> 4.310305
A52: FAZ-001 | B52: 45660.083 | C52: 02:00 | D52: =SUM(Cargas!$F$702:$F$708) -> 4.84954 | E52: =Geracao!F202+Geracao!F203 -> 0.983535 | F52: =D52-E52 -> 3.866005 | G52: =Tarifa!$B$4 -> 0.6813 | H52: =K52*G52 -> 2.6339092 | I52: =Tarifa!$C$4 -> Fora Ponta | J52: =IF(I52="Ponta",Cadastro_Cargas!$F$16,0) -> 0 | K52: =MAX(0,D52-E52-J52) -> 3.866005
A53: FAZ-001 | B53: 45660.125 | C53: 03:00 | D53: =SUM(Cargas!$F$716:$F$722) -> 5.27088 | E53: =Geracao!F206+Geracao!F207 -> 0.7873125 | F53: =D53-E53 -> 4.4835675 | G53: =Tarifa!$B$5 -> 0.6813 | H53: =K53*G53 -> 3.0546545 | I53: =Tarifa!$C$5 -> Fora Ponta | J53: =IF(I53="Ponta",Cadastro_Cargas!$F$16,0) -> 0 | K53: =MAX(0,D53-E53-J53) -> 4.4835675
A54: FAZ-001 | B54: 45660.167 | C54: 04:00 | D54: =SUM(Cargas!$F$730:$F$736) -> 5.25676 | E54: =Geracao!F210+Geracao!F211 -> 0.8212275 | F54: =D54-E54 -> 4.4355325 | G54: =Tarifa!$B$6 -> 0.6813 | H54: =K54*G54 -> 3.0219283 | I54: =Tarifa!$C$6 -> Fora Ponta | J54: =IF(I54="Ponta",Cadastro_Cargas!$F$16,0) -> 0 | K54: =MAX(0,D54-E54-J54) -> 4.4355325
A55: FAZ-001 | B55: 45660.208 | C55: 05:00 | D55: =SUM(Cargas!$F$744:$F$750) -> 1.25172 | E55: =Geracao!F214+Geracao!F215 -> 0.93024 | F55: =D55-E55 -> 0.32148 | G55: =Tarifa!$B$7 -> 0.6813 | H55: =K55*G55 -> 0.21902432 | I55: =Tarifa!$C$7 -> Fora Ponta | J55: =IF(I55="Ponta",Cadastro_Cargas!$F$16,0) -> 0 | K55: =MAX(0,D55-E55-J55) -> 0.32148
A56: FAZ-001 | B56: 45660.25 | C56: 06:00 | D56: =SUM(Cargas!$F$758:$F$764) -> 1.1968 | E56: =Geracao!F218+Geracao!F219 -> 2.3823452 | F56: =D56-E56 -> -1.1855452 | G56: =Tarifa!$B$8 -> 0.6813 | H56: =K56*G56 -> 0 | I56: =Tarifa!$C$8 -> Fora Ponta | J56: =IF(I56="Ponta",Cadastro_Cargas!$F$16,0) -> 0 | K56: =MAX(0,D56-E56-J56) -> 0
A57: FAZ-001 | B57: 45660.292 | C57: 07:00 | D57: =SUM(Cargas!$F$772:$F$778) -> 1.1336 | E57: =Geracao!F222+Geracao!F223 -> 1.3837614 | F57: =D57-E57 -> -0.25016136 | G57: =Tarifa!$B$9 -> 0.6813 | H57: =K57*G57 -> 0 | I57: =Tarifa!$C$9 -> Fora Ponta | J57: =IF(I57="Ponta",Cadastro_Cargas!$F$16,0) -> 0 | K57: =MAX(0,D57-E57-J57) -> 0
A58: FAZ-001 | B58: 45660.333 | C58: 08:00 | D58: =SUM(Cargas!$F$786:$F$792) -> 1.586 | E58: =Geracao!F226+Geracao!F227 -> 5.4490834 | F58: =D58-E58 -> -3.8630834 | G58: =Tarifa!$B$10 -> 0.6813 | H58: =K58*G58 -> 0 | I58: =Tarifa!$C$10 -> Fora Ponta | J58: =IF(I58="Ponta",Cadastro_Cargas!$F$16,0) -> 0 | K58: =MAX(0,D58-E58-J58) -> 0
A59: FAZ-001 | B59: 45660.375 | C59: 09:00 | D59: =SUM(Cargas!$F$800:$F$806) -> 2.42862 | E59: =Geracao!F230+Geracao!F231 -> 3.4561 | F59: =D59-E59 -> -1.02748 | G59: =Tarifa!$B$11 -> 0.6813 | H59: =K59*G59 -> 0 | I59: =Tarifa!$C$11 -> Fora Ponta | J59: =IF(I59="Ponta",Cadastro_Cargas!$F$16,0) -> 0 | K59: =MAX(0,D59-E59-J59) -> 0
A60: FAZ-001 | B60: 45660.417 | C60: 10:00 | D60: =SUM(Cargas!$F$814:$F$820) -> 2.46084 | E60: =Geracao!F234+Geracao!F235 -> 7.9979205 | F60: =D60-E60 -> -5.5370805 | G60: =Tarifa!$B$12 -> 0.6813 | H60: =K60*G60 -> 0 | I60: =Tarifa!$C$12 -> Fora Ponta | J60: =IF(I60="Ponta",Cadastro_Cargas!$F$16,0) -> 0 | K60: =MAX(0,D60-E60-J60) -> 0
A61: FAZ-001 | B61: 45660.458 | C61: 11:00 | D61: =SUM(Cargas!$F$828:$F$834) -> 2.566 | E61: =Geracao!F238+Geracao!F239 -> 5.1736525 | F61: =D61-E61 -> -2.6076525 | G61: =Tarifa!$B$13 -> 0.6813 | H61: =K61*G61 -> 0 | I61: =Tarifa!$C$13 -> Fora Ponta | J61: =IF(I61="Ponta",Cadastro_Cargas!$F$16,0) -> 0 | K61: =MAX(0,D61-E61-J61) -> 0
A62: FAZ-001 | B62: 45660.5 | C62: 12:00 | D62: =SUM(Cargas!$F$842:$F$848) -> 2.4812 | E62: =Geracao!F242+Geracao!F243 -> 8.7143932 | F62: =D62-E62 -> -6.2331932 | G62: =Tarifa!$B$14 -> 0.6813 | H62: =K62*G62 -> 0 | I62: =Tarifa!$C$14 -> Fora Ponta | J62: =IF(I62="Ponta",Cadastro_Cargas!$F$16,0) -> 0 | K62: =MAX(0,D62-E62-J62) -> 0
A63: FAZ-001 | B63: 45660.542 | C63: 13:00 | D63: =SUM(Cargas!$F$856:$F$862) -> 2.568 | E63: =Geracao!F246+Geracao!F247 -> 7.9160693 | F63: =D63-E63 -> -5.3480693 | G63: =Tarifa!$B$15 -> 0.6813 | H63: =K63*G63 -> 0 | I63: =Tarifa!$C$15 -> Fora Ponta | J63: =IF(I63="Ponta",Cadastro_Cargas!$F$16,0) -> 0 | K63: =MAX(0,D63-E63-J63) -> 0
A64: FAZ-001 | B64: 45660.583 | C64: 14:00 | D64: =SUM(Cargas!$F$870:$F$876) -> 2.57 | E64: =Geracao!F250+Geracao!F251 -> 8.0199432 | F64: =D64-E64 -> -5.4499432 | G64: =Tarifa!$B$16 -> 0.6813 | H64: =K64*G64 -> 0 | I64: =Tarifa!$C$16 -> Fora Ponta | J64: =IF(I64="Ponta",Cadastro_Cargas!$F$16,0) -> 0 | K64: =MAX(0,D64-E64-J64) -> 0
A65: FAZ-001 | B65: 45660.625 | C65: 15:00 | D65: =SUM(Cargas!$F$884:$F$890) -> 2.4388 | E65: =Geracao!F254+Geracao!F255 -> 7.1759589 | F65: =D65-E65 -> -4.7371589 | G65: =Tarifa!$B$17 -> 0.6813 | H65: =K65*G65 -> 0 | I65: =Tarifa!$C$17 -> Fora Ponta | J65: =IF(I65="Ponta",Cadastro_Cargas!$F$16,0) -> 0 | K65: =MAX(0,D65-E65-J65) -> 0
A66: FAZ-001 | B66: 45660.667 | C66: 16:00 | D66: =SUM(Cargas!$F$898:$F$904) -> 2.52962 | E66: =Geracao!F258+Geracao!F259 -> 3.8010493 | F66: =D66-E66 -> -1.2714293 | G66: =Tarifa!$B$18 -> 0.6813 | H66: =K66*G66 -> 0 | I66: =Tarifa!$C$18 -> Fora Ponta | J66: =IF(I66="Ponta",Cadastro_Cargas!$F$16,0) -> 0 | K66: =MAX(0,D66-E66-J66) -> 0
A67: FAZ-001 | B67: 45660.708 | C67: 17:00 | D67: =SUM(Cargas!$F$912:$F$918) -> 1.1864 | E67: =Geracao!F262+Geracao!F263 -> 3.8504536 | F67: =D67-E67 -> -2.6640536 | G67: =Tarifa!$B$19 -> 0.6813 | H67: =K67*G67 -> 0 | I67: =Tarifa!$C$19 -> Fora Ponta | J67: =IF(I67="Ponta",Cadastro_Cargas!$F$16,0) -> 0 | K67: =MAX(0,D67-E67-J67) -> 0
A68: FAZ-001 | B68: 45660.75 | C68: 18:00 | D68: =SUM(Cargas!$F$926:$F$932) -> 1.336 | E68: =Geracao!F266+Geracao!F267 -> 2.5679234 | F68: =D68-E68 -> -1.2319234 | G68: =Tarifa!$B$20 -> 1.1039 | H68: =K68*G68 -> 0 | I68: =Tarifa!$C$20 -> Ponta | J68: =IF(I68="Ponta",Cadastro_Cargas!$F$16,0) -> 0.875 | K68: =MAX(0,D68-E68-J68) -> 0
A69: FAZ-001 | B69: 45660.792 | C69: 19:00 | D69: =SUM(Cargas!$F$940:$F$946) -> 1.318 | E69: =Geracao!F270+Geracao!F271 -> 0.7291725 | F69: =D69-E69 -> 0.5888275 | G69: =Tarifa!$B$21 -> 1.1039 | H69: =K69*G69 -> 0 | I69: =Tarifa!$C$21 -> Ponta | J69: =IF(I69="Ponta",Cadastro_Cargas!$F$16,0) -> 0.875 | K69: =MAX(0,D69-E69-J69) -> 0
A70: FAZ-001 | B70: 45660.833 | C70: 20:00 | D70: =SUM(Cargas!$F$954:$F$960) -> 5.28456 | E70: =Geracao!F274+Geracao!F275 -> 0.7970025 | F70: =D70-E70 -> 4.4875575 | G70: =Tarifa!$B$22 -> 1.1039 | H70: =K70*G70 -> 3.9879022 | I70: =Tarifa!$C$22 -> Ponta | J70: =IF(I70="Ponta",Cadastro_Cargas!$F$16,0) -> 0.875 | K70: =MAX(0,D70-E70-J70) -> 3.6125575
A71: FAZ-001 | B71: 45660.875 | C71: 21:00 | D71: =SUM(Cargas!$F$968:$F$974) -> 5.08 | E71: =Geracao!F278+Geracao!F279 -> 0.8212275 | F71: =D71-E71 -> 4.2587725 | G71: =Tarifa!$B$23 -> 0.6813 | H71: =K71*G71 -> 2.9015017 | I71: =Tarifa!$C$23 -> Fora Ponta | J71: =IF(I71="Ponta",Cadastro_Cargas!$F$16,0) -> 0 | K71: =MAX(0,D71-E71-J71) -> 4.2587725
A72: FAZ-001 | B72: 45660.917 | C72: 22:00 | D72: =SUM(Cargas!$F$982:$F$988) -> 5.26148 | E72: =Geracao!F282+Geracao!F283 -> 1.1119275 | F72: =D72-E72 -> 4.1495525 | G72: =Tarifa!$B$24 -> 0.6813 | H72: =K72*G72 -> 2.8270901 | I72: =Tarifa!$C$24 -> Fora Ponta | J72: =IF(I72="Ponta",Cadastro_Cargas!$F$16,0) -> 0 | K72: =MAX(0,D72-E72-J72) -> 4.1495525
A73: FAZ-001 | B73: 45660.958 | C73: 23:00 | D73: =SUM(Cargas!$F$996:$F$1002) -> 5.256 | E73: =Geracao!F286+Geracao!F287 -> 0.74613 | F73: =D73-E73 -> 4.50987 | G73: =Tarifa!$B$25 -> 0.6813 | H73: =K73*G73 -> 3.0725744 | I73: =Tarifa!$C$25 -> Fora Ponta | J73: =IF(I73="Ponta",Cadastro_Cargas!$F$16,0) -> 0 | K73: =MAX(0,D73-E73-J73) -> 4.50987
A74: FAZ-001 | B74: 45661 | C74: 00:00 | D74: =SUM(Cargas!$F$1010:$F$1016) -> 5.21376 | E74: =Geracao!F290+Geracao!F291 -> 0.7340175 | F74: =D74-E74 -> 4.4797425 | G74: =Tarifa!$B$2 -> 0.6813 | H74: =K74*G74 -> 3.0520486 | I74: =Tarifa!$C$2 -> Fora Ponta | J74: =IF(I74="Ponta",Cadastro_Cargas!$F$16,0) -> 0 | K74: =MAX(0,D74-E74-J74) -> 4.4797425
A75: FAZ-001 | B75: 45661.042 | C75: 01:00 | D75: =SUM(Cargas!$F$1024:$F$1030) -> 5.20982 | E75: =Geracao!F294+Geracao!F295 -> 0.7727775 | F75: =D75-E75 -> 4.4370425 | G75: =Tarifa!$B$3 -> 0.6813 | H75: =K75*G75 -> 3.0229571 | I75: =Tarifa!$C$3 -> Fora Ponta | J75: =IF(I75="Ponta",Cadastro_Cargas!$F$16,0) -> 0 | K75: =MAX(0,D75-E75-J75) -> 4.4370425
A76: FAZ-001 | B76: 45661.083 | C76: 02:00 | D76: =SUM(Cargas!$F$1038:$F$1044) -> 5.26308 | E76: =Geracao!F298+Geracao!F299 -> 0.7679325 | F76: =D76-E76 -> 4.4951475 | G76: =Tarifa!$B$4 -> 0.6813 | H76: =K76*G76 -> 3.062544 | I76: =Tarifa!$C$4 -> Fora Ponta | J76: =IF(I76="Ponta",Cadastro_Cargas!$F$16,0) -> 0 | K76: =MAX(0,D76-E76-J76) -> 4.4951475
A77: FAZ-001 | B77: 45661.125 | C77: 03:00 | D77: =SUM(Cargas!$F$1052:$F$1058) -> 5.06052 | E77: =Geracao!F302+Geracao!F303 -> 1.0295625 | F77: =D77-E77 -> 4.0309575 | G77: =Tarifa!$B$5 -> 0.6813 | H77: =K77*G77 -> 2.7462913 | I77: =Tarifa!$C$5 -> Fora Ponta | J77: =IF(I77="Ponta",Cadastro_Cargas!$F$16,0) -> 0 | K77: =MAX(0,D77-E77-J77) -> 4.0309575
A78: FAZ-001 | B78: 45661.167 | C78: 04:00 | D78: =SUM(Cargas!$F$1066:$F$1072) -> 5.26234 | E78: =Geracao!F306+Geracao!F307 -> 0.98838 | F78: =D78-E78 -> 4.27396 | G78: =Tarifa!$B$6 -> 0.6813 | H78: =K78*G78 -> 2.9118489 | I78: =Tarifa!$C$6 -> Fora Ponta | J78: =IF(I78="Ponta",Cadastro_Cargas!$F$16,0) -> 0 | K78: =MAX(0,D78-E78-J78) -> 4.27396
A79: FAZ-001 | B79: 45661.208 | C79: 05:00 | D79: =SUM(Cargas!$F$1080:$F$1086) -> 1.28996 | E79: =Geracao!F310+Geracao!F311 -> 0.9568875 | F79: =D79-E79 -> 0.3330725 | G79: =Tarifa!$B$7 -> 0.6813 | H79: =K79*G79 -> 0.22692229 | I79: =Tarifa!$C$7 -> Fora Ponta | J79: =IF(I79="Ponta",Cadastro_Cargas!$F$16,0) -> 0 | K79: =MAX(0,D79-E79-J79) -> 0.3330725
A80: FAZ-001 | B80: 45661.25 | C80: 06:00 | D80: =SUM(Cargas!$F$1094:$F$1100) -> 1.2128 | E80: =Geracao!F314+Geracao!F315 -> 1.661468 | F80: =D80-E80 -> -0.44866795 | G80: =Tarifa!$B$8 -> 0.6813 | H80: =K80*G80 -> 0 | I80: =Tarifa!$C$8 -> Fora Ponta | J80: =IF(I80="Ponta",Cadastro_Cargas!$F$16,0) -> 0 | K80: =MAX(0,D80-E80-J80) -> 0
A81: FAZ-001 | B81: 45661.292 | C81: 07:00 | D81: =SUM(Cargas!$F$1108:$F$1114) -> 1.2236 | E81: =Geracao!F318+Geracao!F319 -> 2.7381591 | F81: =D81-E81 -> -1.5145591 | G81: =Tarifa!$B$9 -> 0.6813 | H81: =K81*G81 -> 0 | I81: =Tarifa!$C$9 -> Fora Ponta | J81: =IF(I81="Ponta",Cadastro_Cargas!$F$16,0) -> 0 | K81: =MAX(0,D81-E81-J81) -> 0
A82: FAZ-001 | B82: 45661.333 | C82: 08:00 | D82: =SUM(Cargas!$F$1122:$F$1128) -> 1.7378 | E82: =Geracao!F322+Geracao!F323 -> 5.376702 | F82: =D82-E82 -> -3.638902 | G82: =Tarifa!$B$10 -> 0.6813 | H82: =K82*G82 -> 0 | I82: =Tarifa!$C$10 -> Fora Ponta | J82: =IF(I82="Ponta",Cadastro_Cargas!$F$16,0) -> 0 | K82: =MAX(0,D82-E82-J82) -> 0
A83: FAZ-001 | B83: 45661.375 | C83: 09:00 | D83: =SUM(Cargas!$F$1136:$F$1142) -> 2.19852 | E83: =Geracao!F326+Geracao!F327 -> 6.729705 | F83: =D83-E83 -> -4.531185 | G83: =Tarifa!$B$11 -> 0.6813 | H83: =K83*G83 -> 0 | I83: =Tarifa!$C$11 -> Fora Ponta | J83: =IF(I83="Ponta",Cadastro_Cargas!$F$16,0) -> 0 | K83: =MAX(0,D83-E83-J83) -> 0
A84: FAZ-001 | B84: 45661.417 | C84: 10:00 | D84: =SUM(Cargas!$F$1150:$F$1156) -> 2.37778 | E84: =Geracao!F330+Geracao!F331 -> 7.3020757 | F84: =D84-E84 -> -4.9242957 | G84: =Tarifa!$B$12 -> 0.6813 | H84: =K84*G84 -> 0 | I84: =Tarifa!$C$12 -> Fora Ponta | J84: =IF(I84="Ponta",Cadastro_Cargas!$F$16,0) -> 0 | K84: =MAX(0,D84-E84-J84) -> 0
A85: FAZ-001 | B85: 45661.458 | C85: 11:00 | D85: =SUM(Cargas!$F$1164:$F$1170) -> 2.5563 | E85: =Geracao!F334+Geracao!F335 -> 8.3024214 | F85: =D85-E85 -> -5.7461214 | G85: =Tarifa!$B$13 -> 0.6813 | H85: =K85*G85 -> 0 | I85: =Tarifa!$C$13 -> Fora Ponta | J85: =IF(I85="Ponta",Cadastro_Cargas!$F$16,0) -> 0 | K85: =MAX(0,D85-E85-J85) -> 0
A86: FAZ-001 | B86: 45661.5 | C86: 12:00 | D86: =SUM(Cargas!$F$1178:$F$1184) -> 2.574 | E86: =Geracao!F338+Geracao!F339 -> 4.4017559 | F86: =D86-E86 -> -1.8277559 | G86: =Tarifa!$B$14 -> 0.6813 | H86: =K86*G86 -> 0 | I86: =Tarifa!$C$14 -> Fora Ponta | J86: =IF(I86="Ponta",Cadastro_Cargas!$F$16,0) -> 0 | K86: =MAX(0,D86-E86-J86) -> 0
A87: FAZ-001 | B87: 45661.542 | C87: 13:00 | D87: =SUM(Cargas!$F$1192:$F$1198) -> 2.2912 | E87: =Geracao!F342+Geracao!F343 -> 2.1541164 | F87: =D87-E87 -> 0.13708364 | G87: =Tarifa!$B$15 -> 0.6813 | H87: =K87*G87 -> 0.093395081 | I87: =Tarifa!$C$15 -> Fora Ponta | J87: =IF(I87="Ponta",Cadastro_Cargas!$F$16,0) -> 0 | K87: =MAX(0,D87-E87-J87) -> 0.13708364
A88: FAZ-001 | B88: 45661.583 | C88: 14:00 | D88: =SUM(Cargas!$F$1206:$F$1212) -> 2.4672 | E88: =Geracao!F346+Geracao!F347 -> 7.3738698 | F88: =D88-E88 -> -4.9066698 | G88: =Tarifa!$B$16 -> 0.6813 | H88: =K88*G88 -> 0 | I88: =Tarifa!$C$16 -> Fora Ponta | J88: =IF(I88="Ponta",Cadastro_Cargas!$F$16,0) -> 0 | K88: =MAX(0,D88-E88-J88) -> 0
A89: FAZ-001 | B89: 45661.625 | C89: 15:00 | D89: =SUM(Cargas!$F$1220:$F$1226) -> 2.574 | E89: =Geracao!F350+Geracao!F351 -> 6.9591084 | F89: =D89-E89 -> -4.3851084 | G89: =Tarifa!$B$17 -> 0.6813 | H89: =K89*G89 -> 0 | I89: =Tarifa!$C$17 -> Fora Ponta | J89: =IF(I89="Ponta",Cadastro_Cargas!$F$16,0) -> 0 | K89: =MAX(0,D89-E89-J89) -> 0
A90: FAZ-001 | B90: 45661.667 | C90: 16:00 | D90: =SUM(Cargas!$F$1234:$F$1240) -> 2.5331 | E90: =Geracao!F354+Geracao!F355 -> 4.6605964 | F90: =D90-E90 -> -2.1274964 | G90: =Tarifa!$B$18 -> 0.6813 | H90: =K90*G90 -> 0 | I90: =Tarifa!$C$18 -> Fora Ponta | J90: =IF(I90="Ponta",Cadastro_Cargas!$F$16,0) -> 0 | K90: =MAX(0,D90-E90-J90) -> 0
A91: FAZ-001 | B91: 45661.708 | C91: 17:00 | D91: =SUM(Cargas!$F$1248:$F$1254) -> 1.2018 | E91: =Geracao!F358+Geracao!F359 -> 2.7521802 | F91: =D91-E91 -> -1.5503802 | G91: =Tarifa!$B$19 -> 0.6813 | H91: =K91*G91 -> 0 | I91: =Tarifa!$C$19 -> Fora Ponta | J91: =IF(I91="Ponta",Cadastro_Cargas!$F$16,0) -> 0 | K91: =MAX(0,D91-E91-J91) -> 0
A92: FAZ-001 | B92: 45661.75 | C92: 18:00 | D92: =SUM(Cargas!$F$1262:$F$1268) -> 1.31 | E92: =Geracao!F362+Geracao!F363 -> 2.347843 | F92: =D92-E92 -> -1.037843 | G92: =Tarifa!$B$20 -> 1.1039 | H92: =K92*G92 -> 0 | I92: =Tarifa!$C$20 -> Ponta | J92: =IF(I92="Ponta",Cadastro_Cargas!$F$16,0) -> 0.875 | K92: =MAX(0,D92-E92-J92) -> 0
A93: FAZ-001 | B93: 45661.792 | C93: 19:00 | D93: =SUM(Cargas!$F$1276:$F$1282) -> 1.336 | E93: =Geracao!F366+Geracao!F367 -> 1.031985 | F93: =D93-E93 -> 0.304015 | G93: =Tarifa!$B$21 -> 1.1039 | H93: =K93*G93 -> 0 | I93: =Tarifa!$C$21 -> Ponta | J93: =IF(I93="Ponta",Cadastro_Cargas!$F$16,0) -> 0.875 | K93: =MAX(0,D93-E93-J93) -> 0
A94: FAZ-001 | B94: 45661.833 | C94: 20:00 | D94: =SUM(Cargas!$F$1290:$F$1296) -> 4.736 | E94: =Geracao!F370+Geracao!F371 -> 1.2136725 | F94: =D94-E94 -> 3.5223275 | G94: =Tarifa!$B$22 -> 1.1039 | H94: =K94*G94 -> 2.9223848 | I94: =Tarifa!$C$22 -> Ponta | J94: =IF(I94="Ponta",Cadastro_Cargas!$F$16,0) -> 0.875 | K94: =MAX(0,D94-E94-J94) -> 2.6473275
A95: FAZ-001 | B95: 45661.875 | C95: 21:00 | D95: =SUM(Cargas!$F$1304:$F$1310) -> 5.22682 | E95: =Geracao!F374+Geracao!F375 -> 0.9326625 | F95: =D95-E95 -> 4.2941575 | G95: =Tarifa!$B$23 -> 0.6813 | H95: =K95*G95 -> 2.9256095 | I95: =Tarifa!$C$23 -> Fora Ponta | J95: =IF(I95="Ponta",Cadastro_Cargas!$F$16,0) -> 0 | K95: =MAX(0,D95-E95-J95) -> 4.2941575
A96: FAZ-001 | B96: 45661.917 | C96: 22:00 | D96: =SUM(Cargas!$F$1318:$F$1324) -> 5.2149 | E96: =Geracao!F378+Geracao!F379 -> 0.8115375 | F96: =D96-E96 -> 4.4033625 | G96: =Tarifa!$B$24 -> 0.6813 | H96: =K96*G96 -> 3.0000109 | I96: =Tarifa!$C$24 -> Fora Ponta | J96: =IF(I96="Ponta",Cadastro_Cargas!$F$16,0) -> 0 | K96: =MAX(0,D96-E96-J96) -> 4.4033625
A97: FAZ-001 | B97: 45661.958 | C97: 23:00 | D97: =SUM(Cargas!$F$1332:$F$1338) -> 5.0697 | E97: =Geracao!F382+Geracao!F383 -> 0.82365 | F97: =D97-E97 -> 4.24605 | G97: =Tarifa!$B$25 -> 0.6813 | H97: =K97*G97 -> 2.8928339 | I97: =Tarifa!$C$25 -> Fora Ponta | J97: =IF(I97="Ponta",Cadastro_Cargas!$F$16,0) -> 0 | K97: =MAX(0,D97-E97-J97) -> 4.24605
A98: FAZ-001 | B98: 45662 | C98: 00:00 | D98: =SUM(Cargas!$F$1346:$F$1352) -> 5.19566 | E98: =Geracao!F386+Geracao!F387 -> 1.1070825 | F98: =D98-E98 -> 4.0885775 | G98: =Tarifa!$B$2 -> 0.6813 | H98: =K98*G98 -> 2.7855479 | I98: =Tarifa!$C$2 -> Fora Ponta | J98: =IF(I98="Ponta",Cadastro_Cargas!$F$16,0) -> 0 | K98: =MAX(0,D98-E98-J98) -> 4.0885775
A99: FAZ-001 | B99: 45662.042 | C99: 01:00 | D99: =SUM(Cargas!$F$1360:$F$1366) -> 5.21764 | E99: =Geracao!F390+Geracao!F391 -> 1.10466 | F99: =D99-E99 -> 4.11298 | G99: =Tarifa!$B$3 -> 0.6813 | H99: =K99*G99 -> 2.8021733 | I99: =Tarifa!$C$3 -> Fora Ponta | J99: =IF(I99="Ponta",Cadastro_Cargas!$F$16,0) -> 0 | K99: =MAX(0,D99-E99-J99) -> 4.11298
A100: FAZ-001 | B100: 45662.083 | C100: 02:00 | D100: =SUM(Cargas!$F$1374:$F$1380) -> 5.056 | E100: =Geracao!F394+Geracao!F395 -> 0.741285 | F100: =D100-E100 -> 4.314715 | G100: =Tarifa!$B$4 -> 0.6813 | H100: =K100*G100 -> 2.9396153 | I100: =Tarifa!$C$4 -> Fora Ponta | J100: =IF(I100="Ponta",Cadastro_Cargas!$F$16,0) -> 0 | K100: =MAX(0,D100-E100-J100) -> 4.314715
...

Sheet Resumo_Mensal
A1: Fazenda | B1: Consumo_kWh | C1: Geração_kWh | D1: Saldo_Rede_kWh | E1: Custo_Total_R$ | F1: Custo_Ponta_R$ | G1: Custo_Fora_Ponta_R$ | H1: Bateria_Descarga_kWh | I1: Saldo_Liquido_kWh
A2: Fazenda Boa Vista | B2: =SUM(Consumo_Fatura!D2:D745) -> 2315.1975 | C2: =SUM(Consumo_Fatura!E2:E745) -> 2244.0297 | D2: =B2-C2 -> 71.167867 | E2: =SUM(Consumo_Fatura!H2:H745) -> 832.72797 | F2: =SUMPRODUCT((Consumo_Fatura!I2:I745="Ponta")*Consumo_Fatura!H2:H745) -> 120.60309 | G2: =E2-F2 -> 712.12488 | H2: =SUM(Consumo_Fatura!J2:J745) -> 81.375 | I2: =SUM(Consumo_Fatura!K2:K745) -> 1154.496
A3: Fazenda São Pedro | B3: =SUM(Consumo_Fatura!D746:D1489) -> 10091.672 | C3: =SUM(Consumo_Fatura!E746:E1489) -> 8752.8011 | D3: =B3-C3 -> 1338.8706 | E3: =SUM(Consumo_Fatura!H746:H1489) -> 3823.2389 | F3: =SUMPRODUCT((Consumo_Fatura!I746:I1489="Ponta")*Consumo_Fatura!H746:H1489) -> 778.41319 | G3: =E3-F3 -> 3044.8257 | H3: =SUM(Consumo_Fatura!J746:J1489) -> 325.5 | I3: =SUM(Consumo_Fatura!K746:K1489) -> 5174.2892
